{"response": {"version": "0.1", "termsofService": "http://www.wunderground.com/weather/api/d/terms.html", "features": {"history": 1}}, "history": {"observations": [{"wspdm": "22.2", "wspdi": "13.8", "snow": "0", "date": {"pretty": "12:53 AM CDT on April 25, 2015", "year": "2015", "mday": "25", "min": "53", "hour": "00", "tzname": "America/Chicago", "mon": "04"}, "precipi": "0.00", "wgusti": "-9999.0", "heatindexi": "-9999", "vism": "16.1", "precipm": "0.0", "dewpti": "39.9", "fog": "0", "heatindexm": "-9999", "wgustm": "-9999.0", "icon": "cloudy", "visi": "10.0", "windchillm": "3.6", "conds": "Overcast", "windchilli": "38.5", "pressurei": "29.88", "tempm": "7.2", "hum": "82", "tempi": "45.0", "thunder": "0", "dewptm": "4.4", "wdire": "East", "utcdate": {"pretty": "5:53 AM GMT on April 25, 2015", "year": "2015", "mday": "25", "min": "53", "hour": "05", "tzname": "UTC", "mon": "04"}, "pressurem": "1011.7", "wdird": "80", "tornado": "0", "metar": "METAR KMDW 250553Z 08012KT 10SM BKN055 OVC090 07/04 A2987 RMK AO2 RAB22E51 SLP117 P0000 60029 T00720044 10106 20056 401560017 58019", "rain": "0", "hail": "0"}, {"wspdm": "24.1", "wspdi": "15.0", "snow": "0", "date": {"pretty": "1:53 AM CDT on April 25, 2015", "year": "2015", "mday": "25", "min": "53", "hour": "01", "tzname": "America/Chicago", "mon": "04"}, "precipi": "0.00", "wgusti": "-9999.0", "heatindexi": "-9999", "vism": "16.1", "precipm": "0.0", "dewpti": "39.9", "fog": "0", "heatindexm": "-9999", "wgustm": "-9999.0", "icon": "cloudy", "visi": "10.0", "windchillm": "3.5", "conds": "Overcast", "windchilli": "38.2", "pressurei": "29.88", "tempm": "7.2", "hum": "82", "tempi": "45.0", "thunder": "0", "dewptm": "4.4", "wdire": "ENE", "utcdate": {"pretty": "6:53 AM GMT on April 25, 2015", "year": "2015", "mday": "25", "min": "53", "hour": "06", "tzname": "UTC", "mon": "04"}, "pressurem": "1011.7", "wdird": "70", "tornado": "0", "metar": "METAR KMDW 250653Z 07013KT 10SM BKN055 OVC090 07/04 A2987 RMK AO2 RAB0559E12 SLP117 P0000 T00720044", "rain": "0", "hail": "0"}, {"wspdm": "24.1", "wspdi": "15.0", "snow": "0", "date": {"pretty": "2:53 AM CDT on April 25, 2015", "year": "2015", "mday": "25", "min": "53", "hour": "02", "tzname": "America/Chicago", "mon": "04"}, "precipi": "-9999.00", "wgusti": "-9999.0", "heatindexi": "-9999", "vism": "16.1", "precipm": "-9999.00", "dewpti": "39.9", "fog": "0", "heatindexm": "-9999", "wgustm": "-9999.0", "icon": "cloudy", "visi": "10.0", "windchillm": "4.2", "conds": "Overcast", "windchilli": "39.6", "pressurei": "29.83", "tempm": "7.8", "hum": "79", "tempi": "46.0", "thunder": "0", "dewptm": "4.4", "wdire": "ENE", "utcdate": {"pretty": "7:53 AM GMT on April 25, 2015", "year": "2015", "mday": "25", "min": "53", "hour": "07", "tzname": "UTC", "mon": "04"}, "pressurem": "1009.9", "wdird": "70", "tornado": "0", "metar": "METAR KMDW 250753Z 07013KT 10SM BKN060 BKN090 OVC250 08/04 A2982 RMK AO2 SLP099 T00780044", "rain": "0", "hail": "0"}, {"wspdm": "25.9", "wspdi": "16.1", "snow": "0", "date": {"pretty": "3:53 AM CDT on April 25, 2015", "year": "2015", "mday": "25", "min": "53", "hour": "03", "tzname": "America/Chicago", "mon": "04"}, "precipi": "-9999.00", "wgusti": "24.2", "heatindexi": "-9999", "vism": "16.1", "precipm": "-9999.00", "dewpti": "39.9", "fog": "0", "heatindexm": "-9999", "wgustm": "38.9", "icon": "cloudy", "visi": "10.0", "windchillm": "4.1", "conds": "Overcast", "windchilli": "39.3", "pressurei": "29.82", "tempm": "7.8", "hum": "79", "tempi": "46.0", "thunder": "0", "dewptm": "4.4", "wdire": "East", "utcdate": {"pretty": "8:53 AM GMT on April 25, 2015", "year": "2015", "mday": "25", "min": "53", "hour": "08", "tzname": "UTC", "mon": "04"}, "pressurem": "1009.7", "wdird": "90", "tornado": "0", "metar": "METAR KMDW 250853Z 09014G21KT 10SM BKN055 BKN090 OVC250 08/04 A2981 RMK AO2 SLP097 60000 T00780044 58020", "rain": "0", "hail": "0"}, {"wspdm": "29.6", "wspdi": "18.4", "snow": "0", "date": {"pretty": "4:53 AM CDT on April 25, 2015", "year": "2015", "mday": "25", "min": "53", "hour": "04", "tzname": "America/Chicago", "mon": "04"}, "precipi": "-9999.00", "wgusti": "-9999.0", "heatindexi": "-9999", "vism": "16.1", "precipm": "-9999.00", "dewpti": "39.9", "fog": "0", "heatindexm": "-9999", "wgustm": "-9999.0", "icon": "cloudy", "visi": "10.0", "windchillm": "3.8", "conds": "Overcast", "windchilli": "38.8", "pressurei": "29.80", "tempm": "7.8", "hum": "79", "tempi": "46.0", "thunder": "0", "dewptm": "4.4", "wdire": "East", "utcdate": {"pretty": "9:53 AM GMT on April 25, 2015", "year": "2015", "mday": "25", "min": "53", "hour": "09", "tzname": "UTC", "mon": "04"}, "pressurem": "1008.9", "wdird": "90", "tornado": "0", "metar": "METAR KMDW 250953Z 09016KT 10SM OVC055 08/04 A2979 RMK AO2 SLP089 T00780044", "rain": "0", "hail": "0"}, {"wspdm": "24.1", "wspdi": "15.0", "snow": "0", "date": {"pretty": "5:53 AM CDT on April 25, 2015", "year": "2015", "mday": "25", "min": "53", "hour": "05", "tzname": "America/Chicago", "mon": "04"}, "precipi": "-9999.00", "wgusti": "-9999.0", "heatindexi": "-9999", "vism": "16.1", "precipm": "-9999.00", "dewpti": "39.9", "fog": "0", "heatindexm": "-9999", "wgustm": "-9999.0", "icon": "cloudy", "visi": "10.0", "windchillm": "4.2", "conds": "Overcast", "windchilli": "39.6", "pressurei": "29.81", "tempm": "7.8", "hum": "79", "tempi": "46.0", "thunder": "0", "dewptm": "4.4", "wdire": "ENE", "utcdate": {"pretty": "10:53 AM GMT on April 25, 2015", "year": "2015", "mday": "25", "min": "53", "hour": "10", "tzname": "UTC", "mon": "04"}, "pressurem": "1009.3", "wdird": "70", "tornado": "0", "metar": "METAR KMDW 251053Z 07013KT 10SM OVC060 08/04 A2980 RMK AO2 SLP093 T00780044", "rain": "0", "hail": "0"}, {"wspdm": "29.6", "wspdi": "18.4", "snow": "0", "date": {"pretty": "6:53 AM CDT on April 25, 2015", "year": "2015", "mday": "25", "min": "53", "hour": "06", "tzname": "America/Chicago", "mon": "04"}, "precipi": "0.00", "wgusti": "-9999.0", "heatindexi": "-9999", "vism": "16.1", "precipm": "0.0", "dewpti": "39.9", "fog": "0", "heatindexm": "-9999", "wgustm": "-9999.0", "icon": "rain", "visi": "10.0", "windchillm": "3.8", "conds": "Light Rain", "windchilli": "38.8", "pressurei": "29.81", "tempm": "7.8", "hum": "79", "tempi": "46.0", "thunder": "0", "dewptm": "4.4", "wdire": "East", "utcdate": {"pretty": "11:53 AM GMT on April 25, 2015", "year": "2015", "mday": "25", "min": "53", "hour": "11", "tzname": "UTC", "mon": "04"}, "pressurem": "1009.3", "wdird": "100", "tornado": "0", "metar": "METAR KMDW 251153Z 10016KT 10SM -RA OVC055 08/04 A2980 RMK AO2 RAB43 SLP093 P0000 60000 70029 T00780044 10078 20072 56005", "rain": "1", "hail": "0"}, {"wspdm": "18.5", "wspdi": "11.5", "snow": "0", "date": {"pretty": "7:53 AM CDT on April 25, 2015", "year": "2015", "mday": "25", "min": "53", "hour": "07", "tzname": "America/Chicago", "mon": "04"}, "precipi": "-9999.00", "wgusti": "-9999.0", "heatindexi": "-9999", "vism": "16.1", "precipm": "-9999.00", "dewpti": "39.2", "fog": "0", "heatindexm": "-9999", "wgustm": "-9999.0", "icon": "rain", "visi": "10.0", "windchillm": "5.0", "conds": "Light Rain", "windchilli": "41.1", "pressurei": "29.80", "tempm": "8.0", "hum": "76", "tempi": "46.4", "thunder": "0", "dewptm": "4.0", "wdire": "East", "utcdate": {"pretty": "12:53 PM GMT on April 25, 2015", "year": "2015", "mday": "25", "min": "53", "hour": "12", "tzname": "UTC", "mon": "04"}, "pressurem": "1009.0", "wdird": "90", "tornado": "0", "metar": "METAR KMDW 251253Z 09010KT 10SM -RA OVC055 08/04 A2980", "rain": "1", "hail": "0"}, {"wspdm": "20.4", "wspdi": "12.7", "snow": "0", "date": {"pretty": "8:53 AM CDT on April 25, 2015", "year": "2015", "mday": "25", "min": "53", "hour": "08", "tzname": "America/Chicago", "mon": "04"}, "precipi": "0.05", "wgusti": "-9999.0", "heatindexi": "-9999", "vism": "11.3", "precipm": "1.3", "dewpti": "39.9", "fog": "0", "heatindexm": "-9999", "wgustm": "-9999.0", "icon": "rain", "visi": "7.0", "windchillm": "3.8", "conds": "Light Rain", "windchilli": "38.9", "pressurei": "29.80", "tempm": "7.2", "hum": "82", "tempi": "45.0", "thunder": "0", "dewptm": "4.4", "wdire": "East", "utcdate": {"pretty": "1:53 PM GMT on April 25, 2015", "year": "2015", "mday": "25", "min": "53", "hour": "13", "tzname": "UTC", "mon": "04"}, "pressurem": "1009.0", "wdird": "100", "tornado": "0", "metar": "METAR KMDW 251353Z 10011KT 7SM -RA SCT015 OVC050 07/04 A2979 RMK AO2 SLP090 P0005 T00720044", "rain": "1", "hail": "0"}, {"wspdm": "22.2", "wspdi": "13.8", "snow": "0", "date": {"pretty": "9:53 AM CDT on April 25, 2015", "year": "2015", "mday": "25", "min": "53", "hour": "09", "tzname": "America/Chicago", "mon": "04"}, "precipi": "0.08", "wgusti": "-9999.0", "heatindexi": "-9999", "vism": "9.7", "precipm": "2.0", "dewpti": "41.0", "fog": "0", "heatindexm": "-9999", "wgustm": "-9999.0", "icon": "rain", "visi": "6.0", "windchillm": "3.6", "conds": "Light Rain", "windchilli": "38.5", "pressurei": "29.78", "tempm": "7.2", "hum": "86", "tempi": "45.0", "thunder": "0", "dewptm": "5.0", "wdire": "East", "utcdate": {"pretty": "2:53 PM GMT on April 25, 2015", "year": "2015", "mday": "25", "min": "53", "hour": "14", "tzname": "UTC", "mon": "04"}, "pressurem": "1008.3", "wdird": "100", "tornado": "0", "metar": "METAR KMDW 251453Z 10012KT 6SM -RA BR BKN055 BKN070 OVC090 07/05 A2976 RMK AO2 SLP083 P0008 60013 T00720050 58012", "rain": "1", "hail": "0"}, {"wspdm": "27.8", "wspdi": "17.3", "snow": "0", "date": {"pretty": "10:16 AM CDT on April 25, 2015", "year": "2015", "mday": "25", "min": "16", "hour": "10", "tzname": "America/Chicago", "mon": "04"}, "precipi": "0.01", "wgusti": "23.0", "heatindexi": "-9999", "vism": "11.3", "precipm": "0.3", "dewpti": "41.0", "fog": "0", "heatindexm": "-9999", "wgustm": "37.0", "icon": "rain", "visi": "7.0", "windchillm": "3.1", "conds": "Light Rain", "windchilli": "37.6", "pressurei": "29.75", "tempm": "7.2", "hum": "86", "tempi": "45.0", "thunder": "0", "dewptm": "5.0", "wdire": "East", "utcdate": {"pretty": "3:16 PM GMT on April 25, 2015", "year": "2015", "mday": "25", "min": "16", "hour": "15", "tzname": "UTC", "mon": "04"}, "pressurem": "1007.3", "wdird": "80", "tornado": "0", "metar": "SPECI KMDW 251516Z 08015G20KT 7SM -RA BKN013 BKN026 OVC055 07/05 A2975 RMK AO2 P0001 T00720050", "rain": "1", "hail": "0"}, {"wspdm": "25.9", "wspdi": "16.1", "snow": "0", "date": {"pretty": "10:53 AM CDT on April 25, 2015", "year": "2015", "mday": "25", "min": "53", "hour": "10", "tzname": "America/Chicago", "mon": "04"}, "precipi": "0.03", "wgusti": "-9999.0", "heatindexi": "-9999", "vism": "9.7", "precipm": "0.8", "dewpti": "42.1", "fog": "0", "heatindexm": "-9999", "wgustm": "-9999.0", "icon": "rain", "visi": "6.0", "windchillm": "4.1", "conds": "Light Rain", "windchilli": "39.3", "pressurei": "29.78", "tempm": "7.8", "hum": "86", "tempi": "46.0", "thunder": "0", "dewptm": "5.6", "wdire": "East", "utcdate": {"pretty": "3:53 PM GMT on April 25, 2015", "year": "2015", "mday": "25", "min": "53", "hour": "15", "tzname": "UTC", "mon": "04"}, "pressurem": "1008.3", "wdird": "80", "tornado": "0", "metar": "METAR KMDW 251553Z 08014KT 6SM -RA BR SCT012 BKN047 OVC055 08/06 A2976 RMK AO2 SLP083 P0003 T00780056", "rain": "1", "hail": "0"}, {"wspdm": "22.2", "wspdi": "13.8", "snow": "0", "date": {"pretty": "11:31 AM CDT on April 25, 2015", "year": "2015", "mday": "25", "min": "31", "hour": "11", "tzname": "America/Chicago", "mon": "04"}, "precipi": "0.00", "wgusti": "-9999.0", "heatindexi": "-9999", "vism": "16.1", "precipm": "0.0", "dewpti": "41.0", "fog": "0", "heatindexm": "-9999", "wgustm": "-9999.0", "icon": "rain", "visi": "10.0", "windchillm": "3.6", "conds": "Light Rain", "windchilli": "38.5", "pressurei": "29.77", "tempm": "7.2", "hum": "86", "tempi": "45.0", "thunder": "0", "dewptm": "5.0", "wdire": "ENE", "utcdate": {"pretty": "4:31 PM GMT on April 25, 2015", "year": "2015", "mday": "25", "min": "31", "hour": "16", "tzname": "UTC", "mon": "04"}, "pressurem": "1008.0", "wdird": "60", "tornado": "0", "metar": "SPECI KMDW 251631Z 06012KT 10SM -RA BKN010 OVC060 07/05 A2977 RMK AO2 RAE1559B26DZB27E28 P0000 T00720050", "rain": "1", "hail": "0"}, {"wspdm": "18.5", "wspdi": "11.5", "snow": "0", "date": {"pretty": "11:53 AM CDT on April 25, 2015", "year": "2015", "mday": "25", "min": "53", "hour": "11", "tzname": "America/Chicago", "mon": "04"}, "precipi": "0.06", "wgusti": "-9999.0", "heatindexi": "-9999", "vism": "4.8", "precipm": "1.5", "dewpti": "42.1", "fog": "0", "heatindexm": "-9999", "wgustm": "-9999.0", "icon": "rain", "visi": "3.0", "windchillm": "4.8", "conds": "Light Rain", "windchilli": "40.6", "pressurei": "29.79", "tempm": "7.8", "hum": "86", "tempi": "46.0", "thunder": "0", "dewptm": "5.6", "wdire": "East", "utcdate": {"pretty": "4:53 PM GMT on April 25, 2015", "year": "2015", "mday": "25", "min": "53", "hour": "16", "tzname": "UTC", "mon": "04"}, "pressurem": "1008.7", "wdird": "80", "tornado": "0", "metar": "METAR KMDW 251653Z 08010KT 3SM -RA BR BKN012 OVC055 08/06 A2977 RMK AO2 RAE1559B26DZB27E28 SLP087 P0006 T00780056", "rain": "1", "hail": "0"}, {"wspdm": "14.8", "wspdi": "9.2", "snow": "0", "date": {"pretty": "12:53 PM CDT on April 25, 2015", "year": "2015", "mday": "25", "min": "53", "hour": "12", "tzname": "America/Chicago", "mon": "04"}, "precipi": "0.02", "wgusti": "-9999.0", "heatindexi": "-9999", "vism": "9.7", "precipm": "0.5", "dewpti": "41.0", "fog": "0", "heatindexm": "-9999", "wgustm": "-9999.0", "icon": "rain", "visi": "6.0", "windchillm": "5.2", "conds": "Light Rain", "windchilli": "41.4", "pressurei": "29.81", "tempm": "7.8", "hum": "83", "tempi": "46.0", "thunder": "0", "dewptm": "5.0", "wdire": "East", "utcdate": {"pretty": "5:53 PM GMT on April 25, 2015", "year": "2015", "mday": "25", "min": "53", "hour": "17", "tzname": "UTC", "mon": "04"}, "pressurem": "1009.4", "wdird": "80", "tornado": "0", "metar": "METAR KMDW 251753Z 08008KT 6SM -RA BKN014 BKN018 OVC036 08/05 A2980 RMK AO2 RAE14B32 SLP094 P0002 60024 T00780050 10083 20072 53011", "rain": "1", "hail": "0"}, {"wspdm": "20.4", "wspdi": "12.7", "snow": "0", "date": {"pretty": "1:37 PM CDT on April 25, 2015", "year": "2015", "mday": "25", "min": "37", "hour": "13", "tzname": "America/Chicago", "mon": "04"}, "precipi": "0.05", "wgusti": "-9999.0", "heatindexi": "-9999", "vism": "8.0", "precipm": "1.3", "dewpti": "41.0", "fog": "0", "heatindexm": "-9999", "wgustm": "-9999.0", "icon": "rain", "visi": "5.0", "windchillm": "4.6", "conds": "Light Rain", "windchilli": "40.2", "pressurei": "29.78", "tempm": "7.8", "hum": "83", "tempi": "46.0", "thunder": "0", "dewptm": "5.0", "wdire": "ENE", "utcdate": {"pretty": "6:37 PM GMT on April 25, 2015", "year": "2015", "mday": "25", "min": "37", "hour": "18", "tzname": "UTC", "mon": "04"}, "pressurem": "1008.4", "wdird": "60", "tornado": "0", "metar": "SPECI KMDW 251837Z 06011KT 5SM -RA FEW014 BKN043 OVC049 08/05 A2978 RMK AO2 P0005 T00780050", "rain": "1", "hail": "0"}, {"wspdm": "20.4", "wspdi": "12.7", "snow": "0", "date": {"pretty": "1:53 PM CDT on April 25, 2015", "year": "2015", "mday": "25", "min": "53", "hour": "13", "tzname": "America/Chicago", "mon": "04"}, "precipi": "0.06", "wgusti": "-9999.0", "heatindexi": "-9999", "vism": "6.4", "precipm": "1.5", "dewpti": "42.1", "fog": "0", "heatindexm": "-9999", "wgustm": "-9999.0", "icon": "rain", "visi": "4.0", "windchillm": "4.6", "conds": "Light Rain", "windchilli": "40.2", "pressurei": "29.78", "tempm": "7.8", "hum": "86", "tempi": "46.0", "thunder": "0", "dewptm": "5.6", "wdire": "ENE", "utcdate": {"pretty": "6:53 PM GMT on April 25, 2015", "year": "2015", "mday": "25", "min": "53", "hour": "18", "tzname": "UTC", "mon": "04"}, "pressurem": "1008.4", "wdird": "60", "tornado": "0", "metar": "METAR KMDW 251853Z 06011KT 4SM -RA BR FEW019 BKN045 OVC055 08/06 A2977 RMK AO2 SLP084 P0006 T00780056", "rain": "1", "hail": "0"}, {"wspdm": "29.6", "wspdi": "18.4", "snow": "0", "date": {"pretty": "2:53 PM CDT on April 25, 2015", "year": "2015", "mday": "25", "min": "53", "hour": "14", "tzname": "America/Chicago", "mon": "04"}, "precipi": "0.04", "wgusti": "-9999.0", "heatindexi": "-9999", "vism": "9.7", "precipm": "1.0", "dewpti": "43.0", "fog": "0", "heatindexm": "-9999", "wgustm": "-9999.0", "icon": "rain", "visi": "6.0", "windchillm": "3.8", "conds": "Light Rain", "windchilli": "38.8", "pressurei": "29.73", "tempm": "7.8", "hum": "89", "tempi": "46.0", "thunder": "0", "dewptm": "6.1", "wdire": "ENE", "utcdate": {"pretty": "7:53 PM GMT on April 25, 2015", "year": "2015", "mday": "25", "min": "53", "hour": "19", "tzname": "UTC", "mon": "04"}, "pressurem": "1006.8", "wdird": "60", "tornado": "0", "metar": "METAR KMDW 251953Z 06016KT 6SM -RA BR FEW040 SCT065 OVC080 08/06 A2972 RMK AO2 SLP068 P0004 T00780061", "rain": "1", "hail": "0"}, {"wspdm": "38.9", "wspdi": "24.2", "snow": "0", "date": {"pretty": "3:53 PM CDT on April 25, 2015", "year": "2015", "mday": "25", "min": "53", "hour": "15", "tzname": "America/Chicago", "mon": "04"}, "precipi": "0.00", "wgusti": "32.2", "heatindexi": "-9999", "vism": "16.1", "precipm": "0.0", "dewpti": "43.0", "fog": "0", "heatindexm": "-9999", "wgustm": "51.9", "icon": "mostlycloudy", "visi": "10.0", "windchillm": "-999", "conds": "Mostly Cloudy", "windchilli": "-999", "pressurei": "29.73", "tempm": "8.9", "hum": "83", "tempi": "48.0", "thunder": "0", "dewptm": "6.1", "wdire": "NE", "utcdate": {"pretty": "8:53 PM GMT on April 25, 2015", "year": "2015", "mday": "25", "min": "53", "hour": "20", "tzname": "UTC", "mon": "04"}, "pressurem": "1006.7", "wdird": "50", "tornado": "0", "metar": "METAR KMDW 252053Z 05021G28KT 10SM SCT014 SCT030 BKN070 BKN140 09/06 A2972 RMK AO2 PK WND 05028/2052 RAE38 SLP067 P0000 60010 T00890061 56026", "rain": "0", "hail": "0"}, {"wspdm": "33.3", "wspdi": "20.7", "snow": "0", "date": {"pretty": "4:53 PM CDT on April 25, 2015", "year": "2015", "mday": "25", "min": "53", "hour": "16", "tzname": "America/Chicago", "mon": "04"}, "precipi": "-9999.00", "wgusti": "-9999.0", "heatindexi": "-9999", "vism": "16.1", "precipm": "-9999.00", "dewpti": "39.0", "fog": "0", "heatindexm": "-9999", "wgustm": "-9999.0", "icon": "cloudy", "visi": "10.0", "windchillm": "-999", "conds": "Overcast", "windchilli": "-999", "pressurei": "29.76", "tempm": "8.9", "hum": "71", "tempi": "48.0", "thunder": "0", "dewptm": "3.9", "wdire": "ENE", "utcdate": {"pretty": "9:53 PM GMT on April 25, 2015", "year": "2015", "mday": "25", "min": "53", "hour": "21", "tzname": "UTC", "mon": "04"}, "pressurem": "1007.8", "wdird": "70", "tornado": "0", "metar": "METAR KMDW 252153Z 07018KT 10SM FEW018 SCT060 OVC140 09/04 A2975 RMK AO2 PK WND 06026/2054 SLP078 T00890039", "rain": "0", "hail": "0"}, {"wspdm": "24.1", "wspdi": "15.0", "snow": "0", "date": {"pretty": "5:53 PM CDT on April 25, 2015", "year": "2015", "mday": "25", "min": "53", "hour": "17", "tzname": "America/Chicago", "mon": "04"}, "precipi": "-9999.00", "wgusti": "-9999.0", "heatindexi": "-9999", "vism": "14.5", "precipm": "-9999.00", "dewpti": "39.9", "fog": "0", "heatindexm": "-9999", "wgustm": "-9999.0", "icon": "cloudy", "visi": "9.0", "windchillm": "-999", "conds": "Overcast", "windchilli": "-999", "pressurei": "29.80", "tempm": "8.9", "hum": "74", "tempi": "48.0", "thunder": "0", "dewptm": "4.4", "wdire": "NE", "utcdate": {"pretty": "10:53 PM GMT on April 25, 2015", "year": "2015", "mday": "25", "min": "53", "hour": "22", "tzname": "UTC", "mon": "04"}, "pressurem": "1009.1", "wdird": "50", "tornado": "0", "metar": "METAR KMDW 252253Z 05013KT 9SM FEW028 SCT035 OVC060 09/04 A2979 RMK AO2 SLP091 T00890044", "rain": "0", "hail": "0"}, {"wspdm": "22.2", "wspdi": "13.8", "snow": "0", "date": {"pretty": "6:24 PM CDT on April 25, 2015", "year": "2015", "mday": "25", "min": "24", "hour": "18", "tzname": "America/Chicago", "mon": "04"}, "precipi": "-9999.00", "wgusti": "-9999.0", "heatindexi": "-9999", "vism": "14.5", "precipm": "-9999.00", "dewpti": "39.9", "fog": "0", "heatindexm": "-9999", "wgustm": "-9999.0", "icon": "cloudy", "visi": "9.0", "windchillm": "-999", "conds": "Overcast", "windchilli": "-999", "pressurei": "29.79", "tempm": "8.3", "hum": "77", "tempi": "46.9", "thunder": "0", "dewptm": "4.4", "wdire": "NE", "utcdate": {"pretty": "11:24 PM GMT on April 25, 2015", "year": "2015", "mday": "25", "min": "24", "hour": "23", "tzname": "UTC", "mon": "04"}, "pressurem": "1008.7", "wdird": "50", "tornado": "0", "metar": "SPECI KMDW 252324Z 05012KT 9SM BKN020 BKN030 OVC060 08/04 A2979 RMK AO2 T00830044", "rain": "0", "hail": "0"}, {"wspdm": "22.2", "wspdi": "13.8", "snow": "0", "date": {"pretty": "6:53 PM CDT on April 25, 2015", "year": "2015", "mday": "25", "min": "53", "hour": "18", "tzname": "America/Chicago", "mon": "04"}, "precipi": "0.00", "wgusti": "-9999.0", "heatindexi": "-9999", "vism": "14.5", "precipm": "0.0", "dewpti": "39.0", "fog": "0", "heatindexm": "-9999", "wgustm": "-9999.0", "icon": "rain", "visi": "9.0", "windchillm": "4.4", "conds": "Light Drizzle", "windchilli": "39.9", "pressurei": "29.82", "tempm": "7.8", "hum": "76", "tempi": "46.0", "thunder": "0", "dewptm": "3.9", "wdire": "NNE", "utcdate": {"pretty": "11:53 PM GMT on April 25, 2015", "year": "2015", "mday": "25", "min": "53", "hour": "23", "tzname": "UTC", "mon": "04"}, "pressurem": "1009.7", "wdird": "30", "tornado": "0", "metar": "METAR KMDW 252353Z 03012KT 9SM -DZ BKN020 BKN030 OVC060 08/04 A2981 RMK AO2 DZB46 SLP097 P0000 60010 T00780039 10094 20072 51029", "rain": "0", "hail": "0"}, {"wspdm": "20.4", "wspdi": "12.7", "snow": "0", "date": {"pretty": "7:19 PM CDT on April 25, 2015", "year": "2015", "mday": "25", "min": "19", "hour": "19", "tzname": "America/Chicago", "mon": "04"}, "precipi": "0.00", "wgusti": "-9999.0", "heatindexi": "-9999", "vism": "16.1", "precipm": "0.0", "dewpti": "37.9", "fog": "0", "heatindexm": "-9999", "wgustm": "-9999.0", "icon": "cloudy", "visi": "10.0", "windchillm": "3.8", "conds": "Overcast", "windchilli": "38.9", "pressurei": "29.81", "tempm": "7.2", "hum": "76", "tempi": "45.0", "thunder": "0", "dewptm": "3.3", "wdire": "NNE", "utcdate": {"pretty": "12:19 AM GMT on April 26, 2015", "year": "2015", "mday": "26", "min": "19", "hour": "00", "tzname": "UTC", "mon": "04"}, "pressurem": "1009.4", "wdird": "20", "tornado": "0", "metar": "SPECI KMDW 260019Z 02011KT 10SM SCT023 BKN031 OVC060 07/03 A2981 RMK AO2 DZE15 P0000 T00720033", "rain": "0", "hail": "0"}, {"wspdm": "22.2", "wspdi": "13.8", "snow": "0", "date": {"pretty": "7:53 PM CDT on April 25, 2015", "year": "2015", "mday": "25", "min": "53", "hour": "19", "tzname": "America/Chicago", "mon": "04"}, "precipi": "0.00", "wgusti": "-9999.0", "heatindexi": "-9999", "vism": "16.1", "precipm": "0.0", "dewpti": "35.1", "fog": "0", "heatindexm": "-9999", "wgustm": "-9999.0", "icon": "cloudy", "visi": "10.0", "windchillm": "3.0", "conds": "Overcast", "windchilli": "37.4", "pressurei": "29.83", "tempm": "6.7", "hum": "71", "tempi": "44.1", "thunder": "0", "dewptm": "1.7", "wdire": "NNE", "utcdate": {"pretty": "12:53 AM GMT on April 26, 2015", "year": "2015", "mday": "26", "min": "53", "hour": "00", "tzname": "UTC", "mon": "04"}, "pressurem": "1010.2", "wdird": "30", "tornado": "0", "metar": "METAR KMDW 260053Z 03012KT 10SM SCT023 SCT031 OVC060 07/02 A2982 RMK AO2 DZE15 SLP102 P0000 T00670017", "rain": "0", "hail": "0"}, {"wspdm": "13.0", "wspdi": "8.1", "snow": "0", "date": {"pretty": "8:53 PM CDT on April 25, 2015", "year": "2015", "mday": "25", "min": "53", "hour": "20", "tzname": "America/Chicago", "mon": "04"}, "precipi": "-9999.00", "wgusti": "-9999.0", "heatindexi": "-9999", "vism": "16.1", "precipm": "-9999.00", "dewpti": "34.0", "fog": "0", "heatindexm": "-9999", "wgustm": "-9999.0", "icon": "cloudy", "visi": "10.0", "windchillm": "4.2", "conds": "Overcast", "windchilli": "39.5", "pressurei": "29.85", "tempm": "6.7", "hum": "68", "tempi": "44.1", "thunder": "0", "dewptm": "1.1", "wdire": "North", "utcdate": {"pretty": "1:53 AM GMT on April 26, 2015", "year": "2015", "mday": "26", "min": "53", "hour": "01", "tzname": "UTC", "mon": "04"}, "pressurem": "1010.8", "wdird": "10", "tornado": "0", "metar": "METAR KMDW 260153Z 01007KT 10SM OVC065 07/01 A2984 RMK AO2 SLP108 T00670011", "rain": "0", "hail": "0"}, {"wspdm": "18.5", "wspdi": "11.5", "snow": "0", "date": {"pretty": "9:53 PM CDT on April 25, 2015", "year": "2015", "mday": "25", "min": "53", "hour": "21", "tzname": "America/Chicago", "mon": "04"}, "precipi": "-9999.00", "wgusti": "-9999.0", "heatindexi": "-9999", "vism": "16.1", "precipm": "-9999.00", "dewpti": "33.1", "fog": "0", "heatindexm": "-9999", "wgustm": "-9999.0", "icon": "cloudy", "visi": "10.0", "windchillm": "2.7", "conds": "Overcast", "windchilli": "36.8", "pressurei": "29.86", "tempm": "6.1", "hum": "68", "tempi": "43.0", "thunder": "0", "dewptm": "0.6", "wdire": "North", "utcdate": {"pretty": "2:53 AM GMT on April 26, 2015", "year": "2015", "mday": "26", "min": "53", "hour": "02", "tzname": "UTC", "mon": "04"}, "pressurem": "1011.1", "wdird": "360", "tornado": "0", "metar": "METAR KMDW 260253Z 36010KT 10SM SCT065 OVC100 06/01 A2984 RMK AO2 SLP111 60000 T00610006 51012", "rain": "0", "hail": "0"}, {"wspdm": "18.5", "wspdi": "11.5", "snow": "0", "date": {"pretty": "10:53 PM CDT on April 25, 2015", "year": "2015", "mday": "25", "min": "53", "hour": "22", "tzname": "America/Chicago", "mon": "04"}, "precipi": "-9999.00", "wgusti": "-9999.0", "heatindexi": "-9999", "vism": "16.1", "precipm": "-9999.00", "dewpti": "32.0", "fog": "0", "heatindexm": "-9999", "wgustm": "-9999.0", "icon": "mostlycloudy", "visi": "10.0", "windchillm": "1.3", "conds": "Mostly Cloudy", "windchilli": "34.3", "pressurei": "29.86", "tempm": "5.0", "hum": "70", "tempi": "41.0", "thunder": "0", "dewptm": "0.0", "wdire": "North", "utcdate": {"pretty": "3:53 AM GMT on April 26, 2015", "year": "2015", "mday": "26", "min": "53", "hour": "03", "tzname": "UTC", "mon": "04"}, "pressurem": "1010.9", "wdird": "10", "tornado": "0", "metar": "METAR KMDW 260353Z 01010KT 10SM FEW065 BKN095 05/00 A2984 RMK AO2 SLP109 T00500000", "rain": "0", "hail": "0"}, {"wspdm": "16.7", "wspdi": "10.4", "snow": "0", "date": {"pretty": "11:53 PM CDT on April 25, 2015", "year": "2015", "mday": "25", "min": "53", "hour": "23", "tzname": "America/Chicago", "mon": "04"}, "precipi": "-9999.00", "wgusti": "-9999.0", "heatindexi": "-9999", "vism": "16.1", "precipm": "-9999.00", "dewpti": "32.0", "fog": "0", "heatindexm": "-9999", "wgustm": "-9999.0", "icon": "mostlycloudy", "visi": "10.0", "windchillm": "2.3", "conds": "Mostly Cloudy", "windchilli": "36.1", "pressurei": "29.87", "tempm": "5.6", "hum": "67", "tempi": "42.1", "thunder": "0", "dewptm": "0.0", "wdire": "North", "utcdate": {"pretty": "4:53 AM GMT on April 26, 2015", "year": "2015", "mday": "26", "min": "53", "hour": "04", "tzname": "UTC", "mon": "04"}, "pressurem": "1011.3", "wdird": "360", "tornado": "0", "metar": "METAR KMDW 260453Z 36009KT 10SM BKN095 06/00 A2985 RMK AO2 SLP113 T00560000", "rain": "0", "hail": "0"}], "date": {"pretty": "April 25, 2015", "year": "2015", "mday": "25", "min": "00", "hour": "12", "tzname": "America/Chicago", "mon": "04"}, "utcdate": {"pretty": "April 25, 2015", "year": "2015", "mday": "25", "min": "00", "hour": "17", "tzname": "UTC", "mon": "04"}, "dailysummary": [{"heatingdegreedays": "20", "meantempi": "45", "snow": "0", "meanwindspdi": "14", "gdegreedays": "0", "precipm": "8.64", "heatingdegreedaysnormal": "12", "mintempm": "4", "mintempi": "40", "meanpressurem": "1009", "since1sepcoolingdegreedaysnormal": "", "maxpressurei": "29.88", "fog": "0", "monthtodatesnowfalli": "", "maxtempi": "49", "since1jancoolingdegreedaysnormal": "8", "meandewptm": "4", "meanwindspdm": "23", "monthtodatesnowfallm": "", "since1julheatingdegreedaysnormal": "5720", "meandewpti": "39", "since1julsnowfalli": "", "snowfalli": "0.00", "snowdepthm": "", "meanvism": "14", "coolingdegreedays": "0", "precipi": "0.34", "monthtodateheatingdegreedaysnormal": "397", "meanvisi": "9", "minvisi": "3", "since1sepcoolingdegreedays": "", "maxtempm": "9", "since1julsnowfallm": "", "tornado": "0", "maxvisi": "10", "maxpressurem": "1012", "hail": "0", "maxwspdi": "25", "date": {"pretty": "12:00 PM CDT on April 25, 2015", "year": "2015", "mday": "25", "min": "00", "hour": "12", "tzname": "America/Chicago", "mon": "04"}, "snowdepthi": "", "meantempm": "7", "rain": "1", "minwspdi": "8", "monthtodatecoolingdegreedaysnormal": "7", "minvism": "5", "coolingdegreedaysnormal": "1", "minhumidity": "58", "monthtodateheatingdegreedays": "292", "since1sepheatingdegreedays": "", "maxdewptm": "6", "mindewptm": "0", "minpressurem": "1007", "precipsource": "", "mindewpti": "32", "meanpressurei": "29.81", "since1sepheatingdegreedaysnormal": "", "since1julheatingdegreedays": "5840", "maxdewpti": "43", "meanwdird": "61", "minpressurei": "29.73", "thunder": "0", "monthtodatecoolingdegreedays": "0", "maxvism": "16", "maxwspdm": "40", "snowfallm": "0.00", "maxhumidity": "89", "meanwdire": "", "minwspdm": "13", "since1jancoolingdegreedays": "0", "humidity": ""}]}}