{"response": {"version": "0.1", "termsofService": "http://www.wunderground.com/weather/api/d/terms.html", "features": {"history": 1}}, "history": {"observations": [{"wspdm": "11.1", "wspdi": "6.9", "snow": "0", "date": {"pretty": "12:04 AM CST on December 15, 2015", "year": "2015", "mday": "15", "min": "04", "hour": "00", "tzname": "America/Chicago", "mon": "12"}, "precipi": "0.00", "wgusti": "-9999.0", "heatindexi": "-9999", "vism": "16.1", "precipm": "0.0", "dewpti": "37.0", "fog": "0", "heatindexm": "-9999", "wgustm": "-9999.0", "icon": "mostlycloudy", "visi": "10.0", "windchillm": "3.8", "conds": "Mostly Cloudy", "windchilli": "38.8", "pressurei": "29.60", "tempm": "6.1", "hum": "80", "tempi": "43.0", "thunder": "0", "dewptm": "2.8", "wdire": "WSW", "utcdate": {"pretty": "6:04 AM GMT on December 15, 2015", "year": "2015", "mday": "15", "min": "04", "hour": "06", "tzname": "UTC", "mon": "12"}, "pressurem": "1002.3", "wdird": "250", "tornado": "0", "metar": "SPECI KMDW 150604Z 25006KT 10SM SCT013 BKN022 BKN028 06/03 A2960 RMK AO2 DZE01 VIS E AND S 6 P0000 T00610028", "rain": "0", "hail": "0"}, {"wspdm": "11.1", "wspdi": "6.9", "snow": "0", "date": {"pretty": "12:53 AM CST on December 15, 2015", "year": "2015", "mday": "15", "min": "53", "hour": "00", "tzname": "America/Chicago", "mon": "12"}, "precipi": "0.00", "wgusti": "-9999.0", "heatindexi": "-9999", "vism": "16.1", "precipm": "0.0", "dewpti": "37.9", "fog": "0", "heatindexm": "-9999", "wgustm": "-9999.0", "icon": "cloudy", "visi": "10.0", "windchillm": "3.8", "conds": "Overcast", "windchilli": "38.8", "pressurei": "29.64", "tempm": "6.1", "hum": "82", "tempi": "43.0", "thunder": "0", "dewptm": "3.3", "wdire": "SW", "utcdate": {"pretty": "6:53 AM GMT on December 15, 2015", "year": "2015", "mday": "15", "min": "53", "hour": "06", "tzname": "UTC", "mon": "12"}, "pressurem": "1003.5", "wdird": "230", "tornado": "0", "metar": "METAR KMDW 150653Z 23006KT 10SM FEW011 FEW020 OVC035 06/03 A2962 RMK AO2 DZE01 SLP035 P0000 T00610033", "rain": "0", "hail": "0"}, {"wspdm": "11.1", "wspdi": "6.9", "snow": "0", "date": {"pretty": "1:33 AM CST on December 15, 2015", "year": "2015", "mday": "15", "min": "33", "hour": "01", "tzname": "America/Chicago", "mon": "12"}, "precipi": "-9999.00", "wgusti": "-9999.0", "heatindexi": "-9999", "vism": "16.1", "precipm": "-9999.00", "dewpti": "37.9", "fog": "0", "heatindexm": "-9999", "wgustm": "-9999.0", "icon": "cloudy", "visi": "10.0", "windchillm": "3.8", "conds": "Overcast", "windchilli": "38.8", "pressurei": "29.65", "tempm": "6.1", "hum": "82", "tempi": "43.0", "thunder": "0", "dewptm": "3.3", "wdire": "WSW", "utcdate": {"pretty": "7:33 AM GMT on December 15, 2015", "year": "2015", "mday": "15", "min": "33", "hour": "07", "tzname": "UTC", "mon": "12"}, "pressurem": "1003.9", "wdird": "250", "tornado": "0", "metar": "SPECI KMDW 150733Z 25006KT 10SM BKN022 BKN029 OVC035 06/03 A2965 RMK AO2 T00610033", "rain": "0", "hail": "0"}, {"wspdm": "16.7", "wspdi": "10.4", "snow": "0", "date": {"pretty": "1:53 AM CST on December 15, 2015", "year": "2015", "mday": "15", "min": "53", "hour": "01", "tzname": "America/Chicago", "mon": "12"}, "precipi": "0.00", "wgusti": "-9999.0", "heatindexi": "-9999", "vism": "16.1", "precipm": "0.0", "dewpti": "37.9", "fog": "0", "heatindexm": "-9999", "wgustm": "-9999.0", "icon": "rain", "visi": "10.0", "windchillm": "3.6", "conds": "Light Drizzle", "windchilli": "38.6", "pressurei": "29.67", "tempm": "6.7", "hum": "79", "tempi": "44.1", "thunder": "0", "dewptm": "3.3", "wdire": "WSW", "utcdate": {"pretty": "7:53 AM GMT on December 15, 2015", "year": "2015", "mday": "15", "min": "53", "hour": "07", "tzname": "UTC", "mon": "12"}, "pressurem": "1004.7", "wdird": "250", "tornado": "0", "metar": "METAR KMDW 150753Z 25009KT 10SM -DZ BKN013 OVC019 07/03 A2966 RMK AO2 SLP047 DZB46 P0000 T00670033", "rain": "0", "hail": "0"}, {"wspdm": "16.7", "wspdi": "10.4", "snow": "0", "date": {"pretty": "2:53 AM CST on December 15, 2015", "year": "2015", "mday": "15", "min": "53", "hour": "02", "tzname": "America/Chicago", "mon": "12"}, "precipi": "0.00", "wgusti": "-9999.0", "heatindexi": "-9999", "vism": "16.1", "precipm": "0.0", "dewpti": "39.0", "fog": "0", "heatindexm": "-9999", "wgustm": "-9999.0", "icon": "cloudy", "visi": "10.0", "windchillm": "3.6", "conds": "Overcast", "windchilli": "38.6", "pressurei": "29.70", "tempm": "6.7", "hum": "82", "tempi": "44.1", "thunder": "0", "dewptm": "3.9", "wdire": "West", "utcdate": {"pretty": "8:53 AM GMT on December 15, 2015", "year": "2015", "mday": "15", "min": "53", "hour": "08", "tzname": "UTC", "mon": "12"}, "pressurem": "1005.7", "wdird": "260", "tornado": "0", "metar": "METAR KMDW 150853Z 26009KT 10SM BKN010 OVC014 07/04 A2969 RMK AO2 DZE06 SLP057 P0000 60000 T00670039 51033", "rain": "0", "hail": "0"}, {"wspdm": "16.7", "wspdi": "10.4", "snow": "0", "date": {"pretty": "3:53 AM CST on December 15, 2015", "year": "2015", "mday": "15", "min": "53", "hour": "03", "tzname": "America/Chicago", "mon": "12"}, "precipi": "0.00", "wgusti": "-9999.0", "heatindexi": "-9999", "vism": "14.5", "precipm": "0.0", "dewpti": "37.9", "fog": "0", "heatindexm": "-9999", "wgustm": "-9999.0", "icon": "rain", "visi": "9.0", "windchillm": "2.9", "conds": "Light Drizzle", "windchilli": "37.2", "pressurei": "29.74", "tempm": "6.1", "hum": "82", "tempi": "43.0", "thunder": "0", "dewptm": "3.3", "wdire": "NW", "utcdate": {"pretty": "9:53 AM GMT on December 15, 2015", "year": "2015", "mday": "15", "min": "53", "hour": "09", "tzname": "UTC", "mon": "12"}, "pressurem": "1007.0", "wdird": "320", "tornado": "0", "metar": "METAR KMDW 150953Z 32009KT 9SM -DZ BKN010 OVC014 06/03 A2973 RMK AO2 DZB34RAB44E52 SLP070 P0000 T00610033", "rain": "0", "hail": "0"}, {"wspdm": "16.7", "wspdi": "10.4", "snow": "0", "date": {"pretty": "4:06 AM CST on December 15, 2015", "year": "2015", "mday": "15", "min": "06", "hour": "04", "tzname": "America/Chicago", "mon": "12"}, "precipi": "0.00", "wgusti": "-9999.0", "heatindexi": "-9999", "vism": "14.5", "precipm": "0.0", "dewpti": "37.9", "fog": "0", "heatindexm": "-9999", "wgustm": "-9999.0", "icon": "rain", "visi": "9.0", "windchillm": "2.9", "conds": "Light Drizzle", "windchilli": "37.2", "pressurei": "29.73", "tempm": "6.1", "hum": "82", "tempi": "43.0", "thunder": "0", "dewptm": "3.3", "wdire": "NW", "utcdate": {"pretty": "10:06 AM GMT on December 15, 2015", "year": "2015", "mday": "15", "min": "06", "hour": "10", "tzname": "UTC", "mon": "12"}, "pressurem": "1006.7", "wdird": "310", "tornado": "0", "metar": "SPECI KMDW 151006Z 31009KT 9SM -DZ FEW009 BKN016 OVC021 06/03 A2973 RMK AO2 P0000 T00610033", "rain": "0", "hail": "0"}, {"wspdm": "16.7", "wspdi": "10.4", "snow": "0", "date": {"pretty": "4:53 AM CST on December 15, 2015", "year": "2015", "mday": "15", "min": "53", "hour": "04", "tzname": "America/Chicago", "mon": "12"}, "precipi": "0.00", "wgusti": "-9999.0", "heatindexi": "-9999", "vism": "14.5", "precipm": "0.0", "dewpti": "35.1", "fog": "0", "heatindexm": "-9999", "wgustm": "-9999.0", "icon": "cloudy", "visi": "9.0", "windchillm": "2.3", "conds": "Overcast", "windchilli": "36.1", "pressurei": "29.77", "tempm": "5.6", "hum": "76", "tempi": "42.1", "thunder": "0", "dewptm": "1.7", "wdire": "NNW", "utcdate": {"pretty": "10:53 AM GMT on December 15, 2015", "year": "2015", "mday": "15", "min": "53", "hour": "10", "tzname": "UTC", "mon": "12"}, "pressurem": "1008.1", "wdird": "330", "tornado": "0", "metar": "METAR KMDW 151053Z 33009KT 9SM FEW016 OVC029 06/02 A2976 RMK AO2 DZE21 SLP081 P0000 T00560017", "rain": "0", "hail": "0"}, {"wspdm": "11.1", "wspdi": "6.9", "snow": "0", "date": {"pretty": "5:53 AM CST on December 15, 2015", "year": "2015", "mday": "15", "min": "53", "hour": "05", "tzname": "America/Chicago", "mon": "12"}, "precipi": "-9999.00", "wgusti": "-9999.0", "heatindexi": "-9999", "vism": "16.1", "precipm": "-9999.00", "dewpti": "35.1", "fog": "0", "heatindexm": "-9999", "wgustm": "-9999.0", "icon": "cloudy", "visi": "10.0", "windchillm": "3.2", "conds": "Overcast", "windchilli": "37.7", "pressurei": "29.82", "tempm": "5.6", "hum": "76", "tempi": "42.1", "thunder": "0", "dewptm": "1.7", "wdire": "WNW", "utcdate": {"pretty": "11:53 AM GMT on December 15, 2015", "year": "2015", "mday": "15", "min": "53", "hour": "11", "tzname": "UTC", "mon": "12"}, "pressurem": "1009.6", "wdird": "300", "tornado": "0", "metar": "METAR KMDW 151153Z 30006KT 10SM SCT016 OVC024 06/02 A2980 RMK AO2 SLP096 60000 70015 T00560017 10067 20056 53037", "rain": "0", "hail": "0"}, {"wspdm": "14.8", "wspdi": "9.2", "snow": "0", "date": {"pretty": "6:53 AM CST on December 15, 2015", "year": "2015", "mday": "15", "min": "53", "hour": "06", "tzname": "America/Chicago", "mon": "12"}, "precipi": "-9999.00", "wgusti": "-9999.0", "heatindexi": "-9999", "vism": "16.1", "precipm": "-9999.00", "dewpti": "34.0", "fog": "0", "heatindexm": "-9999", "wgustm": "-9999.0", "icon": "cloudy", "visi": "10.0", "windchillm": "1.8", "conds": "Overcast", "windchilli": "35.2", "pressurei": "29.86", "tempm": "5.0", "hum": "76", "tempi": "41.0", "thunder": "0", "dewptm": "1.1", "wdire": "WNW", "utcdate": {"pretty": "12:53 PM GMT on December 15, 2015", "year": "2015", "mday": "15", "min": "53", "hour": "12", "tzname": "UTC", "mon": "12"}, "pressurem": "1010.9", "wdird": "300", "tornado": "0", "metar": "METAR KMDW 151253Z 30008KT 10SM BKN018 OVC024 05/01 A2984 RMK AO2 SLP109 T00500011", "rain": "0", "hail": "0"}, {"wspdm": "13.0", "wspdi": "8.1", "snow": "0", "date": {"pretty": "7:53 AM CST on December 15, 2015", "year": "2015", "mday": "15", "min": "53", "hour": "07", "tzname": "America/Chicago", "mon": "12"}, "precipi": "-9999.00", "wgusti": "-9999.0", "heatindexi": "-9999", "vism": "16.1", "precipm": "-9999.00", "dewpti": "33.1", "fog": "0", "heatindexm": "-9999", "wgustm": "-9999.0", "icon": "cloudy", "visi": "10.0", "windchillm": "2.1", "conds": "Overcast", "windchilli": "35.8", "pressurei": "29.90", "tempm": "5.0", "hum": "73", "tempi": "41.0", "thunder": "0", "dewptm": "0.6", "wdire": "NW", "utcdate": {"pretty": "1:53 PM GMT on December 15, 2015", "year": "2015", "mday": "15", "min": "53", "hour": "13", "tzname": "UTC", "mon": "12"}, "pressurem": "1012.3", "wdird": "320", "tornado": "0", "metar": "METAR KMDW 151353Z 32007KT 10SM OVC021 05/01 A2988 RMK AO2 SLP123 T00500006", "rain": "0", "hail": "0"}, {"wspdm": "11.1", "wspdi": "6.9", "snow": "0", "date": {"pretty": "8:53 AM CST on December 15, 2015", "year": "2015", "mday": "15", "min": "53", "hour": "08", "tzname": "America/Chicago", "mon": "12"}, "precipi": "-9999.00", "wgusti": "-9999.0", "heatindexi": "-9999", "vism": "16.1", "precipm": "-9999.00", "dewpti": "33.1", "fog": "0", "heatindexm": "-9999", "wgustm": "-9999.0", "icon": "cloudy", "visi": "10.0", "windchillm": "3.2", "conds": "Overcast", "windchilli": "37.7", "pressurei": "29.92", "tempm": "5.6", "hum": "70", "tempi": "42.1", "thunder": "0", "dewptm": "0.6", "wdire": "North", "utcdate": {"pretty": "2:53 PM GMT on December 15, 2015", "year": "2015", "mday": "15", "min": "53", "hour": "14", "tzname": "UTC", "mon": "12"}, "pressurem": "1013.2", "wdird": "360", "tornado": "0", "metar": "METAR KMDW 151453Z 36006KT 10SM OVC021 06/01 A2991 RMK AO2 SLP132 T00560006 51036", "rain": "0", "hail": "0"}, {"wspdm": "5.6", "wspdi": "3.5", "snow": "0", "date": {"pretty": "9:53 AM CST on December 15, 2015", "year": "2015", "mday": "15", "min": "53", "hour": "09", "tzname": "America/Chicago", "mon": "12"}, "precipi": "-9999.00", "wgusti": "-9999.0", "heatindexi": "-9999", "vism": "16.1", "precipm": "-9999.00", "dewpti": "33.1", "fog": "0", "heatindexm": "-9999", "wgustm": "-9999.0", "icon": "cloudy", "visi": "10.0", "windchillm": "4.6", "conds": "Overcast", "windchilli": "40.2", "pressurei": "29.95", "tempm": "5.6", "hum": "70", "tempi": "42.1", "thunder": "0", "dewptm": "0.6", "wdire": "North", "utcdate": {"pretty": "3:53 PM GMT on December 15, 2015", "year": "2015", "mday": "15", "min": "53", "hour": "15", "tzname": "UTC", "mon": "12"}, "pressurem": "1014.0", "wdird": "10", "tornado": "0", "metar": "METAR KMDW 151553Z 01003KT 10SM OVC020 06/01 A2993 RMK AO2 SLP140 T00560006", "rain": "0", "hail": "0"}, {"wspdm": "5.6", "wspdi": "3.5", "snow": "0", "date": {"pretty": "10:53 AM CST on December 15, 2015", "year": "2015", "mday": "15", "min": "53", "hour": "10", "tzname": "America/Chicago", "mon": "12"}, "precipi": "-9999.00", "wgusti": "-9999.0", "heatindexi": "-9999", "vism": "16.1", "precipm": "-9999.00", "dewpti": "32.0", "fog": "0", "heatindexm": "-9999", "wgustm": "-9999.0", "icon": "cloudy", "visi": "10.0", "windchillm": "5.2", "conds": "Overcast", "windchilli": "41.3", "pressurei": "29.94", "tempm": "6.1", "hum": "65", "tempi": "43.0", "thunder": "0", "dewptm": "0.0", "wdire": "NE", "utcdate": {"pretty": "4:53 PM GMT on December 15, 2015", "year": "2015", "mday": "15", "min": "53", "hour": "16", "tzname": "UTC", "mon": "12"}, "pressurem": "1013.6", "wdird": "40", "tornado": "0", "metar": "METAR KMDW 151653Z 04003KT 10SM OVC021 06/00 A2992 RMK AO2 SLP136 T00610000", "rain": "0", "hail": "0"}, {"wspdm": "11.1", "wspdi": "6.9", "snow": "0", "date": {"pretty": "11:53 AM CST on December 15, 2015", "year": "2015", "mday": "15", "min": "53", "hour": "11", "tzname": "America/Chicago", "mon": "12"}, "precipi": "-9999.00", "wgusti": "-9999.0", "heatindexi": "-9999", "vism": "16.1", "precipm": "-9999.00", "dewpti": "34.0", "fog": "0", "heatindexm": "-9999", "wgustm": "-9999.0", "icon": "cloudy", "visi": "10.0", "windchillm": "3.8", "conds": "Overcast", "windchilli": "38.8", "pressurei": "29.92", "tempm": "6.1", "hum": "71", "tempi": "43.0", "thunder": "0", "dewptm": "1.1", "wdire": "East", "utcdate": {"pretty": "5:53 PM GMT on December 15, 2015", "year": "2015", "mday": "15", "min": "53", "hour": "17", "tzname": "UTC", "mon": "12"}, "pressurem": "1013.0", "wdird": "100", "tornado": "0", "metar": "METAR KMDW 151753Z 10006KT 10SM OVC019 06/01 A2990 RMK AO2 SLP130 T00610011 10061 20050 58003", "rain": "0", "hail": "0"}, {"wspdm": "11.1", "wspdi": "6.9", "snow": "0", "date": {"pretty": "12:53 PM CST on December 15, 2015", "year": "2015", "mday": "15", "min": "53", "hour": "12", "tzname": "America/Chicago", "mon": "12"}, "precipi": "-9999.00", "wgusti": "-9999.0", "heatindexi": "-9999", "vism": "16.1", "precipm": "-9999.00", "dewpti": "33.1", "fog": "0", "heatindexm": "-9999", "wgustm": "-9999.0", "icon": "cloudy", "visi": "10.0", "windchillm": "3.2", "conds": "Overcast", "windchilli": "37.7", "pressurei": "29.93", "tempm": "5.6", "hum": "70", "tempi": "42.1", "thunder": "0", "dewptm": "0.6", "wdire": "ENE", "utcdate": {"pretty": "6:53 PM GMT on December 15, 2015", "year": "2015", "mday": "15", "min": "53", "hour": "18", "tzname": "UTC", "mon": "12"}, "pressurem": "1013.3", "wdird": "70", "tornado": "0", "metar": "METAR KMDW 151853Z 07006KT 10SM OVC019 06/01 A2991 RMK AO2 SLP133 T00560006", "rain": "0", "hail": "0"}, {"wspdm": "14.8", "wspdi": "9.2", "snow": "0", "date": {"pretty": "1:53 PM CST on December 15, 2015", "year": "2015", "mday": "15", "min": "53", "hour": "13", "tzname": "America/Chicago", "mon": "12"}, "precipi": "-9999.00", "wgusti": "-9999.0", "heatindexi": "-9999", "vism": "16.1", "precipm": "-9999.00", "dewpti": "33.1", "fog": "0", "heatindexm": "-9999", "wgustm": "-9999.0", "icon": "cloudy", "visi": "10.0", "windchillm": "2.5", "conds": "Overcast", "windchilli": "36.6", "pressurei": "29.93", "tempm": "5.6", "hum": "70", "tempi": "42.1", "thunder": "0", "dewptm": "0.6", "wdire": "East", "utcdate": {"pretty": "7:53 PM GMT on December 15, 2015", "year": "2015", "mday": "15", "min": "53", "hour": "19", "tzname": "UTC", "mon": "12"}, "pressurem": "1013.3", "wdird": "80", "tornado": "0", "metar": "METAR KMDW 151953Z 08008KT 10SM OVC018 06/01 A2991 RMK AO2 SLP133 T00560006 $", "rain": "0", "hail": "0"}, {"wspdm": "16.7", "wspdi": "10.4", "snow": "0", "date": {"pretty": "2:53 PM CST on December 15, 2015", "year": "2015", "mday": "15", "min": "53", "hour": "14", "tzname": "America/Chicago", "mon": "12"}, "precipi": "-9999.00", "wgusti": "-9999.0", "heatindexi": "-9999", "vism": "16.1", "precipm": "-9999.00", "dewpti": "32.0", "fog": "0", "heatindexm": "-9999", "wgustm": "-9999.0", "icon": "cloudy", "visi": "10.0", "windchillm": "2.3", "conds": "Overcast", "windchilli": "36.1", "pressurei": "29.94", "tempm": "5.6", "hum": "67", "tempi": "42.1", "thunder": "0", "dewptm": "0.0", "wdire": "East", "utcdate": {"pretty": "8:53 PM GMT on December 15, 2015", "year": "2015", "mday": "15", "min": "53", "hour": "20", "tzname": "UTC", "mon": "12"}, "pressurem": "1013.6", "wdird": "80", "tornado": "0", "metar": "METAR KMDW 152053Z 08009KT 10SM OVC019 06/00 A2991 RMK AO2 SLP136 T00560000 51006 $", "rain": "0", "hail": "0"}, {"wspdm": "13.0", "wspdi": "8.1", "snow": "0", "date": {"pretty": "3:53 PM CST on December 15, 2015", "year": "2015", "mday": "15", "min": "53", "hour": "15", "tzname": "America/Chicago", "mon": "12"}, "precipi": "-9999.00", "wgusti": "-9999.0", "heatindexi": "-9999", "vism": "16.1", "precipm": "-9999.00", "dewpti": "32.0", "fog": "0", "heatindexm": "-9999", "wgustm": "-9999.0", "icon": "cloudy", "visi": "10.0", "windchillm": "2.8", "conds": "Overcast", "windchilli": "37.1", "pressurei": "29.95", "tempm": "5.6", "hum": "67", "tempi": "42.1", "thunder": "0", "dewptm": "0.0", "wdire": "East", "utcdate": {"pretty": "9:53 PM GMT on December 15, 2015", "year": "2015", "mday": "15", "min": "53", "hour": "21", "tzname": "UTC", "mon": "12"}, "pressurem": "1014.1", "wdird": "100", "tornado": "0", "metar": "METAR KMDW 152153Z 10007KT 10SM OVC019 06/00 A2993 RMK AO2 SLP141 T00560000", "rain": "0", "hail": "0"}, {"wspdm": "16.7", "wspdi": "10.4", "snow": "0", "date": {"pretty": "4:53 PM CST on December 15, 2015", "year": "2015", "mday": "15", "min": "53", "hour": "16", "tzname": "America/Chicago", "mon": "12"}, "precipi": "-9999.00", "wgusti": "-9999.0", "heatindexi": "-9999", "vism": "16.1", "precipm": "-9999.00", "dewpti": "33.1", "fog": "0", "heatindexm": "-9999", "wgustm": "-9999.0", "icon": "cloudy", "visi": "10.0", "windchillm": "2.3", "conds": "Overcast", "windchilli": "36.1", "pressurei": "29.95", "tempm": "5.6", "hum": "70", "tempi": "42.1", "thunder": "0", "dewptm": "0.6", "wdire": "East", "utcdate": {"pretty": "10:53 PM GMT on December 15, 2015", "year": "2015", "mday": "15", "min": "53", "hour": "22", "tzname": "UTC", "mon": "12"}, "pressurem": "1014.1", "wdird": "90", "tornado": "0", "metar": "METAR KMDW 152253Z 09009KT 10SM OVC015 06/01 A2993 RMK AO2 SLP141 T00560006 $", "rain": "0", "hail": "0"}, {"wspdm": "13.0", "wspdi": "8.1", "snow": "0", "date": {"pretty": "5:53 PM CST on December 15, 2015", "year": "2015", "mday": "15", "min": "53", "hour": "17", "tzname": "America/Chicago", "mon": "12"}, "precipi": "-9999.00", "wgusti": "-9999.0", "heatindexi": "-9999", "vism": "16.1", "precipm": "-9999.00", "dewpti": "33.1", "fog": "0", "heatindexm": "-9999", "wgustm": "-9999.0", "icon": "cloudy", "visi": "10.0", "windchillm": "2.8", "conds": "Overcast", "windchilli": "37.1", "pressurei": "29.96", "tempm": "5.6", "hum": "70", "tempi": "42.1", "thunder": "0", "dewptm": "0.6", "wdire": "East", "utcdate": {"pretty": "11:53 PM GMT on December 15, 2015", "year": "2015", "mday": "15", "min": "53", "hour": "23", "tzname": "UTC", "mon": "12"}, "pressurem": "1014.5", "wdird": "80", "tornado": "0", "metar": "METAR KMDW 152353Z 08007KT 10SM OVC015 06/01 A2994 RMK AO2 SLP145 T00560006 10061 20050 51009 $", "rain": "0", "hail": "0"}, {"wspdm": "13.0", "wspdi": "8.1", "snow": "0", "date": {"pretty": "6:53 PM CST on December 15, 2015", "year": "2015", "mday": "15", "min": "53", "hour": "18", "tzname": "America/Chicago", "mon": "12"}, "precipi": "-9999.00", "wgusti": "-9999.0", "heatindexi": "-9999", "vism": "16.1", "precipm": "-9999.00", "dewpti": "34.0", "fog": "0", "heatindexm": "-9999", "wgustm": "-9999.0", "icon": "cloudy", "visi": "10.0", "windchillm": "2.8", "conds": "Overcast", "windchilli": "37.1", "pressurei": "29.95", "tempm": "5.6", "hum": "73", "tempi": "42.1", "thunder": "0", "dewptm": "1.1", "wdire": "East", "utcdate": {"pretty": "12:53 AM GMT on December 16, 2015", "year": "2015", "mday": "16", "min": "53", "hour": "00", "tzname": "UTC", "mon": "12"}, "pressurem": "1014.0", "wdird": "90", "tornado": "0", "metar": "METAR KMDW 160053Z 09007KT 10SM OVC015 06/01 A2993 RMK AO2 SLP140 T00560011 $", "rain": "0", "hail": "0"}, {"wspdm": "18.5", "wspdi": "11.5", "snow": "0", "date": {"pretty": "7:53 PM CST on December 15, 2015", "year": "2015", "mday": "15", "min": "53", "hour": "19", "tzname": "America/Chicago", "mon": "12"}, "precipi": "-9999.00", "wgusti": "-9999.0", "heatindexi": "-9999", "vism": "16.1", "precipm": "-9999.00", "dewpti": "34.0", "fog": "0", "heatindexm": "-9999", "wgustm": "-9999.0", "icon": "cloudy", "visi": "10.0", "windchillm": "2.0", "conds": "Overcast", "windchilli": "35.7", "pressurei": "29.93", "tempm": "5.6", "hum": "73", "tempi": "42.1", "thunder": "0", "dewptm": "1.1", "wdire": "SE", "utcdate": {"pretty": "1:53 AM GMT on December 16, 2015", "year": "2015", "mday": "16", "min": "53", "hour": "01", "tzname": "UTC", "mon": "12"}, "pressurem": "1013.5", "wdird": "130", "tornado": "0", "metar": "METAR KMDW 160153Z 13010KT 10SM OVC015 06/01 A2991 RMK AO2 SLP135 T00560011 $", "rain": "0", "hail": "0"}, {"wspdm": "18.5", "wspdi": "11.5", "snow": "0", "date": {"pretty": "8:53 PM CST on December 15, 2015", "year": "2015", "mday": "15", "min": "53", "hour": "20", "tzname": "America/Chicago", "mon": "12"}, "precipi": "-9999.00", "wgusti": "-9999.0", "heatindexi": "-9999", "vism": "16.1", "precipm": "-9999.00", "dewpti": "35.1", "fog": "0", "heatindexm": "-9999", "wgustm": "-9999.0", "icon": "cloudy", "visi": "10.0", "windchillm": "2.0", "conds": "Overcast", "windchilli": "35.7", "pressurei": "29.92", "tempm": "5.6", "hum": "76", "tempi": "42.1", "thunder": "0", "dewptm": "1.7", "wdire": "East", "utcdate": {"pretty": "2:53 AM GMT on December 16, 2015", "year": "2015", "mday": "16", "min": "53", "hour": "02", "tzname": "UTC", "mon": "12"}, "pressurem": "1013.1", "wdird": "100", "tornado": "0", "metar": "METAR KMDW 160253Z 10010KT 10SM OVC013 06/02 A2990 RMK AO2 SLP131 T00560017 56013 $", "rain": "0", "hail": "0"}, {"wspdm": "18.5", "wspdi": "11.5", "snow": "0", "date": {"pretty": "9:53 PM CST on December 15, 2015", "year": "2015", "mday": "15", "min": "53", "hour": "21", "tzname": "America/Chicago", "mon": "12"}, "precipi": "-9999.00", "wgusti": "-9999.0", "heatindexi": "-9999", "vism": "16.1", "precipm": "-9999.00", "dewpti": "36.0", "fog": "0", "heatindexm": "-9999", "wgustm": "-9999.0", "icon": "cloudy", "visi": "10.0", "windchillm": "2.7", "conds": "Overcast", "windchilli": "36.8", "pressurei": "29.90", "tempm": "6.1", "hum": "76", "tempi": "43.0", "thunder": "0", "dewptm": "2.2", "wdire": "SE", "utcdate": {"pretty": "3:53 AM GMT on December 16, 2015", "year": "2015", "mday": "16", "min": "53", "hour": "03", "tzname": "UTC", "mon": "12"}, "pressurem": "1012.4", "wdird": "130", "tornado": "0", "metar": "METAR KMDW 160353Z 13010KT 10SM OVC013 06/02 A2988 RMK AO2 SLP124 T00610022 $", "rain": "0", "hail": "0"}, {"wspdm": "18.5", "wspdi": "11.5", "snow": "0", "date": {"pretty": "10:53 PM CST on December 15, 2015", "year": "2015", "mday": "15", "min": "53", "hour": "22", "tzname": "America/Chicago", "mon": "12"}, "precipi": "-9999.00", "wgusti": "-9999.0", "heatindexi": "-9999", "vism": "16.1", "precipm": "-9999.00", "dewpti": "36.0", "fog": "0", "heatindexm": "-9999", "wgustm": "-9999.0", "icon": "cloudy", "visi": "10.0", "windchillm": "2.7", "conds": "Overcast", "windchilli": "36.8", "pressurei": "29.91", "tempm": "6.1", "hum": "76", "tempi": "43.0", "thunder": "0", "dewptm": "2.2", "wdire": "SE", "utcdate": {"pretty": "4:53 AM GMT on December 16, 2015", "year": "2015", "mday": "16", "min": "53", "hour": "04", "tzname": "UTC", "mon": "12"}, "pressurem": "1012.6", "wdird": "140", "tornado": "0", "metar": "METAR KMDW 160453Z 14010KT 10SM OVC012 06/02 A2989 RMK AO2 SLP126 T00610022 $", "rain": "0", "hail": "0"}, {"wspdm": "22.2", "wspdi": "13.8", "snow": "0", "date": {"pretty": "11:53 PM CST on December 15, 2015", "year": "2015", "mday": "15", "min": "53", "hour": "23", "tzname": "America/Chicago", "mon": "12"}, "precipi": "-9999.00", "wgusti": "21.9", "heatindexi": "-9999", "vism": "16.1", "precipm": "-9999.00", "dewpti": "36.0", "fog": "0", "heatindexm": "-9999", "wgustm": "35.2", "icon": "cloudy", "visi": "10.0", "windchillm": "2.2", "conds": "Overcast", "windchilli": "36.0", "pressurei": "29.91", "tempm": "6.1", "hum": "76", "tempi": "43.0", "thunder": "0", "dewptm": "2.2", "wdire": "SSE", "utcdate": {"pretty": "5:53 AM GMT on December 16, 2015", "year": "2015", "mday": "16", "min": "53", "hour": "05", "tzname": "UTC", "mon": "12"}, "pressurem": "1012.6", "wdird": "160", "tornado": "0", "metar": "METAR KMDW 160553Z 16012G19KT 10SM OVC011 06/02 A2988 RMK AO2 SLP126 T00610022 10061 20056 400670050 56005 $", "rain": "0", "hail": "0"}], "date": {"pretty": "December 15, 2015", "year": "2015", "mday": "15", "min": "00", "hour": "12", "tzname": "America/Chicago", "mon": "12"}, "utcdate": {"pretty": "December 15, 2015", "year": "2015", "mday": "15", "min": "00", "hour": "18", "tzname": "UTC", "mon": "12"}, "dailysummary": [{"heatingdegreedays": "22", "meantempi": "43", "snow": "0", "meanwindspdi": "9", "gdegreedays": "0", "precipm": "T", "heatingdegreedaysnormal": "36", "mintempm": "5", "mintempi": "41", "meanpressurem": "1011", "since1sepcoolingdegreedaysnormal": "", "maxpressurei": "29.96", "fog": "0", "monthtodatesnowfalli": "", "maxtempi": "44", "since1jancoolingdegreedaysnormal": "1045", "meandewptm": "2", "meanwindspdm": "14", "monthtodatesnowfallm": "", "since1julheatingdegreedaysnormal": "1642", "meandewpti": "35", "since1julsnowfalli": "", "snowfalli": "0.00", "snowdepthm": "", "meanvism": "16", "coolingdegreedays": "0", "precipi": "T", "monthtodateheatingdegreedaysnormal": "507", "meanvisi": "10", "minvisi": "9", "since1sepcoolingdegreedays": "", "maxtempm": "7", "since1julsnowfallm": "", "tornado": "0", "maxvisi": "10", "maxpressurem": "1014", "hail": "0", "maxwspdi": "16", "date": {"pretty": "12:00 PM CST on December 15, 2015", "year": "2015", "mday": "15", "min": "00", "hour": "12", "tzname": "America/Chicago", "mon": "12"}, "snowdepthi": "", "meantempm": "6", "rain": "0", "minwspdi": "4", "monthtodatecoolingdegreedaysnormal": "0", "minvism": "14", "coolingdegreedaysnormal": "0", "minhumidity": "57", "monthtodateheatingdegreedays": "300", "since1sepheatingdegreedays": "", "maxdewptm": "4", "mindewptm": "0", "minpressurem": "1002", "precipsource": "", "mindewpti": "32", "meanpressurei": "29.85", "since1sepheatingdegreedaysnormal": "", "since1julheatingdegreedays": "1110", "maxdewpti": "39", "meanwdird": "55", "minpressurei": "29.60", "thunder": "0", "monthtodatecoolingdegreedays": "0", "maxvism": "16", "maxwspdm": "26", "snowfallm": "0.00", "maxhumidity": "82", "meanwdire": "", "minwspdm": "6", "since1jancoolingdegreedays": "1152", "humidity": ""}]}}