{"response": {"version": "0.1", "termsofService": "http://www.wunderground.com/weather/api/d/terms.html", "features": {"history": 1}}, "history": {"observations": [{"wspdm": "7.4", "wspdi": "4.6", "snow": "0", "date": {"pretty": "12:53 AM CDT on June 07, 2015", "year": "2015", "mday": "07", "min": "53", "hour": "00", "tzname": "America/Chicago", "mon": "06"}, "precipi": "-9999.00", "wgusti": "-9999.0", "heatindexi": "-9999", "vism": "16.1", "precipm": "-9999.00", "dewpti": "51.1", "fog": "0", "heatindexm": "-9999", "wgustm": "-9999.0", "icon": "mostlycloudy", "visi": "10.0", "windchillm": "-999", "conds": "Mostly Cloudy", "windchilli": "-999", "pressurei": "29.96", "tempm": "15.6", "hum": "72", "tempi": "60.1", "thunder": "0", "dewptm": "10.6", "wdire": "ESE", "utcdate": {"pretty": "5:53 AM GMT on June 07, 2015", "year": "2015", "mday": "07", "min": "53", "hour": "05", "tzname": "UTC", "mon": "06"}, "pressurem": "1014.4", "wdird": "120", "tornado": "0", "metar": "METAR KMDW 070553Z 12004KT 10SM BKN250 16/11 A2997 RMK AO2 SLP144 T01560106 10194 20150 402280122 58012 $", "rain": "0", "hail": "0"}, {"wspdm": "5.6", "wspdi": "3.5", "snow": "0", "date": {"pretty": "1:53 AM CDT on June 07, 2015", "year": "2015", "mday": "07", "min": "53", "hour": "01", "tzname": "America/Chicago", "mon": "06"}, "precipi": "-9999.00", "wgusti": "-9999.0", "heatindexi": "-9999", "vism": "16.1", "precipm": "-9999.00", "dewpti": "52.0", "fog": "0", "heatindexm": "-9999", "wgustm": "-9999.0", "icon": "mostlycloudy", "visi": "10.0", "windchillm": "-999", "conds": "Mostly Cloudy", "windchilli": "-999", "pressurei": "29.93", "tempm": "15.6", "hum": "75", "tempi": "60.1", "thunder": "0", "dewptm": "11.1", "wdire": "SSE", "utcdate": {"pretty": "6:53 AM GMT on June 07, 2015", "year": "2015", "mday": "07", "min": "53", "hour": "06", "tzname": "UTC", "mon": "06"}, "pressurem": "1013.4", "wdird": "150", "tornado": "0", "metar": "METAR KMDW 070653Z 15003KT 10SM BKN250 16/11 A2994 RMK AO2 SLP134 T01560111 $", "rain": "0", "hail": "0"}, {"wspdm": "13.0", "wspdi": "8.1", "snow": "0", "date": {"pretty": "2:53 AM CDT on June 07, 2015", "year": "2015", "mday": "07", "min": "53", "hour": "02", "tzname": "America/Chicago", "mon": "06"}, "precipi": "-9999.00", "wgusti": "-9999.0", "heatindexi": "-9999", "vism": "16.1", "precipm": "-9999.00", "dewpti": "54.0", "fog": "0", "heatindexm": "-9999", "wgustm": "-9999.0", "icon": "mostlycloudy", "visi": "10.0", "windchillm": "-999", "conds": "Mostly Cloudy", "windchilli": "-999", "pressurei": "29.90", "tempm": "16.1", "hum": "78", "tempi": "61.0", "thunder": "0", "dewptm": "12.2", "wdire": "SE", "utcdate": {"pretty": "7:53 AM GMT on June 07, 2015", "year": "2015", "mday": "07", "min": "53", "hour": "07", "tzname": "UTC", "mon": "06"}, "pressurem": "1012.3", "wdird": "140", "tornado": "0", "metar": "METAR KMDW 070753Z 14007KT 10SM BKN250 16/12 A2991 RMK AO2 SLP123 T01610122 $", "rain": "0", "hail": "0"}, {"wspdm": "14.8", "wspdi": "9.2", "snow": "0", "date": {"pretty": "3:53 AM CDT on June 07, 2015", "year": "2015", "mday": "07", "min": "53", "hour": "03", "tzname": "America/Chicago", "mon": "06"}, "precipi": "-9999.00", "wgusti": "-9999.0", "heatindexi": "-9999", "vism": "16.1", "precipm": "-9999.00", "dewpti": "55.9", "fog": "0", "heatindexm": "-9999", "wgustm": "-9999.0", "icon": "mostlycloudy", "visi": "10.0", "windchillm": "-999", "conds": "Mostly Cloudy", "windchilli": "-999", "pressurei": "29.88", "tempm": "17.2", "hum": "78", "tempi": "63.0", "thunder": "0", "dewptm": "13.3", "wdire": "South", "utcdate": {"pretty": "8:53 AM GMT on June 07, 2015", "year": "2015", "mday": "07", "min": "53", "hour": "08", "tzname": "UTC", "mon": "06"}, "pressurem": "1011.7", "wdird": "170", "tornado": "0", "metar": "METAR KMDW 070853Z 17008KT 10SM BKN250 17/13 A2989 RMK AO2 SLP117 T01720133 56025 $", "rain": "0", "hail": "0"}, {"wspdm": "14.8", "wspdi": "9.2", "snow": "0", "date": {"pretty": "4:53 AM CDT on June 07, 2015", "year": "2015", "mday": "07", "min": "53", "hour": "04", "tzname": "America/Chicago", "mon": "06"}, "precipi": "-9999.00", "wgusti": "-9999.0", "heatindexi": "-9999", "vism": "14.5", "precipm": "-9999.00", "dewpti": "55.9", "fog": "0", "heatindexm": "-9999", "wgustm": "-9999.0", "icon": "mostlycloudy", "visi": "9.0", "windchillm": "-999", "conds": "Mostly Cloudy", "windchilli": "-999", "pressurei": "29.88", "tempm": "17.2", "hum": "78", "tempi": "63.0", "thunder": "0", "dewptm": "13.3", "wdire": "SSE", "utcdate": {"pretty": "9:53 AM GMT on June 07, 2015", "year": "2015", "mday": "07", "min": "53", "hour": "09", "tzname": "UTC", "mon": "06"}, "pressurem": "1011.6", "wdird": "160", "tornado": "0", "metar": "METAR KMDW 070953Z 16008KT 9SM FEW150 BKN250 17/13 A2989 RMK AO2 SLP116 T01720133 $", "rain": "0", "hail": "0"}, {"wspdm": "18.5", "wspdi": "11.5", "snow": "0", "date": {"pretty": "5:53 AM CDT on June 07, 2015", "year": "2015", "mday": "07", "min": "53", "hour": "05", "tzname": "America/Chicago", "mon": "06"}, "precipi": "-9999.00", "wgusti": "-9999.0", "heatindexi": "-9999", "vism": "12.9", "precipm": "-9999.00", "dewpti": "57.9", "fog": "0", "heatindexm": "-9999", "wgustm": "-9999.0", "icon": "mostlycloudy", "visi": "8.0", "windchillm": "-999", "conds": "Mostly Cloudy", "windchilli": "-999", "pressurei": "29.84", "tempm": "18.3", "hum": "78", "tempi": "64.9", "thunder": "0", "dewptm": "14.4", "wdire": "SSE", "utcdate": {"pretty": "10:53 AM GMT on June 07, 2015", "year": "2015", "mday": "07", "min": "53", "hour": "10", "tzname": "UTC", "mon": "06"}, "pressurem": "1010.5", "wdird": "160", "tornado": "0", "metar": "METAR KMDW 071053Z 16010KT 8SM BKN120 BKN250 18/14 A2986 RMK AO2 SLP105 T01830144 $", "rain": "0", "hail": "0"}, {"wspdm": "18.5", "wspdi": "11.5", "snow": "0", "date": {"pretty": "6:53 AM CDT on June 07, 2015", "year": "2015", "mday": "07", "min": "53", "hour": "06", "tzname": "America/Chicago", "mon": "06"}, "precipi": "-9999.00", "wgusti": "-9999.0", "heatindexi": "-9999", "vism": "14.5", "precipm": "-9999.00", "dewpti": "60.1", "fog": "0", "heatindexm": "-9999", "wgustm": "-9999.0", "icon": "cloudy", "visi": "9.0", "windchillm": "-999", "conds": "Overcast", "windchilli": "-999", "pressurei": "29.82", "tempm": "20.6", "hum": "73", "tempi": "69.1", "thunder": "0", "dewptm": "15.6", "wdire": "South", "utcdate": {"pretty": "11:53 AM GMT on June 07, 2015", "year": "2015", "mday": "07", "min": "53", "hour": "11", "tzname": "UTC", "mon": "06"}, "pressurem": "1009.6", "wdird": "180", "tornado": "0", "metar": "METAR KMDW 071153Z 18010KT 9SM BKN150 OVC250 21/16 A2983 RMK AO2 SLP096 T02060156 10206 20156 58020 $", "rain": "0", "hail": "0"}, {"wspdm": "24.1", "wspdi": "15.0", "snow": "0", "date": {"pretty": "7:53 AM CDT on June 07, 2015", "year": "2015", "mday": "07", "min": "53", "hour": "07", "tzname": "America/Chicago", "mon": "06"}, "precipi": "-9999.00", "wgusti": "-9999.0", "heatindexi": "-9999", "vism": "14.5", "precipm": "-9999.00", "dewpti": "60.1", "fog": "0", "heatindexm": "-9999", "wgustm": "-9999.0", "icon": "cloudy", "visi": "9.0", "windchillm": "-999", "conds": "Overcast", "windchilli": "-999", "pressurei": "29.80", "tempm": "21.1", "hum": "71", "tempi": "70.0", "thunder": "0", "dewptm": "15.6", "wdire": "South", "utcdate": {"pretty": "12:53 PM GMT on June 07, 2015", "year": "2015", "mday": "07", "min": "53", "hour": "12", "tzname": "UTC", "mon": "06"}, "pressurem": "1009.1", "wdird": "190", "tornado": "0", "metar": "METAR KMDW 071253Z 19013KT 9SM FEW040 BKN120 OVC250 21/16 A2982 RMK AO2 SLP091 T02110156 $", "rain": "0", "hail": "0"}, {"wspdm": "27.8", "wspdi": "17.3", "snow": "0", "date": {"pretty": "8:30 AM CDT on June 07, 2015", "year": "2015", "mday": "07", "min": "30", "hour": "08", "tzname": "America/Chicago", "mon": "06"}, "precipi": "0.00", "wgusti": "29.9", "heatindexi": "-9999", "vism": "16.1", "precipm": "0.0", "dewpti": "61.0", "fog": "0", "heatindexm": "-9999", "wgustm": "48.2", "icon": "rain", "visi": "10.0", "windchillm": "-999", "conds": "Rain", "windchilli": "-999", "pressurei": "29.88", "tempm": "21.1", "hum": "73", "tempi": "70.0", "thunder": "0", "dewptm": "16.1", "wdire": "West", "utcdate": {"pretty": "1:30 PM GMT on June 07, 2015", "year": "2015", "mday": "07", "min": "30", "hour": "13", "tzname": "UTC", "mon": "06"}, "pressurem": "1011.7", "wdird": "270", "tornado": "0", "metar": "SPECI KMDW 071330Z 27015G26KT 10SM RA SCT033 BKN170 OVC250 21/16 A2988 RMK AO2 PK WND 28026/1327 WSHFT 1310 RAB26 PRESRR P0000 T02110161 $", "rain": "1", "hail": "0"}, {"wspdm": "16.7", "wspdi": "10.4", "snow": "0", "date": {"pretty": "8:42 AM CDT on June 07, 2015", "year": "2015", "mday": "07", "min": "42", "hour": "08", "tzname": "America/Chicago", "mon": "06"}, "precipi": "0.13", "wgusti": "-9999.0", "heatindexi": "-9999", "vism": "2.8", "precipm": "3.3", "dewpti": "62.1", "fog": "0", "heatindexm": "-9999", "wgustm": "-9999.0", "icon": "rain", "visi": "1.8", "windchillm": "-999", "conds": "Heavy Rain", "windchilli": "-999", "pressurei": "29.88", "tempm": "20.0", "hum": "81", "tempi": "68.0", "thunder": "0", "dewptm": "16.7", "wdire": "WSW", "utcdate": {"pretty": "1:42 PM GMT on June 07, 2015", "year": "2015", "mday": "07", "min": "42", "hour": "13", "tzname": "UTC", "mon": "06"}, "pressurem": "1011.7", "wdird": "250", "tornado": "0", "metar": "SPECI KMDW 071342Z 25009KT 1 3/4SM R31C/4500VP6000FT +RA BKN024 OVC035 20/17 A2988 RMK AO2 PK WND 28026/1327 WSHFT 1310 RAB26 P0013 T02000167 $", "rain": "1", "hail": "0"}, {"wspdm": "16.7", "wspdi": "10.4", "snow": "0", "date": {"pretty": "8:53 AM CDT on June 07, 2015", "year": "2015", "mday": "07", "min": "53", "hour": "08", "tzname": "America/Chicago", "mon": "06"}, "precipi": "0.24", "wgusti": "-9999.0", "heatindexi": "-9999", "vism": "2.4", "precipm": "6.1", "dewpti": "63.0", "fog": "0", "heatindexm": "-9999", "wgustm": "-9999.0", "icon": "rain", "visi": "1.5", "windchillm": "-999", "conds": "Rain", "windchilli": "-999", "pressurei": "29.86", "tempm": "19.4", "hum": "87", "tempi": "66.9", "thunder": "0", "dewptm": "17.2", "wdire": "SW", "utcdate": {"pretty": "1:53 PM GMT on June 07, 2015", "year": "2015", "mday": "07", "min": "53", "hour": "13", "tzname": "UTC", "mon": "06"}, "pressurem": "1011.0", "wdird": "220", "tornado": "0", "metar": "METAR KMDW 071353Z 22009KT 1 1/2SM R31C/5000VP6000FT RA BR FEW023 BKN033 OVC050 19/17 A2987 RMK AO2 PK WND 28026/1327 WSHFT 1310 RAB26 SLP110 P0024 T01940172 $", "rain": "1", "hail": "0"}, {"wspdm": "22.2", "wspdi": "13.8", "snow": "0", "date": {"pretty": "9:05 AM CDT on June 07, 2015", "year": "2015", "mday": "07", "min": "05", "hour": "09", "tzname": "America/Chicago", "mon": "06"}, "precipi": "0.06", "wgusti": "-9999.0", "heatindexi": "-9999", "vism": "4.0", "precipm": "1.5", "dewpti": "64.0", "fog": "0", "heatindexm": "-9999", "wgustm": "-9999.0", "icon": "rain", "visi": "2.5", "windchillm": "-999", "conds": "Rain", "windchilli": "-999", "pressurei": "29.85", "tempm": "19.4", "hum": "90", "tempi": "66.9", "thunder": "0", "dewptm": "17.8", "wdire": "SSW", "utcdate": {"pretty": "2:05 PM GMT on June 07, 2015", "year": "2015", "mday": "07", "min": "05", "hour": "14", "tzname": "UTC", "mon": "06"}, "pressurem": "1010.7", "wdird": "200", "tornado": "0", "metar": "SPECI KMDW 071405Z 20012KT 2 1/2SM RA BR BKN037 BKN080 OVC100 19/18 A2985 RMK AO2 PRESFR P0006 T01940178 $", "rain": "1", "hail": "0"}, {"wspdm": "16.7", "wspdi": "10.4", "snow": "0", "date": {"pretty": "9:38 AM CDT on June 07, 2015", "year": "2015", "mday": "07", "min": "38", "hour": "09", "tzname": "America/Chicago", "mon": "06"}, "precipi": "0.17", "wgusti": "19.6", "heatindexi": "-9999", "vism": "4.8", "precipm": "4.3", "dewpti": "64.9", "fog": "0", "heatindexm": "-9999", "wgustm": "31.5", "icon": "rain", "visi": "3.0", "windchillm": "-999", "conds": "Light Rain", "windchilli": "-999", "pressurei": "29.80", "tempm": "20.0", "hum": "90", "tempi": "68.0", "thunder": "0", "dewptm": "18.3", "wdire": "South", "utcdate": {"pretty": "2:38 PM GMT on June 07, 2015", "year": "2015", "mday": "07", "min": "38", "hour": "14", "tzname": "UTC", "mon": "06"}, "pressurem": "1009.0", "wdird": "190", "tornado": "0", "metar": "SPECI KMDW 071438Z 19009G17KT 3SM -RA BR FEW070 BKN095 OVC110 20/18 A2980 RMK AO2 CB DSNT SE P0017 T02000183 $", "rain": "1", "hail": "0"}, {"wspdm": "20.4", "wspdi": "12.7", "snow": "0", "date": {"pretty": "9:53 AM CDT on June 07, 2015", "year": "2015", "mday": "07", "min": "53", "hour": "09", "tzname": "America/Chicago", "mon": "06"}, "precipi": "-9999.00", "wgusti": "-9999.0", "heatindexi": "-9999", "vism": "8.0", "precipm": "-9999.00", "dewpti": "64.4", "fog": "0", "heatindexm": "-9999", "wgustm": "-9999.0", "icon": "rain", "visi": "5.0", "windchillm": "-999", "conds": "Light Rain", "windchilli": "-999", "pressurei": "29.79", "tempm": "20.0", "hum": "88", "tempi": "68.0", "thunder": "0", "dewptm": "18.0", "wdire": "South", "utcdate": {"pretty": "2:53 PM GMT on June 07, 2015", "year": "2015", "mday": "07", "min": "53", "hour": "14", "tzname": "UTC", "mon": "06"}, "pressurem": "1008.7", "wdird": "180", "tornado": "0", "metar": "METAR KMDW 071453Z 18011KT 5SM -RA BR FEW010 SCT029 BKN080 OVC200 20/18 A2979", "rain": "1", "hail": "0"}, {"wspdm": "27.8", "wspdi": "17.3", "snow": "0", "date": {"pretty": "10:53 AM CDT on June 07, 2015", "year": "2015", "mday": "07", "min": "53", "hour": "10", "tzname": "America/Chicago", "mon": "06"}, "precipi": "0.00", "wgusti": "-9999.0", "heatindexi": "-9999", "vism": "9.7", "precipm": "0.0", "dewpti": "66.0", "fog": "0", "heatindexm": "-9999", "wgustm": "-9999.0", "icon": "rain", "visi": "6.0", "windchillm": "-999", "conds": "Light Rain", "windchilli": "-999", "pressurei": "29.78", "tempm": "21.1", "hum": "87", "tempi": "70.0", "thunder": "0", "dewptm": "18.9", "wdire": "SSW", "utcdate": {"pretty": "3:53 PM GMT on June 07, 2015", "year": "2015", "mday": "07", "min": "53", "hour": "15", "tzname": "UTC", "mon": "06"}, "pressurem": "1008.2", "wdird": "200", "tornado": "0", "metar": "METAR KMDW 071553Z COR 20015KT 6SM -RA BR SCT040CB BKN050 BKN110 OVC200 21/19 A2979 RMK AO2 RAE1459B31 SLP082 CB DSNT S MOV E P0000 T02110189 $", "rain": "1", "hail": "0"}, {"wspdm": "25.9", "wspdi": "16.1", "snow": "0", "date": {"pretty": "11:53 AM CDT on June 07, 2015", "year": "2015", "mday": "07", "min": "53", "hour": "11", "tzname": "America/Chicago", "mon": "06"}, "precipi": "0.03", "wgusti": "25.3", "heatindexi": "-9999", "vism": "14.5", "precipm": "0.8", "dewpti": "66.9", "fog": "0", "heatindexm": "-9999", "wgustm": "40.7", "icon": "cloudy", "visi": "9.0", "windchillm": "-999", "conds": "Overcast", "windchilli": "-999", "pressurei": "29.76", "tempm": "21.1", "hum": "90", "tempi": "70.0", "thunder": "0", "dewptm": "19.4", "wdire": "South", "utcdate": {"pretty": "4:53 PM GMT on June 07, 2015", "year": "2015", "mday": "07", "min": "53", "hour": "16", "tzname": "UTC", "mon": "06"}, "pressurem": "1007.8", "wdird": "190", "tornado": "0", "metar": "METAR KMDW 071653Z 19014G22KT 9SM BKN050 BKN065 OVC085 21/19 A2978 RMK AO2 PK WND 20027/1628 RAE18 SLP078 P0003 T02110194 $", "rain": "0", "hail": "0"}, {"wspdm": "24.1", "wspdi": "15.0", "snow": "0", "date": {"pretty": "12:53 PM CDT on June 07, 2015", "year": "2015", "mday": "07", "min": "53", "hour": "12", "tzname": "America/Chicago", "mon": "06"}, "precipi": "-9999.00", "wgusti": "19.6", "heatindexi": "-9999", "vism": "16.1", "precipm": "-9999.00", "dewpti": "66.9", "fog": "0", "heatindexm": "-9999", "wgustm": "31.5", "icon": "mostlycloudy", "visi": "10.0", "windchillm": "-999", "conds": "Mostly Cloudy", "windchilli": "-999", "pressurei": "29.75", "tempm": "22.8", "hum": "81", "tempi": "73.0", "thunder": "0", "dewptm": "19.4", "wdire": "South", "utcdate": {"pretty": "5:53 PM GMT on June 07, 2015", "year": "2015", "mday": "07", "min": "53", "hour": "17", "tzname": "UTC", "mon": "06"}, "pressurem": "1007.3", "wdird": "190", "tornado": "0", "metar": "METAR KMDW 071753Z 19013G17KT 10SM FEW034 BKN049 BKN060 23/19 A2977 RMK AO2 SLP073 60044 T02280194 10228 20194 58008 $", "rain": "0", "hail": "0"}, {"wspdm": "22.2", "wspdi": "13.8", "snow": "0", "date": {"pretty": "1:53 PM CDT on June 07, 2015", "year": "2015", "mday": "07", "min": "53", "hour": "13", "tzname": "America/Chicago", "mon": "06"}, "precipi": "-9999.00", "wgusti": "21.9", "heatindexi": "-9999", "vism": "16.1", "precipm": "-9999.00", "dewpti": "68.0", "fog": "0", "heatindexm": "-9999", "wgustm": "35.2", "icon": "cloudy", "visi": "10.0", "windchillm": "-999", "conds": "Overcast", "windchilli": "-999", "pressurei": "29.73", "tempm": "24.4", "hum": "76", "tempi": "75.9", "thunder": "0", "dewptm": "20.0", "wdire": "SSW", "utcdate": {"pretty": "6:53 PM GMT on June 07, 2015", "year": "2015", "mday": "07", "min": "53", "hour": "18", "tzname": "UTC", "mon": "06"}, "pressurem": "1006.7", "wdird": "200", "tornado": "0", "metar": "METAR KMDW 071853Z 20012G19KT 10SM FEW018 OVC039 24/20 A2975 RMK AO2 SLP067 T02440200 $", "rain": "0", "hail": "0"}, {"wspdm": "27.8", "wspdi": "17.3", "snow": "0", "date": {"pretty": "2:53 PM CDT on June 07, 2015", "year": "2015", "mday": "07", "min": "53", "hour": "14", "tzname": "America/Chicago", "mon": "06"}, "precipi": "-9999.00", "wgusti": "25.3", "heatindexi": "83.6", "vism": "16.1", "precipm": "-9999.00", "dewpti": "71.1", "fog": "0", "heatindexm": "28.6", "wgustm": "40.7", "icon": "mostlycloudy", "visi": "10.0", "windchillm": "-999", "conds": "Mostly Cloudy", "windchilli": "-999", "pressurei": "29.71", "tempm": "26.7", "hum": "74", "tempi": "80.1", "thunder": "0", "dewptm": "21.7", "wdire": "SSW", "utcdate": {"pretty": "7:53 PM GMT on June 07, 2015", "year": "2015", "mday": "07", "min": "53", "hour": "19", "tzname": "UTC", "mon": "06"}, "pressurem": "1005.9", "wdird": "210", "tornado": "0", "metar": "METAR KMDW 071953Z 21015G22KT 10SM SCT022 SCT029 BKN050 BKN250 27/22 A2973 RMK AO2 SLP059 CB DSNT SW T02670217 $", "rain": "0", "hail": "0"}, {"wspdm": "25.9", "wspdi": "16.1", "snow": "0", "date": {"pretty": "3:53 PM CDT on June 07, 2015", "year": "2015", "mday": "07", "min": "53", "hour": "15", "tzname": "America/Chicago", "mon": "06"}, "precipi": "-9999.00", "wgusti": "-9999.0", "heatindexi": "86.3", "vism": "16.1", "precipm": "-9999.00", "dewpti": "71.1", "fog": "0", "heatindexm": "30.2", "wgustm": "-9999.0", "icon": "mostlycloudy", "visi": "10.0", "windchillm": "-999", "conds": "Mostly Cloudy", "windchilli": "-999", "pressurei": "29.67", "tempm": "27.8", "hum": "69", "tempi": "82.0", "thunder": "0", "dewptm": "21.7", "wdire": "SW", "utcdate": {"pretty": "8:53 PM GMT on June 07, 2015", "year": "2015", "mday": "07", "min": "53", "hour": "20", "tzname": "UTC", "mon": "06"}, "pressurem": "1004.6", "wdird": "220", "tornado": "0", "metar": "METAR KMDW 072053Z 22014KT 10SM FEW022 SCT050 BKN065 BKN250 28/22 A2969 RMK AO2 PK WND 22026/1959 SLP046 CB DSNT SE-SW T02780217 58024 $", "rain": "0", "hail": "0"}, {"wspdm": "11.1", "wspdi": "6.9", "snow": "0", "date": {"pretty": "4:53 PM CDT on June 07, 2015", "year": "2015", "mday": "07", "min": "53", "hour": "16", "tzname": "America/Chicago", "mon": "06"}, "precipi": "-9999.00", "wgusti": "-9999.0", "heatindexi": "85.2", "vism": "16.1", "precipm": "-9999.00", "dewpti": "72.0", "fog": "0", "heatindexm": "29.6", "wgustm": "-9999.0", "icon": "cloudy", "visi": "10.0", "windchillm": "-999", "conds": "Overcast", "windchilli": "-999", "pressurei": "29.64", "tempm": "27.2", "hum": "74", "tempi": "81.0", "thunder": "0", "dewptm": "22.2", "wdire": "WSW", "utcdate": {"pretty": "9:53 PM GMT on June 07, 2015", "year": "2015", "mday": "07", "min": "53", "hour": "21", "tzname": "UTC", "mon": "06"}, "pressurem": "1003.7", "wdird": "240", "tornado": "0", "metar": "METAR KMDW 072153Z 24006KT 10SM SCT050 BKN065 BKN080 OVC250 27/22 A2966 RMK AO2 PRESFR SLP037 CB DSNT SE-SW T02720222 $", "rain": "0", "hail": "0"}, {"wspdm": "22.2", "wspdi": "13.8", "snow": "0", "date": {"pretty": "5:36 PM CDT on June 07, 2015", "year": "2015", "mday": "07", "min": "36", "hour": "17", "tzname": "America/Chicago", "mon": "06"}, "precipi": "-9999.00", "wgusti": "-9999.0", "heatindexi": "-9999", "vism": "16.1", "precipm": "-9999.00", "dewpti": "70.0", "fog": "0", "heatindexm": "-9999", "wgustm": "-9999.0", "icon": "cloudy", "visi": "10.0", "windchillm": "-999", "conds": "Overcast", "windchilli": "-999", "pressurei": "29.68", "tempm": "25.0", "hum": "79", "tempi": "77.0", "thunder": "0", "dewptm": "21.1", "wdire": "South", "utcdate": {"pretty": "10:36 PM GMT on June 07, 2015", "year": "2015", "mday": "07", "min": "36", "hour": "22", "tzname": "UTC", "mon": "06"}, "pressurem": "1005.0", "wdird": "170", "tornado": "0", "metar": "SPECI KMDW 072236Z 17012KT 10SM BKN021 BKN027 OVC033 25/21 A2968 RMK AO2 CB DSNT SE-SW T02500211 $", "rain": "0", "hail": "0"}, {"wspdm": "16.7", "wspdi": "10.4", "snow": "0", "date": {"pretty": "5:53 PM CDT on June 07, 2015", "year": "2015", "mday": "07", "min": "53", "hour": "17", "tzname": "America/Chicago", "mon": "06"}, "precipi": "-9999.00", "wgusti": "-9999.0", "heatindexi": "-9999", "vism": "16.1", "precipm": "-9999.00", "dewpti": "70.0", "fog": "0", "heatindexm": "-9999", "wgustm": "-9999.0", "icon": "cloudy", "visi": "10.0", "windchillm": "-999", "conds": "Overcast", "windchilli": "-999", "pressurei": "29.65", "tempm": "25.0", "hum": "79", "tempi": "77.0", "thunder": "0", "dewptm": "21.1", "wdire": "South", "utcdate": {"pretty": "10:53 PM GMT on June 07, 2015", "year": "2015", "mday": "07", "min": "53", "hour": "22", "tzname": "UTC", "mon": "06"}, "pressurem": "1003.8", "wdird": "170", "tornado": "0", "metar": "METAR KMDW 072253Z 17009KT 10SM SCT021 BKN047 OVC250 25/21 A2967 RMK AO2 SLP038 CB DSNT SE-SW T02500211 $", "rain": "0", "hail": "0"}, {"wspdm": "16.7", "wspdi": "10.4", "snow": "0", "date": {"pretty": "6:53 PM CDT on June 07, 2015", "year": "2015", "mday": "07", "min": "53", "hour": "18", "tzname": "America/Chicago", "mon": "06"}, "precipi": "-9999.00", "wgusti": "-9999.0", "heatindexi": "-9999", "vism": "16.1", "precipm": "-9999.00", "dewpti": "70.0", "fog": "0", "heatindexm": "-9999", "wgustm": "-9999.0", "icon": "cloudy", "visi": "10.0", "windchillm": "-999", "conds": "Overcast", "windchilli": "-999", "pressurei": "29.65", "tempm": "24.4", "hum": "82", "tempi": "75.9", "thunder": "0", "dewptm": "21.1", "wdire": "South", "utcdate": {"pretty": "11:53 PM GMT on June 07, 2015", "year": "2015", "mday": "07", "min": "53", "hour": "23", "tzname": "UTC", "mon": "06"}, "pressurem": "1004.1", "wdird": "170", "tornado": "0", "metar": "METAR KMDW 072353Z 17009KT 10SM FEW021 SCT047 BKN190 OVC250 24/21 A2968 RMK AO2 SLP041 CB DSNT N AND DSNT SE-S T02440211 10283 20228 55005 $", "rain": "0", "hail": "0"}, {"wspdm": "16.7", "wspdi": "10.4", "snow": "0", "date": {"pretty": "7:53 PM CDT on June 07, 2015", "year": "2015", "mday": "07", "min": "53", "hour": "19", "tzname": "America/Chicago", "mon": "06"}, "precipi": "-9999.00", "wgusti": "-9999.0", "heatindexi": "-9999", "vism": "16.1", "precipm": "-9999.00", "dewpti": "70.0", "fog": "0", "heatindexm": "-9999", "wgustm": "-9999.0", "icon": "cloudy", "visi": "10.0", "windchillm": "-999", "conds": "Overcast", "windchilli": "-999", "pressurei": "29.64", "tempm": "23.9", "hum": "84", "tempi": "75.0", "thunder": "0", "dewptm": "21.1", "wdire": "South", "utcdate": {"pretty": "12:53 AM GMT on June 08, 2015", "year": "2015", "mday": "08", "min": "53", "hour": "00", "tzname": "UTC", "mon": "06"}, "pressurem": "1003.7", "wdird": "190", "tornado": "0", "metar": "METAR KMDW 080053Z 19009KT 10SM FEW021 SCT047 BKN190 OVC230 24/21 A2967 RMK AO2 SLP037 CB DSNT NE AND DSNT SE-SW T02390211 $", "rain": "0", "hail": "0"}, {"wspdm": "14.8", "wspdi": "9.2", "snow": "0", "date": {"pretty": "8:53 PM CDT on June 07, 2015", "year": "2015", "mday": "07", "min": "53", "hour": "20", "tzname": "America/Chicago", "mon": "06"}, "precipi": "-9999.00", "wgusti": "-9999.0", "heatindexi": "-9999", "vism": "16.1", "precipm": "-9999.00", "dewpti": "69.1", "fog": "0", "heatindexm": "-9999", "wgustm": "-9999.0", "icon": "cloudy", "visi": "10.0", "windchillm": "-999", "conds": "Overcast", "windchilli": "-999", "pressurei": "29.67", "tempm": "23.9", "hum": "82", "tempi": "75.0", "thunder": "0", "dewptm": "20.6", "wdire": "South", "utcdate": {"pretty": "1:53 AM GMT on June 08, 2015", "year": "2015", "mday": "08", "min": "53", "hour": "01", "tzname": "UTC", "mon": "06"}, "pressurem": "1004.5", "wdird": "190", "tornado": "0", "metar": "METAR KMDW 080153Z 19008KT 10SM SCT035 BKN047 BKN190 OVC230 24/21 A2969 RMK AO2 SLP045 T02390206 $", "rain": "0", "hail": "0"}, {"wspdm": "14.8", "wspdi": "9.2", "snow": "0", "date": {"pretty": "9:53 PM CDT on June 07, 2015", "year": "2015", "mday": "07", "min": "53", "hour": "21", "tzname": "America/Chicago", "mon": "06"}, "precipi": "0.00", "wgusti": "19.6", "heatindexi": "-9999", "vism": "16.1", "precipm": "0.0", "dewpti": "66.9", "fog": "0", "heatindexm": "-9999", "wgustm": "31.5", "icon": "rain", "visi": "10.0", "windchillm": "-999", "conds": "Light Rain", "windchilli": "-999", "pressurei": "29.66", "tempm": "22.8", "hum": "81", "tempi": "73.0", "thunder": "0", "dewptm": "19.4", "wdire": "SSW", "utcdate": {"pretty": "2:53 AM GMT on June 08, 2015", "year": "2015", "mday": "08", "min": "53", "hour": "02", "tzname": "UTC", "mon": "06"}, "pressurem": "1004.3", "wdird": "200", "tornado": "0", "metar": "METAR KMDW 080253Z 20008G17KT 10SM -RA SCT035 BKN075 BKN120 OVC230 23/19 A2968 RMK AO2 RAB44 SLP043 P0000 60000 T02280194 53002 $", "rain": "1", "hail": "0"}, {"wspdm": "18.5", "wspdi": "11.5", "snow": "0", "date": {"pretty": "10:53 PM CDT on June 07, 2015", "year": "2015", "mday": "07", "min": "53", "hour": "22", "tzname": "America/Chicago", "mon": "06"}, "precipi": "0.00", "wgusti": "-9999.0", "heatindexi": "-9999", "vism": "16.1", "precipm": "0.0", "dewpti": "68.0", "fog": "0", "heatindexm": "-9999", "wgustm": "-9999.0", "icon": "cloudy", "visi": "10.0", "windchillm": "-999", "conds": "Overcast", "windchilli": "-999", "pressurei": "29.67", "tempm": "22.2", "hum": "87", "tempi": "72.0", "thunder": "0", "dewptm": "20.0", "wdire": "SSW", "utcdate": {"pretty": "3:53 AM GMT on June 08, 2015", "year": "2015", "mday": "08", "min": "53", "hour": "03", "tzname": "UTC", "mon": "06"}, "pressurem": "1004.6", "wdird": "210", "tornado": "0", "metar": "METAR KMDW 080353Z 21010KT 10SM SCT040 BKN075 BKN120 OVC200 22/20 A2969 RMK AO2 RAE22 SLP046 OCNL LTG DSNT W P0000 T02220200 $", "rain": "0", "hail": "0"}, {"wspdm": "11.1", "wspdi": "6.9", "snow": "0", "date": {"pretty": "11:53 PM CDT on June 07, 2015", "year": "2015", "mday": "07", "min": "53", "hour": "23", "tzname": "America/Chicago", "mon": "06"}, "precipi": "0.00", "wgusti": "-9999.0", "heatindexi": "-9999", "vism": "16.1", "precipm": "0.0", "dewpti": "68.0", "fog": "0", "heatindexm": "-9999", "wgustm": "-9999.0", "icon": "rain", "visi": "10.0", "windchillm": "-999", "conds": "Light Drizzle", "windchilli": "-999", "pressurei": "29.67", "tempm": "21.7", "hum": "90", "tempi": "71.1", "thunder": "0", "dewptm": "20.0", "wdire": "SSW", "utcdate": {"pretty": "4:53 AM GMT on June 08, 2015", "year": "2015", "mday": "08", "min": "53", "hour": "04", "tzname": "UTC", "mon": "06"}, "pressurem": "1004.6", "wdird": "210", "tornado": "0", "metar": "METAR KMDW 080453Z 21006KT 10SM -DZ SCT045 BKN070 BKN120 OVC150 22/20 A2969 RMK AO2 RAB31E50DZB50 SLP046 P0000 T02170200 $", "rain": "0", "hail": "0"}], "date": {"pretty": "June 7, 2015", "year": "2015", "mday": "07", "min": "00", "hour": "12", "tzname": "America/Chicago", "mon": "06"}, "utcdate": {"pretty": "June 7, 2015", "year": "2015", "mday": "07", "min": "00", "hour": "17", "tzname": "UTC", "mon": "06"}, "dailysummary": [{"heatingdegreedays": "0", "meantempi": "72", "snow": "0", "meanwindspdi": "12", "gdegreedays": "21", "precipm": "11.18", "heatingdegreedaysnormal": "2", "mintempm": "16", "mintempi": "60", "meanpressurem": "1008", "since1sepcoolingdegreedaysnormal": "", "maxpressurei": "29.96", "fog": "0", "monthtodatesnowfalli": "", "maxtempi": "83", "since1jancoolingdegreedaysnormal": "101", "meandewptm": "18", "meanwindspdm": "19", "monthtodatesnowfallm": "", "since1julheatingdegreedaysnormal": "5975", "meandewpti": "64", "since1julsnowfalli": "", "snowfalli": "0.00", "snowdepthm": "", "meanvism": "14", "coolingdegreedays": "7", "precipi": "0.44", "monthtodateheatingdegreedaysnormal": "16", "meanvisi": "8", "minvisi": "2", "since1sepcoolingdegreedays": "", "maxtempm": "28", "since1julsnowfallm": "", "tornado": "0", "maxvisi": "10", "maxpressurem": "1014", "hail": "0", "maxwspdi": "23", "date": {"pretty": "12:00 PM CDT on June 07, 2015", "year": "2015", "mday": "07", "min": "00", "hour": "12", "tzname": "America/Chicago", "mon": "06"}, "snowdepthi": "", "meantempm": "22", "rain": "1", "minwspdi": "4", "monthtodatecoolingdegreedaysnormal": "27", "minvism": "2", "coolingdegreedaysnormal": "5", "minhumidity": "62", "monthtodateheatingdegreedays": "18", "since1sepheatingdegreedays": "", "maxdewptm": "22", "mindewptm": "11", "minpressurem": "1004", "precipsource": "", "mindewpti": "51", "meanpressurei": "29.77", "since1sepheatingdegreedaysnormal": "", "since1julheatingdegreedays": "6081", "maxdewpti": "72", "meanwdird": "191", "minpressurei": "29.64", "thunder": "0", "monthtodatecoolingdegreedays": "16", "maxvism": "16", "maxwspdm": "37", "snowfallm": "0.00", "maxhumidity": "90", "meanwdire": "", "minwspdm": "6", "since1jancoolingdegreedays": "122", "humidity": ""}]}}