{"response": {"version": "0.1", "termsofService": "http://www.wunderground.com/weather/api/d/terms.html", "features": {"history": 1}}, "history": {"observations": [{"wspdm": "22.2", "wspdi": "13.8", "snow": "0", "date": {"pretty": "12:53 AM CST on December 11, 2015", "year": "2015", "mday": "11", "min": "53", "hour": "00", "tzname": "America/Chicago", "mon": "12"}, "precipi": "-9999.00", "wgusti": "25.3", "heatindexi": "-9999", "vism": "16.1", "precipm": "-9999.00", "dewpti": "35.1", "fog": "0", "heatindexm": "-9999", "wgustm": "40.7", "icon": "mostlycloudy", "visi": "10.0", "windchillm": "-999", "conds": "Mostly Cloudy", "windchilli": "-999", "pressurei": "29.63", "tempm": "9.4", "hum": "59", "tempi": "48.9", "thunder": "0", "dewptm": "1.7", "wdire": "WSW", "utcdate": {"pretty": "6:53 AM GMT on December 11, 2015", "year": "2015", "mday": "11", "min": "53", "hour": "06", "tzname": "UTC", "mon": "12"}, "pressurem": "1003.3", "wdird": "240", "tornado": "0", "metar": "METAR KMDW 110653Z 24012G22KT 10SM BKN250 09/02 A2963 RMK AO2 SLP033 T00940017", "rain": "0", "hail": "0"}, {"wspdm": "18.5", "wspdi": "11.5", "snow": "0", "date": {"pretty": "1:53 AM CST on December 11, 2015", "year": "2015", "mday": "11", "min": "53", "hour": "01", "tzname": "America/Chicago", "mon": "12"}, "precipi": "-9999.00", "wgusti": "-9999.0", "heatindexi": "-9999", "vism": "16.1", "precipm": "-9999.00", "dewpti": "33.1", "fog": "0", "heatindexm": "-9999", "wgustm": "-9999.0", "icon": "clear", "visi": "10.0", "windchillm": "-999", "conds": "Clear", "windchilli": "-999", "pressurei": "29.65", "tempm": "9.4", "hum": "54", "tempi": "48.9", "thunder": "0", "dewptm": "0.6", "wdire": "SW", "utcdate": {"pretty": "7:53 AM GMT on December 11, 2015", "year": "2015", "mday": "11", "min": "53", "hour": "07", "tzname": "UTC", "mon": "12"}, "pressurem": "1003.8", "wdird": "230", "tornado": "0", "metar": "METAR KMDW 110753Z 23010KT 10SM CLR 09/01 A2964 RMK AO2 SLP038 T00940006", "rain": "0", "hail": "0"}, {"wspdm": "16.7", "wspdi": "10.4", "snow": "0", "date": {"pretty": "2:53 AM CST on December 11, 2015", "year": "2015", "mday": "11", "min": "53", "hour": "02", "tzname": "America/Chicago", "mon": "12"}, "precipi": "-9999.00", "wgusti": "-9999.0", "heatindexi": "-9999", "vism": "16.1", "precipm": "-9999.00", "dewpti": "34.0", "fog": "0", "heatindexm": "-9999", "wgustm": "-9999.0", "icon": "clear", "visi": "10.0", "windchillm": "-999", "conds": "Clear", "windchilli": "-999", "pressurei": "29.66", "tempm": "8.3", "hum": "61", "tempi": "46.9", "thunder": "0", "dewptm": "1.1", "wdire": "SSW", "utcdate": {"pretty": "8:53 AM GMT on December 11, 2015", "year": "2015", "mday": "11", "min": "53", "hour": "08", "tzname": "UTC", "mon": "12"}, "pressurem": "1004.2", "wdird": "210", "tornado": "0", "metar": "METAR KMDW 110853Z 21009KT 10SM CLR 08/01 A2965 RMK AO2 SLP042 T00830011 53007", "rain": "0", "hail": "0"}, {"wspdm": "22.2", "wspdi": "13.8", "snow": "0", "date": {"pretty": "3:53 AM CST on December 11, 2015", "year": "2015", "mday": "11", "min": "53", "hour": "03", "tzname": "America/Chicago", "mon": "12"}, "precipi": "-9999.00", "wgusti": "20.7", "heatindexi": "-9999", "vism": "16.1", "precipm": "-9999.00", "dewpti": "33.1", "fog": "0", "heatindexm": "-9999", "wgustm": "33.3", "icon": "clear", "visi": "10.0", "windchillm": "-999", "conds": "Clear", "windchilli": "-999", "pressurei": "29.68", "tempm": "9.4", "hum": "54", "tempi": "48.9", "thunder": "0", "dewptm": "0.6", "wdire": "West", "utcdate": {"pretty": "9:53 AM GMT on December 11, 2015", "year": "2015", "mday": "11", "min": "53", "hour": "09", "tzname": "UTC", "mon": "12"}, "pressurem": "1004.8", "wdird": "260", "tornado": "0", "metar": "METAR KMDW 110953Z 26012G18KT 10SM CLR 09/01 A2967 RMK AO2 SLP048 T00940006", "rain": "0", "hail": "0"}, {"wspdm": "24.1", "wspdi": "15.0", "snow": "0", "date": {"pretty": "4:53 AM CST on December 11, 2015", "year": "2015", "mday": "11", "min": "53", "hour": "04", "tzname": "America/Chicago", "mon": "12"}, "precipi": "-9999.00", "wgusti": "-9999.0", "heatindexi": "-9999", "vism": "16.1", "precipm": "-9999.00", "dewpti": "33.1", "fog": "0", "heatindexm": "-9999", "wgustm": "-9999.0", "icon": "partlycloudy", "visi": "10.0", "windchillm": "-999", "conds": "Partly Cloudy", "windchilli": "-999", "pressurei": "29.70", "tempm": "8.3", "hum": "59", "tempi": "46.9", "thunder": "0", "dewptm": "0.6", "wdire": "WSW", "utcdate": {"pretty": "10:53 AM GMT on December 11, 2015", "year": "2015", "mday": "11", "min": "53", "hour": "10", "tzname": "UTC", "mon": "12"}, "pressurem": "1005.6", "wdird": "250", "tornado": "0", "metar": "METAR KMDW 111053Z 25013KT 10SM FEW250 08/01 A2969 RMK AO2 SLP056 T00830006", "rain": "0", "hail": "0"}, {"wspdm": "18.5", "wspdi": "11.5", "snow": "0", "date": {"pretty": "5:53 AM CST on December 11, 2015", "year": "2015", "mday": "11", "min": "53", "hour": "05", "tzname": "America/Chicago", "mon": "12"}, "precipi": "-9999.00", "wgusti": "-9999.0", "heatindexi": "-9999", "vism": "16.1", "precipm": "-9999.00", "dewpti": "32.0", "fog": "0", "heatindexm": "-9999", "wgustm": "-9999.0", "icon": "mostlycloudy", "visi": "10.0", "windchillm": "4.8", "conds": "Mostly Cloudy", "windchilli": "40.6", "pressurei": "29.73", "tempm": "7.8", "hum": "58", "tempi": "46.0", "thunder": "0", "dewptm": "0.0", "wdire": "WSW", "utcdate": {"pretty": "11:53 AM GMT on December 11, 2015", "year": "2015", "mday": "11", "min": "53", "hour": "11", "tzname": "UTC", "mon": "12"}, "pressurem": "1006.8", "wdird": "250", "tornado": "0", "metar": "METAR KMDW 111153Z 25010KT 10SM BKN160 08/00 A2972 RMK AO2 SLP068 T00780000 10094 20078 53024", "rain": "0", "hail": "0"}, {"wspdm": "11.1", "wspdi": "6.9", "snow": "0", "date": {"pretty": "6:53 AM CST on December 11, 2015", "year": "2015", "mday": "11", "min": "53", "hour": "06", "tzname": "America/Chicago", "mon": "12"}, "precipi": "-9999.00", "wgusti": "-9999.0", "heatindexi": "-9999", "vism": "16.1", "precipm": "-9999.00", "dewpti": "32.0", "fog": "0", "heatindexm": "-9999", "wgustm": "-9999.0", "icon": "mostlycloudy", "visi": "10.0", "windchillm": "5.1", "conds": "Mostly Cloudy", "windchilli": "41.2", "pressurei": "29.76", "tempm": "7.2", "hum": "60", "tempi": "45.0", "thunder": "0", "dewptm": "0.0", "wdire": "WSW", "utcdate": {"pretty": "12:53 PM GMT on December 11, 2015", "year": "2015", "mday": "11", "min": "53", "hour": "12", "tzname": "UTC", "mon": "12"}, "pressurem": "1007.7", "wdird": "240", "tornado": "0", "metar": "METAR KMDW 111253Z 24006KT 10SM BKN150 BKN200 07/00 A2975 RMK AO2 SLP077 T00720000", "rain": "0", "hail": "0"}, {"wspdm": "11.1", "wspdi": "6.9", "snow": "0", "date": {"pretty": "7:53 AM CST on December 11, 2015", "year": "2015", "mday": "11", "min": "53", "hour": "07", "tzname": "America/Chicago", "mon": "12"}, "precipi": "-9999.00", "wgusti": "-9999.0", "heatindexi": "-9999", "vism": "16.1", "precipm": "-9999.00", "dewpti": "32.0", "fog": "0", "heatindexm": "-9999", "wgustm": "-9999.0", "icon": "mostlycloudy", "visi": "10.0", "windchillm": "4.5", "conds": "Mostly Cloudy", "windchilli": "40.1", "pressurei": "29.79", "tempm": "6.7", "hum": "63", "tempi": "44.1", "thunder": "0", "dewptm": "0.0", "wdire": "SW", "utcdate": {"pretty": "1:53 PM GMT on December 11, 2015", "year": "2015", "mday": "11", "min": "53", "hour": "13", "tzname": "UTC", "mon": "12"}, "pressurem": "1008.7", "wdird": "220", "tornado": "0", "metar": "METAR KMDW 111353Z 22006KT 10SM FEW120 SCT180 BKN250 07/00 A2978 RMK AO2 SLP087 T00670000", "rain": "0", "hail": "0"}, {"wspdm": "14.8", "wspdi": "9.2", "snow": "0", "date": {"pretty": "8:53 AM CST on December 11, 2015", "year": "2015", "mday": "11", "min": "53", "hour": "08", "tzname": "America/Chicago", "mon": "12"}, "precipi": "-9999.00", "wgusti": "-9999.0", "heatindexi": "-9999", "vism": "16.1", "precipm": "-9999.00", "dewpti": "33.1", "fog": "0", "heatindexm": "-9999", "wgustm": "-9999.0", "icon": "mostlycloudy", "visi": "10.0", "windchillm": "5.2", "conds": "Mostly Cloudy", "windchilli": "41.4", "pressurei": "29.81", "tempm": "7.8", "hum": "61", "tempi": "46.0", "thunder": "0", "dewptm": "0.6", "wdire": "SW", "utcdate": {"pretty": "2:53 PM GMT on December 11, 2015", "year": "2015", "mday": "11", "min": "53", "hour": "14", "tzname": "UTC", "mon": "12"}, "pressurem": "1009.5", "wdird": "230", "tornado": "0", "metar": "METAR KMDW 111453Z 23008KT 10SM FEW120 SCT170 BKN250 08/01 A2980 RMK AO2 SLP095 T00780006 51025", "rain": "0", "hail": "0"}, {"wspdm": "13.0", "wspdi": "8.1", "snow": "0", "date": {"pretty": "9:53 AM CST on December 11, 2015", "year": "2015", "mday": "11", "min": "53", "hour": "09", "tzname": "America/Chicago", "mon": "12"}, "precipi": "-9999.00", "wgusti": "-9999.0", "heatindexi": "-9999", "vism": "16.1", "precipm": "-9999.00", "dewpti": "32.0", "fog": "0", "heatindexm": "-9999", "wgustm": "-9999.0", "icon": "mostlycloudy", "visi": "10.0", "windchillm": "-999", "conds": "Mostly Cloudy", "windchilli": "-999", "pressurei": "29.84", "tempm": "8.9", "hum": "54", "tempi": "48.0", "thunder": "0", "dewptm": "0.0", "wdire": "SSW", "utcdate": {"pretty": "3:53 PM GMT on December 11, 2015", "year": "2015", "mday": "11", "min": "53", "hour": "15", "tzname": "UTC", "mon": "12"}, "pressurem": "1010.5", "wdird": "200", "tornado": "0", "metar": "METAR KMDW 111553Z 20007KT 10SM BKN200 BKN250 09/00 A2983 RMK AO2 SLP105 T00890000", "rain": "0", "hail": "0"}, {"wspdm": "13.0", "wspdi": "8.1", "snow": "0", "date": {"pretty": "10:53 AM CST on December 11, 2015", "year": "2015", "mday": "11", "min": "53", "hour": "10", "tzname": "America/Chicago", "mon": "12"}, "precipi": "-9999.00", "wgusti": "-9999.0", "heatindexi": "-9999", "vism": "16.1", "precipm": "-9999.00", "dewpti": "33.1", "fog": "0", "heatindexm": "-9999", "wgustm": "-9999.0", "icon": "mostlycloudy", "visi": "10.0", "windchillm": "-999", "conds": "Mostly Cloudy", "windchilli": "-999", "pressurei": "29.85", "tempm": "9.4", "hum": "54", "tempi": "48.9", "thunder": "0", "dewptm": "0.6", "wdire": "WSW", "utcdate": {"pretty": "4:53 PM GMT on December 11, 2015", "year": "2015", "mday": "11", "min": "53", "hour": "16", "tzname": "UTC", "mon": "12"}, "pressurem": "1010.6", "wdird": "250", "tornado": "0", "metar": "METAR KMDW 111653Z 25007KT 10SM FEW110 BKN200 BKN250 09/01 A2983 RMK AO2 SLP106 T00940006", "rain": "0", "hail": "0"}, {"wspdm": "9.3", "wspdi": "5.8", "snow": "0", "date": {"pretty": "11:53 AM CST on December 11, 2015", "year": "2015", "mday": "11", "min": "53", "hour": "11", "tzname": "America/Chicago", "mon": "12"}, "precipi": "-9999.00", "wgusti": "-9999.0", "heatindexi": "-9999", "vism": "16.1", "precipm": "-9999.00", "dewpti": "34.0", "fog": "0", "heatindexm": "-9999", "wgustm": "-9999.0", "icon": "cloudy", "visi": "10.0", "windchillm": "-999", "conds": "Overcast", "windchilli": "-999", "pressurei": "29.83", "tempm": "10.6", "hum": "52", "tempi": "51.1", "thunder": "0", "dewptm": "1.1", "wdire": "Variable", "utcdate": {"pretty": "5:53 PM GMT on December 11, 2015", "year": "2015", "mday": "11", "min": "53", "hour": "17", "tzname": "UTC", "mon": "12"}, "pressurem": "1010.0", "wdird": "0", "tornado": "0", "metar": "METAR KMDW 111753Z VRB05KT 10SM FEW110 BKN180 OVC250 11/01 A2982 RMK AO2 SLP100 T01060011 10106 20067 50007", "rain": "0", "hail": "0"}, {"wspdm": "0.0", "wspdi": "0.0", "snow": "0", "date": {"pretty": "12:53 PM CST on December 11, 2015", "year": "2015", "mday": "11", "min": "53", "hour": "12", "tzname": "America/Chicago", "mon": "12"}, "precipi": "-9999.00", "wgusti": "-9999.0", "heatindexi": "-9999", "vism": "16.1", "precipm": "-9999.00", "dewpti": "33.1", "fog": "0", "heatindexm": "-9999", "wgustm": "-9999.0", "icon": "cloudy", "visi": "10.0", "windchillm": "-999", "conds": "Overcast", "windchilli": "-999", "pressurei": "29.82", "tempm": "11.1", "hum": "49", "tempi": "52.0", "thunder": "0", "dewptm": "0.6", "wdire": "North", "utcdate": {"pretty": "6:53 PM GMT on December 11, 2015", "year": "2015", "mday": "11", "min": "53", "hour": "18", "tzname": "UTC", "mon": "12"}, "pressurem": "1009.7", "wdird": "0", "tornado": "0", "metar": "METAR KMDW 111853Z 00000KT 10SM BKN190 OVC250 11/01 A2981 RMK AO2 SLP097 T01110006", "rain": "0", "hail": "0"}, {"wspdm": "7.4", "wspdi": "4.6", "snow": "0", "date": {"pretty": "1:53 PM CST on December 11, 2015", "year": "2015", "mday": "11", "min": "53", "hour": "13", "tzname": "America/Chicago", "mon": "12"}, "precipi": "-9999.00", "wgusti": "-9999.0", "heatindexi": "-9999", "vism": "16.1", "precipm": "-9999.00", "dewpti": "33.1", "fog": "0", "heatindexm": "-9999", "wgustm": "-9999.0", "icon": "mostlycloudy", "visi": "10.0", "windchillm": "-999", "conds": "Mostly Cloudy", "windchilli": "-999", "pressurei": "29.81", "tempm": "11.7", "hum": "47", "tempi": "53.1", "thunder": "0", "dewptm": "0.6", "wdire": "Variable", "utcdate": {"pretty": "7:53 PM GMT on December 11, 2015", "year": "2015", "mday": "11", "min": "53", "hour": "19", "tzname": "UTC", "mon": "12"}, "pressurem": "1009.5", "wdird": "0", "tornado": "0", "metar": "METAR KMDW 111953Z VRB04KT 10SM FEW110 FEW150 BKN190 BKN250 12/01 A2981 RMK AO2 SLP095 T01170006", "rain": "0", "hail": "0"}, {"wspdm": "7.4", "wspdi": "4.6", "snow": "0", "date": {"pretty": "2:53 PM CST on December 11, 2015", "year": "2015", "mday": "11", "min": "53", "hour": "14", "tzname": "America/Chicago", "mon": "12"}, "precipi": "-9999.00", "wgusti": "-9999.0", "heatindexi": "-9999", "vism": "16.1", "precipm": "-9999.00", "dewpti": "34.0", "fog": "0", "heatindexm": "-9999", "wgustm": "-9999.0", "icon": "mostlycloudy", "visi": "10.0", "windchillm": "-999", "conds": "Mostly Cloudy", "windchilli": "-999", "pressurei": "29.82", "tempm": "12.2", "hum": "47", "tempi": "54.0", "thunder": "0", "dewptm": "1.1", "wdire": "ESE", "utcdate": {"pretty": "8:53 PM GMT on December 11, 2015", "year": "2015", "mday": "11", "min": "53", "hour": "20", "tzname": "UTC", "mon": "12"}, "pressurem": "1009.6", "wdird": "120", "tornado": "0", "metar": "METAR KMDW 112053Z 12004KT 10SM FEW110 SCT150 BKN220 BKN250 12/01 A2981 RMK AO2 SLP096 T01220011 55004", "rain": "0", "hail": "0"}, {"wspdm": "9.3", "wspdi": "5.8", "snow": "0", "date": {"pretty": "3:53 PM CST on December 11, 2015", "year": "2015", "mday": "11", "min": "53", "hour": "15", "tzname": "America/Chicago", "mon": "12"}, "precipi": "-9999.00", "wgusti": "-9999.0", "heatindexi": "-9999", "vism": "16.1", "precipm": "-9999.00", "dewpti": "35.1", "fog": "0", "heatindexm": "-9999", "wgustm": "-9999.0", "icon": "cloudy", "visi": "10.0", "windchillm": "-999", "conds": "Overcast", "windchilli": "-999", "pressurei": "29.83", "tempm": "12.2", "hum": "49", "tempi": "54.0", "thunder": "0", "dewptm": "1.7", "wdire": "ESE", "utcdate": {"pretty": "9:53 PM GMT on December 11, 2015", "year": "2015", "mday": "11", "min": "53", "hour": "21", "tzname": "UTC", "mon": "12"}, "pressurem": "1010.1", "wdird": "120", "tornado": "0", "metar": "METAR KMDW 112153Z 12005KT 10SM FEW170 BKN190 OVC250 12/02 A2983 RMK AO2 SLP101 T01220017", "rain": "0", "hail": "0"}, {"wspdm": "9.3", "wspdi": "5.8", "snow": "0", "date": {"pretty": "4:53 PM CST on December 11, 2015", "year": "2015", "mday": "11", "min": "53", "hour": "16", "tzname": "America/Chicago", "mon": "12"}, "precipi": "-9999.00", "wgusti": "-9999.0", "heatindexi": "-9999", "vism": "16.1", "precipm": "-9999.00", "dewpti": "36.0", "fog": "0", "heatindexm": "-9999", "wgustm": "-9999.0", "icon": "cloudy", "visi": "10.0", "windchillm": "-999", "conds": "Overcast", "windchilli": "-999", "pressurei": "29.85", "tempm": "12.2", "hum": "51", "tempi": "54.0", "thunder": "0", "dewptm": "2.2", "wdire": "ESE", "utcdate": {"pretty": "10:53 PM GMT on December 11, 2015", "year": "2015", "mday": "11", "min": "53", "hour": "22", "tzname": "UTC", "mon": "12"}, "pressurem": "1010.6", "wdird": "120", "tornado": "0", "metar": "METAR KMDW 112253Z 12005KT 10SM BKN180 OVC250 12/02 A2984 RMK AO2 SLP106 T01220022", "rain": "0", "hail": "0"}, {"wspdm": "9.3", "wspdi": "5.8", "snow": "0", "date": {"pretty": "5:53 PM CST on December 11, 2015", "year": "2015", "mday": "11", "min": "53", "hour": "17", "tzname": "America/Chicago", "mon": "12"}, "precipi": "-9999.00", "wgusti": "-9999.0", "heatindexi": "-9999", "vism": "16.1", "precipm": "-9999.00", "dewpti": "36.0", "fog": "0", "heatindexm": "-9999", "wgustm": "-9999.0", "icon": "mostlycloudy", "visi": "10.0", "windchillm": "-999", "conds": "Mostly Cloudy", "windchilli": "-999", "pressurei": "29.84", "tempm": "10.6", "hum": "56", "tempi": "51.1", "thunder": "0", "dewptm": "2.2", "wdire": "East", "utcdate": {"pretty": "11:53 PM GMT on December 11, 2015", "year": "2015", "mday": "11", "min": "53", "hour": "23", "tzname": "UTC", "mon": "12"}, "pressurem": "1010.3", "wdird": "80", "tornado": "0", "metar": "METAR KMDW 112353Z 08005KT 10SM BKN180 BKN230 11/02 A2983 RMK AO2 SLP103 T01060022 10128 20106 50006", "rain": "0", "hail": "0"}, {"wspdm": "11.1", "wspdi": "6.9", "snow": "0", "date": {"pretty": "6:53 PM CST on December 11, 2015", "year": "2015", "mday": "11", "min": "53", "hour": "18", "tzname": "America/Chicago", "mon": "12"}, "precipi": "-9999.00", "wgusti": "-9999.0", "heatindexi": "-9999", "vism": "16.1", "precipm": "-9999.00", "dewpti": "37.0", "fog": "0", "heatindexm": "-9999", "wgustm": "-9999.0", "icon": "cloudy", "visi": "10.0", "windchillm": "-999", "conds": "Overcast", "windchilli": "-999", "pressurei": "29.83", "tempm": "10.0", "hum": "61", "tempi": "50.0", "thunder": "0", "dewptm": "2.8", "wdire": "East", "utcdate": {"pretty": "12:53 AM GMT on December 12, 2015", "year": "2015", "mday": "12", "min": "53", "hour": "00", "tzname": "UTC", "mon": "12"}, "pressurem": "1010.0", "wdird": "100", "tornado": "0", "metar": "METAR KMDW 120053Z 10006KT 10SM FEW047 OVC200 10/03 A2982 RMK AO2 SLP100 T01000028", "rain": "0", "hail": "0"}, {"wspdm": "11.1", "wspdi": "6.9", "snow": "0", "date": {"pretty": "7:53 PM CST on December 11, 2015", "year": "2015", "mday": "11", "min": "53", "hour": "19", "tzname": "America/Chicago", "mon": "12"}, "precipi": "-9999.00", "wgusti": "-9999.0", "heatindexi": "-9999", "vism": "16.1", "precipm": "-9999.00", "dewpti": "39.0", "fog": "0", "heatindexm": "-9999", "wgustm": "-9999.0", "icon": "cloudy", "visi": "10.0", "windchillm": "-999", "conds": "Overcast", "windchilli": "-999", "pressurei": "29.84", "tempm": "11.1", "hum": "61", "tempi": "52.0", "thunder": "0", "dewptm": "3.9", "wdire": "East", "utcdate": {"pretty": "1:53 AM GMT on December 12, 2015", "year": "2015", "mday": "12", "min": "53", "hour": "01", "tzname": "UTC", "mon": "12"}, "pressurem": "1010.4", "wdird": "80", "tornado": "0", "metar": "METAR KMDW 120153Z 08006KT 10SM BKN019 OVC050 11/04 A2983 RMK AO2 SLP104 T01110039", "rain": "0", "hail": "0"}, {"wspdm": "13.0", "wspdi": "8.1", "snow": "0", "date": {"pretty": "8:25 PM CST on December 11, 2015", "year": "2015", "mday": "11", "min": "25", "hour": "20", "tzname": "America/Chicago", "mon": "12"}, "precipi": "-9999.00", "wgusti": "-9999.0", "heatindexi": "-9999", "vism": "16.1", "precipm": "-9999.00", "dewpti": "39.9", "fog": "0", "heatindexm": "-9999", "wgustm": "-9999.0", "icon": "cloudy", "visi": "10.0", "windchillm": "-999", "conds": "Overcast", "windchilli": "-999", "pressurei": "29.83", "tempm": "11.7", "hum": "61", "tempi": "53.1", "thunder": "0", "dewptm": "4.4", "wdire": "East", "utcdate": {"pretty": "2:25 AM GMT on December 12, 2015", "year": "2015", "mday": "12", "min": "25", "hour": "02", "tzname": "UTC", "mon": "12"}, "pressurem": "1010.0", "wdird": "80", "tornado": "0", "metar": "SPECI KMDW 120225Z 08007KT 10SM OVC014 12/04 A2983 RMK AO2 T01170044", "rain": "0", "hail": "0"}, {"wspdm": "11.1", "wspdi": "6.9", "snow": "0", "date": {"pretty": "8:53 PM CST on December 11, 2015", "year": "2015", "mday": "11", "min": "53", "hour": "20", "tzname": "America/Chicago", "mon": "12"}, "precipi": "0.00", "wgusti": "-9999.0", "heatindexi": "-9999", "vism": "11.3", "precipm": "0.0", "dewpti": "42.1", "fog": "0", "heatindexm": "-9999", "wgustm": "-9999.0", "icon": "rain", "visi": "7.0", "windchillm": "-999", "conds": "Light Drizzle", "windchilli": "-999", "pressurei": "29.84", "tempm": "11.1", "hum": "69", "tempi": "52.0", "thunder": "0", "dewptm": "5.6", "wdire": "East", "utcdate": {"pretty": "2:53 AM GMT on December 12, 2015", "year": "2015", "mday": "12", "min": "53", "hour": "02", "tzname": "UTC", "mon": "12"}, "pressurem": "1010.4", "wdird": "90", "tornado": "0", "metar": "METAR KMDW 120253Z 09006KT 7SM -DZ OVC013 11/06 A2983 RMK AO2 RAB33E50DZB40 SLP104 P0000 60000 T01110056 53001", "rain": "0", "hail": "0"}, {"wspdm": "9.3", "wspdi": "5.8", "snow": "0", "date": {"pretty": "9:53 PM CST on December 11, 2015", "year": "2015", "mday": "11", "min": "53", "hour": "21", "tzname": "America/Chicago", "mon": "12"}, "precipi": "0.00", "wgusti": "-9999.0", "heatindexi": "-9999", "vism": "16.1", "precipm": "0.0", "dewpti": "43.0", "fog": "0", "heatindexm": "-9999", "wgustm": "-9999.0", "icon": "cloudy", "visi": "10.0", "windchillm": "-999", "conds": "Overcast", "windchilli": "-999", "pressurei": "29.82", "tempm": "10.6", "hum": "74", "tempi": "51.1", "thunder": "0", "dewptm": "6.1", "wdire": "East", "utcdate": {"pretty": "3:53 AM GMT on December 12, 2015", "year": "2015", "mday": "12", "min": "53", "hour": "03", "tzname": "UTC", "mon": "12"}, "pressurem": "1009.8", "wdird": "100", "tornado": "0", "metar": "METAR KMDW 120353Z 10005KT 10SM OVC012 11/06 A2981 RMK AO2 DZE19 SLP098 P0000 T01060061", "rain": "0", "hail": "0"}, {"wspdm": "5.6", "wspdi": "3.5", "snow": "0", "date": {"pretty": "10:53 PM CST on December 11, 2015", "year": "2015", "mday": "11", "min": "53", "hour": "22", "tzname": "America/Chicago", "mon": "12"}, "precipi": "-9999.00", "wgusti": "-9999.0", "heatindexi": "-9999", "vism": "14.5", "precipm": "-9999.00", "dewpti": "44.1", "fog": "0", "heatindexm": "-9999", "wgustm": "-9999.0", "icon": "cloudy", "visi": "9.0", "windchillm": "-999", "conds": "Overcast", "windchilli": "-999", "pressurei": "29.83", "tempm": "11.1", "hum": "74", "tempi": "52.0", "thunder": "0", "dewptm": "6.7", "wdire": "East", "utcdate": {"pretty": "4:53 AM GMT on December 12, 2015", "year": "2015", "mday": "12", "min": "53", "hour": "04", "tzname": "UTC", "mon": "12"}, "pressurem": "1009.9", "wdird": "80", "tornado": "0", "metar": "METAR KMDW 120453Z 08003KT 9SM OVC011 11/07 A2982 RMK AO2 SLP099 T01110067", "rain": "0", "hail": "0"}, {"wspdm": "0.0", "wspdi": "0.0", "snow": "0", "date": {"pretty": "11:53 PM CST on December 11, 2015", "year": "2015", "mday": "11", "min": "53", "hour": "23", "tzname": "America/Chicago", "mon": "12"}, "precipi": "-9999.00", "wgusti": "-9999.0", "heatindexi": "-9999", "vism": "11.3", "precipm": "-9999.00", "dewpti": "46.0", "fog": "0", "heatindexm": "-9999", "wgustm": "-9999.0", "icon": "cloudy", "visi": "7.0", "windchillm": "-999", "conds": "Overcast", "windchilli": "-999", "pressurei": "29.83", "tempm": "11.7", "hum": "77", "tempi": "53.1", "thunder": "0", "dewptm": "7.8", "wdire": "North", "utcdate": {"pretty": "5:53 AM GMT on December 12, 2015", "year": "2015", "mday": "12", "min": "53", "hour": "05", "tzname": "UTC", "mon": "12"}, "pressurem": "1009.9", "wdird": "0", "tornado": "0", "metar": "METAR KMDW 120553Z 00000KT 7SM OVC010 12/08 A2982 RMK AO2 SLP099 60000 T01170078 10117 20089 401280067 55003", "rain": "0", "hail": "0"}], "date": {"pretty": "December 11, 2015", "year": "2015", "mday": "11", "min": "00", "hour": "12", "tzname": "America/Chicago", "mon": "12"}, "utcdate": {"pretty": "December 11, 2015", "year": "2015", "mday": "11", "min": "00", "hour": "18", "tzname": "UTC", "mon": "12"}, "dailysummary": [{"heatingdegreedays": "15", "meantempi": "50", "snow": "0", "meanwindspdi": "7", "gdegreedays": "0", "precipm": "T", "heatingdegreedaysnormal": "35", "mintempm": "7", "mintempi": "44", "meanpressurem": "1009", "since1sepcoolingdegreedaysnormal": "", "maxpressurei": "29.85", "fog": "0", "monthtodatesnowfalli": "", "maxtempi": "55", "since1jancoolingdegreedaysnormal": "1045", "meandewptm": "2", "meanwindspdm": "12", "monthtodatesnowfallm": "", "since1julheatingdegreedaysnormal": "1499", "meandewpti": "36", "since1julsnowfalli": "", "snowfalli": "0.00", "snowdepthm": "", "meanvism": "16", "coolingdegreedays": "0", "precipi": "T", "monthtodateheatingdegreedaysnormal": "364", "meanvisi": "10", "minvisi": "7", "since1sepcoolingdegreedays": "", "maxtempm": "13", "since1julsnowfallm": "", "tornado": "0", "maxvisi": "10", "maxpressurem": "1011", "hail": "0", "maxwspdi": "18", "date": {"pretty": "12:00 PM CST on December 11, 2015", "year": "2015", "mday": "11", "min": "00", "hour": "12", "tzname": "America/Chicago", "mon": "12"}, "snowdepthi": "", "meantempm": "10", "rain": "1", "minwspdi": "0", "monthtodatecoolingdegreedaysnormal": "0", "minvism": "11", "coolingdegreedaysnormal": "0", "minhumidity": "34", "monthtodateheatingdegreedays": "251", "since1sepheatingdegreedays": "", "maxdewptm": "8", "mindewptm": "0", "minpressurem": "1003", "precipsource": "", "mindewpti": "32", "meanpressurei": "29.79", "since1sepheatingdegreedaysnormal": "", "since1julheatingdegreedays": "1061", "maxdewpti": "46", "meanwdird": "172", "minpressurei": "29.63", "thunder": "0", "monthtodatecoolingdegreedays": "0", "maxvism": "16", "maxwspdm": "29", "snowfallm": "0.00", "maxhumidity": "77", "meanwdire": "", "minwspdm": "0", "since1jancoolingdegreedays": "1152", "humidity": ""}]}}