{"response": {"version": "0.1", "termsofService": "http://www.wunderground.com/weather/api/d/terms.html", "features": {"history": 1}}, "history": {"observations": [{"wspdm": "29.6", "wspdi": "18.4", "snow": "1", "date": {"pretty": "12:25 AM CST on February 02, 2015", "year": "2015", "mday": "02", "min": "25", "hour": "00", "tzname": "America/Chicago", "mon": "02"}, "precipi": "0.00", "wgusti": "31.1", "heatindexi": "-9999", "vism": "1.6", "precipm": "0.0", "dewpti": "17.1", "fog": "0", "heatindexm": "-9999", "wgustm": "50.0", "icon": "snow", "visi": "1.0", "windchillm": "-14.4", "conds": "Light Snow", "windchilli": "6.2", "pressurei": "29.88", "tempm": "-6.1", "hum": "85", "tempi": "21.0", "thunder": "0", "dewptm": "-8.3", "wdire": "North", "utcdate": {"pretty": "6:25 AM GMT on February 02, 2015", "year": "2015", "mday": "02", "min": "25", "hour": "06", "tzname": "UTC", "mon": "02"}, "pressurem": "1011.7", "wdird": "10", "tornado": "0", "metar": "SPECI KMDW 020625Z 01016G27KT 1SM R31C/5500VP6000FT -SN BLSN BR BKN013 OVC019 M06/M08 A2988 RMK AO2 PK WND 02027/0618 P0000 T10611083 $", "rain": "0", "hail": "0"}, {"wspdm": "33.3", "wspdi": "20.7", "snow": "1", "date": {"pretty": "12:53 AM CST on February 02, 2015", "year": "2015", "mday": "02", "min": "53", "hour": "00", "tzname": "America/Chicago", "mon": "02"}, "precipi": "0.00", "wgusti": "29.9", "heatindexi": "-9999", "vism": "2.4", "precipm": "0.0", "dewpti": "17.1", "fog": "0", "heatindexm": "-9999", "wgustm": "48.2", "icon": "snow", "visi": "1.5", "windchillm": "-14.8", "conds": "Light Snow", "windchilli": "5.4", "pressurei": "29.94", "tempm": "-6.1", "hum": "85", "tempi": "21.0", "thunder": "0", "dewptm": "-8.3", "wdire": "North", "utcdate": {"pretty": "6:53 AM GMT on February 02, 2015", "year": "2015", "mday": "02", "min": "53", "hour": "06", "tzname": "UTC", "mon": "02"}, "pressurem": "1013.7", "wdird": "10", "tornado": "0", "metar": "METAR KMDW 020653Z 01018G26KT 1 1/2SM -SN BLSN BR OVC015 M06/M08 A2989 RMK AO2 PK WND 01028/0626 SLP137 P0000 T10611083 $", "rain": "0", "hail": "0"}, {"wspdm": "27.8", "wspdi": "17.3", "snow": "1", "date": {"pretty": "1:27 AM CST on February 02, 2015", "year": "2015", "mday": "02", "min": "27", "hour": "01", "tzname": "America/Chicago", "mon": "02"}, "precipi": "0.00", "wgusti": "-9999.0", "heatindexi": "-9999", "vism": "0.8", "precipm": "0.0", "dewpti": "18.0", "fog": "1", "heatindexm": "-9999", "wgustm": "-9999.0", "icon": "snow", "visi": "0.5", "windchillm": "-13.5", "conds": "Snow", "windchilli": "7.8", "pressurei": "29.91", "tempm": "-5.6", "hum": "85", "tempi": "21.9", "thunder": "0", "dewptm": "-7.8", "wdire": "North", "utcdate": {"pretty": "7:27 AM GMT on February 02, 2015", "year": "2015", "mday": "02", "min": "27", "hour": "07", "tzname": "UTC", "mon": "02"}, "pressurem": "1012.8", "wdird": "360", "tornado": "0", "metar": "SPECI KMDW 020727Z 36015KT 1/2SM R31C/4000VP6000FT SN BLSN FZFG VV013 M06/M08 A2991 RMK AO2 P0000 T10561078 $", "rain": "0", "hail": "0"}, {"wspdm": "29.6", "wspdi": "18.4", "snow": "1", "date": {"pretty": "1:38 AM CST on February 02, 2015", "year": "2015", "mday": "02", "min": "38", "hour": "01", "tzname": "America/Chicago", "mon": "02"}, "precipi": "0.00", "wgusti": "27.6", "heatindexi": "-9999", "vism": "1.2", "precipm": "0.0", "dewpti": "18.0", "fog": "0", "heatindexm": "-9999", "wgustm": "44.4", "icon": "snow", "visi": "0.8", "windchillm": "-13.7", "conds": "Light Snow", "windchilli": "7.3", "pressurei": "29.92", "tempm": "-5.6", "hum": "85", "tempi": "21.9", "thunder": "0", "dewptm": "-7.8", "wdire": "North", "utcdate": {"pretty": "7:38 AM GMT on February 02, 2015", "year": "2015", "mday": "02", "min": "38", "hour": "07", "tzname": "UTC", "mon": "02"}, "pressurem": "1013.1", "wdird": "360", "tornado": "0", "metar": "SPECI KMDW 020738Z 36016G24KT 3/4SM R31C/4000V6000FT -SN BLSN BR VV011 M06/M08 A2992 RMK AO2 P0000 T10561078 $", "rain": "0", "hail": "0"}, {"wspdm": "29.6", "wspdi": "18.4", "snow": "1", "date": {"pretty": "1:53 AM CST on February 02, 2015", "year": "2015", "mday": "02", "min": "53", "hour": "01", "tzname": "America/Chicago", "mon": "02"}, "precipi": "0.00", "wgusti": "28.8", "heatindexi": "-9999", "vism": "2.4", "precipm": "0.0", "dewpti": "14.0", "fog": "0", "heatindexm": "-9999", "wgustm": "46.3", "icon": "snow", "visi": "1.5", "windchillm": "-16.6", "conds": "Light Snow", "windchilli": "2.2", "pressurei": "29.98", "tempm": "-7.8", "hum": "84", "tempi": "18.0", "thunder": "0", "dewptm": "-10.0", "wdire": "NW", "utcdate": {"pretty": "7:53 AM GMT on February 02, 2015", "year": "2015", "mday": "02", "min": "53", "hour": "07", "tzname": "UTC", "mon": "02"}, "pressurem": "1015.2", "wdird": "320", "tornado": "0", "metar": "METAR KMDW 020753Z 32016G25KT 1 1/2SM -SN BLSN BR BKN011 OVC018 M08/M10 A2993 RMK AO2 PK WND 36028/0743 SLP152 P0000 T10781100 $", "rain": "0", "hail": "0"}, {"wspdm": "29.6", "wspdi": "18.4", "snow": "1", "date": {"pretty": "2:25 AM CST on February 02, 2015", "year": "2015", "mday": "02", "min": "25", "hour": "02", "tzname": "America/Chicago", "mon": "02"}, "precipi": "0.00", "wgusti": "-9999.0", "heatindexi": "-9999", "vism": "2.4", "precipm": "0.0", "dewpti": "12.0", "fog": "0", "heatindexm": "-9999", "wgustm": "-9999.0", "icon": "snow", "visi": "1.5", "windchillm": "-17.2", "conds": "Light Snow", "windchilli": "1.0", "pressurei": "29.95", "tempm": "-8.3", "hum": "81", "tempi": "17.1", "thunder": "0", "dewptm": "-11.1", "wdire": "NNW", "utcdate": {"pretty": "8:25 AM GMT on February 02, 2015", "year": "2015", "mday": "02", "min": "25", "hour": "08", "tzname": "UTC", "mon": "02"}, "pressurem": "1014.1", "wdird": "330", "tornado": "0", "metar": "SPECI KMDW 020825Z 33016KT 1 1/2SM -SN BLSN BR SCT019 BKN026 OVC032 M08/M11 A2995 RMK AO2 P0000 T10831111 $", "rain": "0", "hail": "0"}, {"wspdm": "35.2", "wspdi": "21.9", "snow": "1", "date": {"pretty": "2:53 AM CST on February 02, 2015", "year": "2015", "mday": "02", "min": "53", "hour": "02", "tzname": "America/Chicago", "mon": "02"}, "precipi": "0.00", "wgusti": "-9999.0", "heatindexi": "-9999", "vism": "1.6", "precipm": "0.0", "dewpti": "12.0", "fog": "0", "heatindexm": "-9999", "wgustm": "-9999.0", "icon": "snow", "visi": "1.0", "windchillm": "-18.7", "conds": "Light Snow", "windchilli": "-1.7", "pressurei": "30.02", "tempm": "-8.9", "hum": "84", "tempi": "16.0", "thunder": "0", "dewptm": "-11.1", "wdire": "NNW", "utcdate": {"pretty": "8:53 AM GMT on February 02, 2015", "year": "2015", "mday": "02", "min": "53", "hour": "08", "tzname": "UTC", "mon": "02"}, "pressurem": "1016.4", "wdird": "340", "tornado": "0", "metar": "METAR KMDW 020853Z 34019KT 1SM R31C/P6000FT -SN BLSN BR FEW015 BKN024 OVC028 M09/M11 A2997 RMK AO2 SLP164 P0000 60000 T10891111 53033 $", "rain": "0", "hail": "0"}, {"wspdm": "29.6", "wspdi": "18.4", "snow": "1", "date": {"pretty": "3:53 AM CST on February 02, 2015", "year": "2015", "mday": "02", "min": "53", "hour": "03", "tzname": "America/Chicago", "mon": "02"}, "precipi": "0.00", "wgusti": "24.2", "heatindexi": "-9999", "vism": "4.8", "precipm": "0.0", "dewpti": "10.0", "fog": "0", "heatindexm": "-9999", "wgustm": "38.9", "icon": "snow", "visi": "3.0", "windchillm": "-18.0", "conds": "Light Snow", "windchilli": "-0.4", "pressurei": "30.04", "tempm": "-8.9", "hum": "77", "tempi": "16.0", "thunder": "0", "dewptm": "-12.2", "wdire": "NNW", "utcdate": {"pretty": "9:53 AM GMT on February 02, 2015", "year": "2015", "mday": "02", "min": "53", "hour": "09", "tzname": "UTC", "mon": "02"}, "pressurem": "1017.0", "wdird": "340", "tornado": "0", "metar": "METAR KMDW 020953Z 34016G21KT 3SM -SN BR OVC026 M09/M12 A2998 RMK AO2 SLP170 P0000 T10891122 $", "rain": "0", "hail": "0"}, {"wspdm": "24.1", "wspdi": "15.0", "snow": "1", "date": {"pretty": "4:21 AM CST on February 02, 2015", "year": "2015", "mday": "02", "min": "21", "hour": "04", "tzname": "America/Chicago", "mon": "02"}, "precipi": "0.00", "wgusti": "-9999.0", "heatindexi": "-9999", "vism": "3.2", "precipm": "0.0", "dewpti": "10.0", "fog": "0", "heatindexm": "-9999", "wgustm": "-9999.0", "icon": "snow", "visi": "2.0", "windchillm": "-17.8", "conds": "Light Snow", "windchilli": "-0.1", "pressurei": "30.00", "tempm": "-9.4", "hum": "80", "tempi": "15.1", "thunder": "0", "dewptm": "-12.2", "wdire": "NNW", "utcdate": {"pretty": "10:21 AM GMT on February 02, 2015", "year": "2015", "mday": "02", "min": "21", "hour": "10", "tzname": "UTC", "mon": "02"}, "pressurem": "1015.8", "wdird": "330", "tornado": "0", "metar": "SPECI KMDW 021021Z 33013KT 2SM -SN BR FEW025 OVC031 M09/M12 A3000 RMK AO2 P0000 T10941122 $", "rain": "0", "hail": "0"}, {"wspdm": "24.1", "wspdi": "15.0", "snow": "1", "date": {"pretty": "4:53 AM CST on February 02, 2015", "year": "2015", "mday": "02", "min": "53", "hour": "04", "tzname": "America/Chicago", "mon": "02"}, "precipi": "0.00", "wgusti": "-9999.0", "heatindexi": "-9999", "vism": "2.4", "precipm": "0.0", "dewpti": "9.0", "fog": "0", "heatindexm": "-9999", "wgustm": "-9999.0", "icon": "snow", "visi": "1.5", "windchillm": "-18.6", "conds": "Light Snow", "windchilli": "-1.4", "pressurei": "30.08", "tempm": "-10.0", "hum": "80", "tempi": "14.0", "thunder": "0", "dewptm": "-12.8", "wdire": "NW", "utcdate": {"pretty": "10:53 AM GMT on February 02, 2015", "year": "2015", "mday": "02", "min": "53", "hour": "10", "tzname": "UTC", "mon": "02"}, "pressurem": "1018.6", "wdird": "320", "tornado": "0", "metar": "METAR KMDW 021053Z 32013KT 1 1/2SM -SN BR OVC031 M10/M13 A3003 RMK AO2 SLP186 P0000 T11001128 $", "rain": "0", "hail": "0"}, {"wspdm": "29.6", "wspdi": "18.4", "snow": "1", "date": {"pretty": "5:53 AM CST on February 02, 2015", "year": "2015", "mday": "02", "min": "53", "hour": "05", "tzname": "America/Chicago", "mon": "02"}, "precipi": "0.00", "wgusti": "-9999.0", "heatindexi": "-9999", "vism": "4.8", "precipm": "0.0", "dewpti": "8.1", "fog": "0", "heatindexm": "-9999", "wgustm": "-9999.0", "icon": "snow", "visi": "3.0", "windchillm": "-20.2", "conds": "Light Snow", "windchilli": "-4.4", "pressurei": "30.11", "tempm": "-10.6", "hum": "81", "tempi": "12.9", "thunder": "0", "dewptm": "-13.3", "wdire": "NNW", "utcdate": {"pretty": "11:53 AM GMT on February 02, 2015", "year": "2015", "mday": "02", "min": "53", "hour": "11", "tzname": "UTC", "mon": "02"}, "pressurem": "1019.6", "wdird": "330", "tornado": "0", "metar": "METAR KMDW 021153Z 33016KT 3SM -SN BR OVC033 M11/M13 A3005 RMK AO2 SLP196 4/017 P0000 60000 70021 T11061133 11056 21106 53029 $", "rain": "0", "hail": "0"}, {"wspdm": "27.8", "wspdi": "17.3", "snow": "1", "date": {"pretty": "6:53 AM CST on February 02, 2015", "year": "2015", "mday": "02", "min": "53", "hour": "06", "tzname": "America/Chicago", "mon": "02"}, "precipi": "0.00", "wgusti": "-9999.0", "heatindexi": "-9999", "vism": "4.8", "precipm": "0.0", "dewpti": "6.1", "fog": "0", "heatindexm": "-9999", "wgustm": "-9999.0", "icon": "snow", "visi": "3.0", "windchillm": "-20.6", "conds": "Light Snow", "windchilli": "-5.1", "pressurei": "30.17", "tempm": "-11.1", "hum": "77", "tempi": "12.0", "thunder": "0", "dewptm": "-14.4", "wdire": "NW", "utcdate": {"pretty": "12:53 PM GMT on February 02, 2015", "year": "2015", "mday": "02", "min": "53", "hour": "12", "tzname": "UTC", "mon": "02"}, "pressurem": "1021.5", "wdird": "320", "tornado": "0", "metar": "METAR KMDW 021253Z 32015KT 3SM -SN BR SCT022 BKN033 M11/M14 A3011 RMK AO2 SLP215 P0000 T11111144 $", "rain": "0", "hail": "0"}, {"wspdm": "20.4", "wspdi": "12.7", "snow": "0", "date": {"pretty": "7:53 AM CST on February 02, 2015", "year": "2015", "mday": "02", "min": "53", "hour": "07", "tzname": "America/Chicago", "mon": "02"}, "precipi": "0.00", "wgusti": "-9999.0", "heatindexi": "-9999", "vism": "16.1", "precipm": "0.0", "dewpti": "3.9", "fog": "0", "heatindexm": "-9999", "wgustm": "-9999.0", "icon": "partlycloudy", "visi": "10.0", "windchillm": "-20.7", "conds": "Partly Cloudy", "windchilli": "-5.2", "pressurei": "30.21", "tempm": "-12.2", "hum": "76", "tempi": "10.0", "thunder": "0", "dewptm": "-15.6", "wdire": "NW", "utcdate": {"pretty": "1:53 PM GMT on February 02, 2015", "year": "2015", "mday": "02", "min": "53", "hour": "13", "tzname": "UTC", "mon": "02"}, "pressurem": "1022.8", "wdird": "320", "tornado": "0", "metar": "METAR KMDW 021353Z 32011KT 10SM FEW017 FEW027 M12/M16 A3015 RMK AO2 SNE16 SLP228 P0000 T11221156 $", "rain": "0", "hail": "0"}, {"wspdm": "20.4", "wspdi": "12.7", "snow": "0", "date": {"pretty": "8:53 AM CST on February 02, 2015", "year": "2015", "mday": "02", "min": "53", "hour": "08", "tzname": "America/Chicago", "mon": "02"}, "precipi": "-9999.00", "wgusti": "-9999.0", "heatindexi": "-9999", "vism": "16.1", "precipm": "-9999.00", "dewpti": "3.9", "fog": "0", "heatindexm": "-9999", "wgustm": "-9999.0", "icon": "partlycloudy", "visi": "10.0", "windchillm": "-20.0", "conds": "Partly Cloudy", "windchilli": "-4.1", "pressurei": "30.23", "tempm": "-11.7", "hum": "73", "tempi": "10.9", "thunder": "0", "dewptm": "-15.6", "wdire": "NW", "utcdate": {"pretty": "2:53 PM GMT on February 02, 2015", "year": "2015", "mday": "02", "min": "53", "hour": "14", "tzname": "UTC", "mon": "02"}, "pressurem": "1023.5", "wdird": "320", "tornado": "0", "metar": "METAR KMDW 021453Z 32011KT 10SM FEW017 M12/M16 A3017 RMK AO2 SLP235 60000 T11171156 51038", "rain": "0", "hail": "0"}, {"wspdm": "18.5", "wspdi": "11.5", "snow": "0", "date": {"pretty": "9:53 AM CST on February 02, 2015", "year": "2015", "mday": "02", "min": "53", "hour": "09", "tzname": "America/Chicago", "mon": "02"}, "precipi": "-9999.00", "wgusti": "-9999.0", "heatindexi": "-9999", "vism": "16.1", "precipm": "-9999.00", "dewpti": "5.0", "fog": "0", "heatindexm": "-9999", "wgustm": "-9999.0", "icon": "partlycloudy", "visi": "10.0", "windchillm": "-17.5", "conds": "Partly Cloudy", "windchilli": "0.5", "pressurei": "30.24", "tempm": "-10.0", "hum": "67", "tempi": "14.0", "thunder": "0", "dewptm": "-15.0", "wdire": "NW", "utcdate": {"pretty": "3:53 PM GMT on February 02, 2015", "year": "2015", "mday": "02", "min": "53", "hour": "15", "tzname": "UTC", "mon": "02"}, "pressurem": "1023.9", "wdird": "310", "tornado": "0", "metar": "METAR KMDW 021553Z 31010KT 10SM FEW017 M10/M15 A3018 RMK AO2 SLP239 T11001150", "rain": "0", "hail": "0"}, {"wspdm": "11.1", "wspdi": "6.9", "snow": "0", "date": {"pretty": "10:53 AM CST on February 02, 2015", "year": "2015", "mday": "02", "min": "53", "hour": "10", "tzname": "America/Chicago", "mon": "02"}, "precipi": "-9999.00", "wgusti": "-9999.0", "heatindexi": "-9999", "vism": "16.1", "precipm": "-9999.00", "dewpti": "8.1", "fog": "0", "heatindexm": "-9999", "wgustm": "-9999.0", "icon": "partlycloudy", "visi": "10.0", "windchillm": "-13.6", "conds": "Partly Cloudy", "windchilli": "7.6", "pressurei": "30.24", "tempm": "-8.3", "hum": "68", "tempi": "17.1", "thunder": "0", "dewptm": "-13.3", "wdire": "NW", "utcdate": {"pretty": "4:53 PM GMT on February 02, 2015", "year": "2015", "mday": "02", "min": "53", "hour": "16", "tzname": "UTC", "mon": "02"}, "pressurem": "1024.0", "wdird": "310", "tornado": "0", "metar": "METAR KMDW 021653Z 31006KT 10SM FEW017 M08/M13 A3019 RMK AO2 SLP240 T10831133", "rain": "0", "hail": "0"}, {"wspdm": "13.0", "wspdi": "8.1", "snow": "0", "date": {"pretty": "11:53 AM CST on February 02, 2015", "year": "2015", "mday": "02", "min": "53", "hour": "11", "tzname": "America/Chicago", "mon": "02"}, "precipi": "-9999.00", "wgusti": "-9999.0", "heatindexi": "-9999", "vism": "16.1", "precipm": "-9999.00", "dewpti": "9.0", "fog": "0", "heatindexm": "-9999", "wgustm": "-9999.0", "icon": "partlycloudy", "visi": "10.0", "windchillm": "-12.8", "conds": "Partly Cloudy", "windchilli": "9.0", "pressurei": "30.25", "tempm": "-7.2", "hum": "65", "tempi": "19.0", "thunder": "0", "dewptm": "-12.8", "wdire": "West", "utcdate": {"pretty": "5:53 PM GMT on February 02, 2015", "year": "2015", "mday": "02", "min": "53", "hour": "17", "tzname": "UTC", "mon": "02"}, "pressurem": "1024.1", "wdird": "280", "tornado": "0", "metar": "METAR KMDW 021753Z 28007KT 10SM FEW017 M07/M13 A3019 RMK AO2 SLP241 4/017 60000 T10721128 11072 21122 51007", "rain": "0", "hail": "0"}, {"wspdm": "14.8", "wspdi": "9.2", "snow": "0", "date": {"pretty": "12:53 PM CST on February 02, 2015", "year": "2015", "mday": "02", "min": "53", "hour": "12", "tzname": "America/Chicago", "mon": "02"}, "precipi": "-9999.00", "wgusti": "-9999.0", "heatindexi": "-9999", "vism": "16.1", "precipm": "-9999.00", "dewpti": "10.0", "fog": "0", "heatindexm": "-9999", "wgustm": "-9999.0", "icon": "partlycloudy", "visi": "10.0", "windchillm": "-11.9", "conds": "Partly Cloudy", "windchilli": "10.6", "pressurei": "30.24", "tempm": "-6.1", "hum": "63", "tempi": "21.0", "thunder": "0", "dewptm": "-12.2", "wdire": "West", "utcdate": {"pretty": "6:53 PM GMT on February 02, 2015", "year": "2015", "mday": "02", "min": "53", "hour": "18", "tzname": "UTC", "mon": "02"}, "pressurem": "1023.9", "wdird": "270", "tornado": "0", "metar": "METAR KMDW 021853Z 27008KT 10SM FEW017 M06/M12 A3019 RMK AO2 SLP239 T10611122", "rain": "0", "hail": "0"}, {"wspdm": "18.5", "wspdi": "11.5", "snow": "0", "date": {"pretty": "1:53 PM CST on February 02, 2015", "year": "2015", "mday": "02", "min": "53", "hour": "13", "tzname": "America/Chicago", "mon": "02"}, "precipi": "-9999.00", "wgusti": "-9999.0", "heatindexi": "-9999", "vism": "16.1", "precipm": "-9999.00", "dewpti": "8.1", "fog": "0", "heatindexm": "-9999", "wgustm": "-9999.0", "icon": "partlycloudy", "visi": "10.0", "windchillm": "-12.6", "conds": "Partly Cloudy", "windchilli": "9.3", "pressurei": "30.23", "tempm": "-6.1", "hum": "57", "tempi": "21.0", "thunder": "0", "dewptm": "-13.3", "wdire": "West", "utcdate": {"pretty": "7:53 PM GMT on February 02, 2015", "year": "2015", "mday": "02", "min": "53", "hour": "19", "tzname": "UTC", "mon": "02"}, "pressurem": "1023.6", "wdird": "270", "tornado": "0", "metar": "METAR KMDW 021953Z 27010KT 10SM FEW017 M06/M13 A3018 RMK AO2 SLP236 T10611133", "rain": "0", "hail": "0"}, {"wspdm": "20.4", "wspdi": "12.7", "snow": "0", "date": {"pretty": "2:53 PM CST on February 02, 2015", "year": "2015", "mday": "02", "min": "53", "hour": "14", "tzname": "America/Chicago", "mon": "02"}, "precipi": "-9999.00", "wgusti": "-9999.0", "heatindexi": "-9999", "vism": "16.1", "precipm": "-9999.00", "dewpti": "6.8", "fog": "0", "heatindexm": "-9999", "wgustm": "-9999.0", "icon": "partlycloudy", "visi": "10.0", "windchillm": "-14.1", "conds": "Partly Cloudy", "windchilli": "6.6", "pressurei": "30.18", "tempm": "-7.0", "hum": "58", "tempi": "19.4", "thunder": "0", "dewptm": "-14.0", "wdire": "West", "utcdate": {"pretty": "8:53 PM GMT on February 02, 2015", "year": "2015", "mday": "02", "min": "53", "hour": "20", "tzname": "UTC", "mon": "02"}, "pressurem": "1021.9", "wdird": "280", "tornado": "0", "metar": "METAR KMDW 022053Z 28011KT 10SM FEW017 M07/M14 A3018", "rain": "0", "hail": "0"}, {"wspdm": "14.8", "wspdi": "9.2", "snow": "0", "date": {"pretty": "3:53 PM CST on February 02, 2015", "year": "2015", "mday": "02", "min": "53", "hour": "15", "tzname": "America/Chicago", "mon": "02"}, "precipi": "-9999.00", "wgusti": "-9999.0", "heatindexi": "-9999", "vism": "16.1", "precipm": "-9999.00", "dewpti": "5.0", "fog": "0", "heatindexm": "-9999", "wgustm": "-9999.0", "icon": "partlycloudy", "visi": "10.0", "windchillm": "-14.2", "conds": "Partly Cloudy", "windchilli": "6.4", "pressurei": "30.19", "tempm": "-8.0", "hum": "58", "tempi": "17.6", "thunder": "0", "dewptm": "-15.0", "wdire": "West", "utcdate": {"pretty": "9:53 PM GMT on February 02, 2015", "year": "2015", "mday": "02", "min": "53", "hour": "21", "tzname": "UTC", "mon": "02"}, "pressurem": "1022.2", "wdird": "270", "tornado": "0", "metar": "METAR KMDW 022153Z 27008KT 10SM FEW017 FEW250 M08/M15 A3019", "rain": "0", "hail": "0"}, {"wspdm": "16.7", "wspdi": "10.4", "snow": "0", "date": {"pretty": "4:53 PM CST on February 02, 2015", "year": "2015", "mday": "02", "min": "53", "hour": "16", "tzname": "America/Chicago", "mon": "02"}, "precipi": "-9999.00", "wgusti": "-9999.0", "heatindexi": "-9999", "vism": "16.1", "precipm": "-9999.00", "dewpti": "1.9", "fog": "0", "heatindexm": "-9999", "wgustm": "-9999.0", "icon": "partlycloudy", "visi": "10.0", "windchillm": "-16.4", "conds": "Scattered Clouds", "windchilli": "2.5", "pressurei": "30.26", "tempm": "-9.4", "hum": "56", "tempi": "15.1", "thunder": "0", "dewptm": "-16.7", "wdire": "WSW", "utcdate": {"pretty": "10:53 PM GMT on February 02, 2015", "year": "2015", "mday": "02", "min": "53", "hour": "22", "tzname": "UTC", "mon": "02"}, "pressurem": "1024.6", "wdird": "250", "tornado": "0", "metar": "METAR KMDW 022253Z 25009KT 10SM FEW017 SCT150 SCT250 M09/M17 A3020 RMK AO2 SLP246 T10941167", "rain": "0", "hail": "0"}, {"wspdm": "14.8", "wspdi": "9.2", "snow": "0", "date": {"pretty": "5:53 PM CST on February 02, 2015", "year": "2015", "mday": "02", "min": "53", "hour": "17", "tzname": "America/Chicago", "mon": "02"}, "precipi": "-9999.00", "wgusti": "-9999.0", "heatindexi": "-9999", "vism": "16.1", "precipm": "-9999.00", "dewpti": "3.0", "fog": "0", "heatindexm": "-9999", "wgustm": "-9999.0", "icon": "mostlycloudy", "visi": "10.0", "windchillm": "-17.4", "conds": "Mostly Cloudy", "windchilli": "0.7", "pressurei": "30.27", "tempm": "-10.6", "hum": "65", "tempi": "12.9", "thunder": "0", "dewptm": "-16.1", "wdire": "West", "utcdate": {"pretty": "11:53 PM GMT on February 02, 2015", "year": "2015", "mday": "02", "min": "53", "hour": "23", "tzname": "UTC", "mon": "02"}, "pressurem": "1024.9", "wdird": "260", "tornado": "0", "metar": "METAR KMDW 022353Z 26008KT 10SM FEW017 BKN160 BKN250 M11/M16 A3020 RMK AO2 SLP249 4/017 T11061161 11061 21106 51007", "rain": "0", "hail": "0"}, {"wspdm": "16.7", "wspdi": "10.4", "snow": "0", "date": {"pretty": "6:53 PM CST on February 02, 2015", "year": "2015", "mday": "02", "min": "53", "hour": "18", "tzname": "America/Chicago", "mon": "02"}, "precipi": "-9999.00", "wgusti": "-9999.0", "heatindexi": "-9999", "vism": "16.1", "precipm": "-9999.00", "dewpti": "3.0", "fog": "0", "heatindexm": "-9999", "wgustm": "-9999.0", "icon": "mostlycloudy", "visi": "10.0", "windchillm": "-18.5", "conds": "Mostly Cloudy", "windchilli": "-1.3", "pressurei": "30.27", "tempm": "-11.1", "hum": "67", "tempi": "12.0", "thunder": "0", "dewptm": "-16.1", "wdire": "WSW", "utcdate": {"pretty": "12:53 AM GMT on February 03, 2015", "year": "2015", "mday": "03", "min": "53", "hour": "00", "tzname": "UTC", "mon": "02"}, "pressurem": "1025.1", "wdird": "240", "tornado": "0", "metar": "METAR KMDW 030053Z 24009KT 10SM FEW017 BKN150 BKN250 M11/M16 A3020 RMK AO2 SLP251 T11111161", "rain": "0", "hail": "0"}, {"wspdm": "16.7", "wspdi": "10.4", "snow": "0", "date": {"pretty": "7:53 PM CST on February 02, 2015", "year": "2015", "mday": "02", "min": "53", "hour": "19", "tzname": "America/Chicago", "mon": "02"}, "precipi": "-9999.00", "wgusti": "-9999.0", "heatindexi": "-9999", "vism": "16.1", "precipm": "-9999.00", "dewpti": "1.4", "fog": "0", "heatindexm": "-9999", "wgustm": "-9999.0", "icon": "mostlycloudy", "visi": "10.0", "windchillm": "-19.6", "conds": "Mostly Cloudy", "windchilli": "-3.3", "pressurei": "30.22", "tempm": "-12.0", "hum": "67", "tempi": "10.4", "thunder": "0", "dewptm": "-17.0", "wdire": "WSW", "utcdate": {"pretty": "1:53 AM GMT on February 03, 2015", "year": "2015", "mday": "03", "min": "53", "hour": "01", "tzname": "UTC", "mon": "02"}, "pressurem": "1023.2", "wdird": "240", "tornado": "0", "metar": "METAR KMDW 030153Z 24009KT 10SM FEW017 BKN130 BKN250 M12/M17 A3022", "rain": "0", "hail": "0"}, {"wspdm": "20.4", "wspdi": "12.7", "snow": "0", "date": {"pretty": "8:53 PM CST on February 02, 2015", "year": "2015", "mday": "02", "min": "53", "hour": "20", "tzname": "America/Chicago", "mon": "02"}, "precipi": "-9999.00", "wgusti": "-9999.0", "heatindexi": "-9999", "vism": "16.1", "precipm": "-9999.00", "dewpti": "3.0", "fog": "0", "heatindexm": "-9999", "wgustm": "-9999.0", "icon": "mostlycloudy", "visi": "10.0", "windchillm": "-20.7", "conds": "Mostly Cloudy", "windchilli": "-5.2", "pressurei": "30.30", "tempm": "-12.2", "hum": "73", "tempi": "10.0", "thunder": "0", "dewptm": "-16.1", "wdire": "WSW", "utcdate": {"pretty": "2:53 AM GMT on February 03, 2015", "year": "2015", "mday": "03", "min": "53", "hour": "02", "tzname": "UTC", "mon": "02"}, "pressurem": "1025.9", "wdird": "240", "tornado": "0", "metar": "METAR KMDW 030253Z 24011KT 10SM FEW017 BKN130 BKN250 M12/M16 A3023 RMK AO2 SLP259 T11221161 53009", "rain": "0", "hail": "0"}, {"wspdm": "18.5", "wspdi": "11.5", "snow": "0", "date": {"pretty": "9:53 PM CST on February 02, 2015", "year": "2015", "mday": "02", "min": "53", "hour": "21", "tzname": "America/Chicago", "mon": "02"}, "precipi": "-9999.00", "wgusti": "-9999.0", "heatindexi": "-9999", "vism": "16.1", "precipm": "-9999.00", "dewpti": "3.0", "fog": "0", "heatindexm": "-9999", "wgustm": "-9999.0", "icon": "cloudy", "visi": "10.0", "windchillm": "-20.3", "conds": "Overcast", "windchilli": "-4.5", "pressurei": "30.31", "tempm": "-12.2", "hum": "73", "tempi": "10.0", "thunder": "0", "dewptm": "-16.1", "wdire": "WSW", "utcdate": {"pretty": "3:53 AM GMT on February 03, 2015", "year": "2015", "mday": "03", "min": "53", "hour": "03", "tzname": "UTC", "mon": "02"}, "pressurem": "1026.3", "wdird": "240", "tornado": "0", "metar": "METAR KMDW 030353Z 24010KT 10SM FEW017 BKN150 OVC250 M12/M16 A3024 RMK AO2 SLP263 T11221161", "rain": "0", "hail": "0"}, {"wspdm": "20.4", "wspdi": "12.7", "snow": "0", "date": {"pretty": "10:53 PM CST on February 02, 2015", "year": "2015", "mday": "02", "min": "53", "hour": "22", "tzname": "America/Chicago", "mon": "02"}, "precipi": "-9999.00", "wgusti": "-9999.0", "heatindexi": "-9999", "vism": "16.1", "precipm": "-9999.00", "dewpti": "3.9", "fog": "0", "heatindexm": "-9999", "wgustm": "-9999.0", "icon": "mostlycloudy", "visi": "10.0", "windchillm": "-20.7", "conds": "Mostly Cloudy", "windchilli": "-5.2", "pressurei": "30.29", "tempm": "-12.2", "hum": "76", "tempi": "10.0", "thunder": "0", "dewptm": "-15.6", "wdire": "WSW", "utcdate": {"pretty": "4:53 AM GMT on February 03, 2015", "year": "2015", "mday": "03", "min": "53", "hour": "04", "tzname": "UTC", "mon": "02"}, "pressurem": "1025.5", "wdird": "240", "tornado": "0", "metar": "METAR KMDW 030453Z 24011KT 10SM BKN110 BKN250 M12/M16 A3022 RMK AO2 SLP255 T11221156", "rain": "0", "hail": "0"}, {"wspdm": "13.0", "wspdi": "8.1", "snow": "0", "date": {"pretty": "11:53 PM CST on February 02, 2015", "year": "2015", "mday": "02", "min": "53", "hour": "23", "tzname": "America/Chicago", "mon": "02"}, "precipi": "-9999.00", "wgusti": "-9999.0", "heatindexi": "-9999", "vism": "16.1", "precipm": "-9999.00", "dewpti": "3.0", "fog": "0", "heatindexm": "-9999", "wgustm": "-9999.0", "icon": "mostlycloudy", "visi": "10.0", "windchillm": "-18.9", "conds": "Mostly Cloudy", "windchilli": "-1.9", "pressurei": "30.27", "tempm": "-12.2", "hum": "73", "tempi": "10.0", "thunder": "0", "dewptm": "-16.1", "wdire": "SW", "utcdate": {"pretty": "5:53 AM GMT on February 03, 2015", "year": "2015", "mday": "03", "min": "53", "hour": "05", "tzname": "UTC", "mon": "02"}, "pressurem": "1024.9", "wdird": "230", "tornado": "0", "metar": "METAR KMDW 030553Z 23007KT 10SM FEW110 BKN250 M12/M16 A3021 RMK AO2 SLP249 4/017 T11221161 11106 21128 410561128 58007", "rain": "0", "hail": "0"}], "date": {"pretty": "February 2, 2015", "year": "2015", "mday": "02", "min": "00", "hour": "12", "tzname": "America/Chicago", "mon": "02"}, "utcdate": {"pretty": "February 2, 2015", "year": "2015", "mday": "02", "min": "00", "hour": "18", "tzname": "UTC", "mon": "02"}, "dailysummary": [{"heatingdegreedays": "49", "meantempi": "16", "snow": "1", "meanwindspdi": "13", "gdegreedays": "0", "precipm": "T", "heatingdegreedaysnormal": "39", "mintempm": "-13", "mintempi": "9", "meanpressurem": "1021", "since1sepcoolingdegreedaysnormal": "", "maxpressurei": "30.31", "fog": "1", "monthtodatesnowfalli": "", "maxtempi": "22", "since1jancoolingdegreedaysnormal": "0", "meandewptm": "-13", "meanwindspdm": "21", "monthtodatesnowfallm": "", "since1julheatingdegreedaysnormal": "3575", "meandewpti": "8", "since1julsnowfalli": "", "snowfalli": "0.00", "snowdepthm": "43.18", "meanvism": "11", "coolingdegreedays": "0", "precipi": "T", "monthtodateheatingdegreedaysnormal": "79", "meanvisi": "7", "minvisi": "0", "since1sepcoolingdegreedays": "", "maxtempm": "-6", "since1julsnowfallm": "", "tornado": "0", "maxvisi": "10", "maxpressurem": "1026", "hail": "0", "maxwspdi": "25", "date": {"pretty": "12:00 PM CST on February 02, 2015", "year": "2015", "mday": "02", "min": "00", "hour": "12", "tzname": "America/Chicago", "mon": "02"}, "snowdepthi": "17.00", "meantempm": "-9", "rain": "0", "minwspdi": "7", "monthtodatecoolingdegreedaysnormal": "0", "minvism": "1", "coolingdegreedaysnormal": "0", "minhumidity": "43", "monthtodateheatingdegreedays": "87", "since1sepheatingdegreedays": "", "maxdewptm": "-8", "mindewptm": "-17", "minpressurem": "1012", "precipsource": "", "mindewpti": "1", "meanpressurei": "30.15", "since1sepheatingdegreedaysnormal": "", "since1julheatingdegreedays": "3504", "maxdewpti": "18", "meanwdird": "299", "minpressurei": "29.88", "thunder": "0", "monthtodatecoolingdegreedays": "0", "maxvism": "16", "maxwspdm": "40", "snowfallm": "0.00", "maxhumidity": "85", "meanwdire": "", "minwspdm": "11", "since1jancoolingdegreedays": "0", "humidity": ""}]}}