{"response": {"version": "0.1", "termsofService": "http://www.wunderground.com/weather/api/d/terms.html", "features": {"history": 1}}, "history": {"observations": [{"wspdm": "11.1", "wspdi": "6.9", "snow": "0", "date": {"pretty": "12:53 AM CDT on September 17, 2015", "year": "2015", "mday": "17", "min": "53", "hour": "00", "tzname": "America/Chicago", "mon": "09"}, "precipi": "-9999.00", "wgusti": "-9999.0", "heatindexi": "-9999", "vism": "16.1", "precipm": "-9999.00", "dewpti": "55.0", "fog": "0", "heatindexm": "-9999", "wgustm": "-9999.0", "icon": "clear", "visi": "10.0", "windchillm": "-999", "conds": "Clear", "windchilli": "-999", "pressurei": "30.07", "tempm": "20.6", "hum": "61", "tempi": "69.1", "thunder": "0", "dewptm": "12.8", "wdire": "South", "utcdate": {"pretty": "5:53 AM GMT on September 17, 2015", "year": "2015", "mday": "17", "min": "53", "hour": "05", "tzname": "UTC", "mon": "09"}, "pressurem": "1018.3", "wdird": "170", "tornado": "0", "metar": "METAR KMDW 170553Z 17006KT 10SM CLR 21/13 A3010 RMK AO2 SLP183 T02060128 10272 20206 402890161 58003", "rain": "0", "hail": "0"}, {"wspdm": "9.3", "wspdi": "5.8", "snow": "0", "date": {"pretty": "1:53 AM CDT on September 17, 2015", "year": "2015", "mday": "17", "min": "53", "hour": "01", "tzname": "America/Chicago", "mon": "09"}, "precipi": "-9999.00", "wgusti": "-9999.0", "heatindexi": "-9999", "vism": "16.1", "precipm": "-9999.00", "dewpti": "55.0", "fog": "0", "heatindexm": "-9999", "wgustm": "-9999.0", "icon": "clear", "visi": "10.0", "windchillm": "-999", "conds": "Clear", "windchilli": "-999", "pressurei": "30.07", "tempm": "20.0", "hum": "63", "tempi": "68.0", "thunder": "0", "dewptm": "12.8", "wdire": "South", "utcdate": {"pretty": "6:53 AM GMT on September 17, 2015", "year": "2015", "mday": "17", "min": "53", "hour": "06", "tzname": "UTC", "mon": "09"}, "pressurem": "1018.2", "wdird": "170", "tornado": "0", "metar": "METAR KMDW 170653Z 17005KT 10SM CLR 20/13 A3010 RMK AO2 SLP182 T02000128", "rain": "0", "hail": "0"}, {"wspdm": "11.1", "wspdi": "6.9", "snow": "0", "date": {"pretty": "2:53 AM CDT on September 17, 2015", "year": "2015", "mday": "17", "min": "53", "hour": "02", "tzname": "America/Chicago", "mon": "09"}, "precipi": "-9999.00", "wgusti": "-9999.0", "heatindexi": "-9999", "vism": "16.1", "precipm": "-9999.00", "dewpti": "55.0", "fog": "0", "heatindexm": "-9999", "wgustm": "-9999.0", "icon": "clear", "visi": "10.0", "windchillm": "-999", "conds": "Clear", "windchilli": "-999", "pressurei": "30.07", "tempm": "19.4", "hum": "66", "tempi": "66.9", "thunder": "0", "dewptm": "12.8", "wdire": "South", "utcdate": {"pretty": "7:53 AM GMT on September 17, 2015", "year": "2015", "mday": "17", "min": "53", "hour": "07", "tzname": "UTC", "mon": "09"}, "pressurem": "1018.2", "wdird": "170", "tornado": "0", "metar": "METAR KMDW 170753Z 17006KT 10SM CLR 19/13 A3009 RMK AO2 SLP182 T01940128", "rain": "0", "hail": "0"}, {"wspdm": "11.1", "wspdi": "6.9", "snow": "0", "date": {"pretty": "3:53 AM CDT on September 17, 2015", "year": "2015", "mday": "17", "min": "53", "hour": "03", "tzname": "America/Chicago", "mon": "09"}, "precipi": "-9999.00", "wgusti": "-9999.0", "heatindexi": "-9999", "vism": "16.1", "precipm": "-9999.00", "dewpti": "55.0", "fog": "0", "heatindexm": "-9999", "wgustm": "-9999.0", "icon": "clear", "visi": "10.0", "windchillm": "-999", "conds": "Clear", "windchilli": "-999", "pressurei": "30.06", "tempm": "19.4", "hum": "66", "tempi": "66.9", "thunder": "0", "dewptm": "12.8", "wdire": "South", "utcdate": {"pretty": "8:53 AM GMT on September 17, 2015", "year": "2015", "mday": "17", "min": "53", "hour": "08", "tzname": "UTC", "mon": "09"}, "pressurem": "1017.8", "wdird": "170", "tornado": "0", "metar": "METAR KMDW 170853Z 17006KT 10SM CLR 19/13 A3009 RMK AO2 SLP178 T01940128 58004", "rain": "0", "hail": "0"}, {"wspdm": "14.8", "wspdi": "9.2", "snow": "0", "date": {"pretty": "4:53 AM CDT on September 17, 2015", "year": "2015", "mday": "17", "min": "53", "hour": "04", "tzname": "America/Chicago", "mon": "09"}, "precipi": "-9999.00", "wgusti": "-9999.0", "heatindexi": "-9999", "vism": "16.1", "precipm": "-9999.00", "dewpti": "55.9", "fog": "0", "heatindexm": "-9999", "wgustm": "-9999.0", "icon": "clear", "visi": "10.0", "windchillm": "-999", "conds": "Clear", "windchilli": "-999", "pressurei": "30.06", "tempm": "18.9", "hum": "70", "tempi": "66.0", "thunder": "0", "dewptm": "13.3", "wdire": "South", "utcdate": {"pretty": "9:53 AM GMT on September 17, 2015", "year": "2015", "mday": "17", "min": "53", "hour": "09", "tzname": "UTC", "mon": "09"}, "pressurem": "1017.8", "wdird": "180", "tornado": "0", "metar": "METAR KMDW 170953Z 18008KT 10SM CLR 19/13 A3008 RMK AO2 SLP178 T01890133", "rain": "0", "hail": "0"}, {"wspdm": "13.0", "wspdi": "8.1", "snow": "0", "date": {"pretty": "5:53 AM CDT on September 17, 2015", "year": "2015", "mday": "17", "min": "53", "hour": "05", "tzname": "America/Chicago", "mon": "09"}, "precipi": "-9999.00", "wgusti": "-9999.0", "heatindexi": "-9999", "vism": "16.1", "precipm": "-9999.00", "dewpti": "55.9", "fog": "0", "heatindexm": "-9999", "wgustm": "-9999.0", "icon": "mostlycloudy", "visi": "10.0", "windchillm": "-999", "conds": "Mostly Cloudy", "windchilli": "-999", "pressurei": "30.05", "tempm": "18.9", "hum": "70", "tempi": "66.0", "thunder": "0", "dewptm": "13.3", "wdire": "South", "utcdate": {"pretty": "10:53 AM GMT on September 17, 2015", "year": "2015", "mday": "17", "min": "53", "hour": "10", "tzname": "UTC", "mon": "09"}, "pressurem": "1017.6", "wdird": "190", "tornado": "0", "metar": "METAR KMDW 171053Z 19007KT 10SM BKN040 19/13 A3008 RMK AO2 SLP176 T01890133", "rain": "0", "hail": "0"}, {"wspdm": "16.7", "wspdi": "10.4", "snow": "0", "date": {"pretty": "6:53 AM CDT on September 17, 2015", "year": "2015", "mday": "17", "min": "53", "hour": "06", "tzname": "America/Chicago", "mon": "09"}, "precipi": "-9999.00", "wgusti": "-9999.0", "heatindexi": "-9999", "vism": "16.1", "precipm": "-9999.00", "dewpti": "55.0", "fog": "0", "heatindexm": "-9999", "wgustm": "-9999.0", "icon": "mostlycloudy", "visi": "10.0", "windchillm": "-999", "conds": "Mostly Cloudy", "windchilli": "-999", "pressurei": "30.04", "tempm": "20.0", "hum": "63", "tempi": "68.0", "thunder": "0", "dewptm": "12.8", "wdire": "South", "utcdate": {"pretty": "11:53 AM GMT on September 17, 2015", "year": "2015", "mday": "17", "min": "53", "hour": "11", "tzname": "UTC", "mon": "09"}, "pressurem": "1017.3", "wdird": "190", "tornado": "0", "metar": "METAR KMDW 171153Z 19009KT 10SM BKN038 20/13 A3007 RMK AO2 SLP173 T02000128 10211 20189 58006", "rain": "0", "hail": "0"}, {"wspdm": "14.8", "wspdi": "9.2", "snow": "0", "date": {"pretty": "7:53 AM CDT on September 17, 2015", "year": "2015", "mday": "17", "min": "53", "hour": "07", "tzname": "America/Chicago", "mon": "09"}, "precipi": "-9999.00", "wgusti": "17.3", "heatindexi": "-9999", "vism": "16.1", "precipm": "-9999.00", "dewpti": "55.9", "fog": "0", "heatindexm": "-9999", "wgustm": "27.8", "icon": "partlycloudy", "visi": "10.0", "windchillm": "-999", "conds": "Scattered Clouds", "windchilli": "-999", "pressurei": "30.04", "tempm": "20.6", "hum": "63", "tempi": "69.1", "thunder": "0", "dewptm": "13.3", "wdire": "South", "utcdate": {"pretty": "12:53 PM GMT on September 17, 2015", "year": "2015", "mday": "17", "min": "53", "hour": "12", "tzname": "UTC", "mon": "09"}, "pressurem": "1017.0", "wdird": "190", "tornado": "0", "metar": "METAR KMDW 171253Z 19008G15KT 10SM SCT047 21/13 A3006 RMK AO2 SLP170 T02060133", "rain": "0", "hail": "0"}, {"wspdm": "18.5", "wspdi": "11.5", "snow": "0", "date": {"pretty": "8:53 AM CDT on September 17, 2015", "year": "2015", "mday": "17", "min": "53", "hour": "08", "tzname": "America/Chicago", "mon": "09"}, "precipi": "-9999.00", "wgusti": "21.9", "heatindexi": "-9999", "vism": "16.1", "precipm": "-9999.00", "dewpti": "57.0", "fog": "0", "heatindexm": "-9999", "wgustm": "35.2", "icon": "mostlycloudy", "visi": "10.0", "windchillm": "-999", "conds": "Mostly Cloudy", "windchilli": "-999", "pressurei": "30.03", "tempm": "22.2", "hum": "59", "tempi": "72.0", "thunder": "0", "dewptm": "13.9", "wdire": "South", "utcdate": {"pretty": "1:53 PM GMT on September 17, 2015", "year": "2015", "mday": "17", "min": "53", "hour": "13", "tzname": "UTC", "mon": "09"}, "pressurem": "1016.8", "wdird": "190", "tornado": "0", "metar": "METAR KMDW 171353Z 19010G19KT 10SM SCT039 BKN055 22/14 A3005 RMK AO2 SLP168 T02220139", "rain": "0", "hail": "0"}, {"wspdm": "20.4", "wspdi": "12.7", "snow": "0", "date": {"pretty": "9:53 AM CDT on September 17, 2015", "year": "2015", "mday": "17", "min": "53", "hour": "09", "tzname": "America/Chicago", "mon": "09"}, "precipi": "-9999.00", "wgusti": "19.6", "heatindexi": "-9999", "vism": "16.1", "precipm": "-9999.00", "dewpti": "57.9", "fog": "0", "heatindexm": "-9999", "wgustm": "31.5", "icon": "partlycloudy", "visi": "10.0", "windchillm": "-999", "conds": "Scattered Clouds", "windchilli": "-999", "pressurei": "30.01", "tempm": "23.9", "hum": "55", "tempi": "75.0", "thunder": "0", "dewptm": "14.4", "wdire": "South", "utcdate": {"pretty": "2:53 PM GMT on September 17, 2015", "year": "2015", "mday": "17", "min": "53", "hour": "14", "tzname": "UTC", "mon": "09"}, "pressurem": "1016.3", "wdird": "180", "tornado": "0", "metar": "METAR KMDW 171453Z 18011G17KT 10SM FEW036 SCT050 24/14 A3004 RMK AO2 SLP163 T02390144 58009", "rain": "0", "hail": "0"}, {"wspdm": "24.1", "wspdi": "15.0", "snow": "0", "date": {"pretty": "10:53 AM CDT on September 17, 2015", "year": "2015", "mday": "17", "min": "53", "hour": "10", "tzname": "America/Chicago", "mon": "09"}, "precipi": "-9999.00", "wgusti": "24.2", "heatindexi": "-9999", "vism": "16.1", "precipm": "-9999.00", "dewpti": "60.1", "fog": "0", "heatindexm": "-9999", "wgustm": "38.9", "icon": "partlycloudy", "visi": "10.0", "windchillm": "-999", "conds": "Partly Cloudy", "windchilli": "-999", "pressurei": "29.99", "tempm": "25.6", "hum": "54", "tempi": "78.1", "thunder": "0", "dewptm": "15.6", "wdire": "South", "utcdate": {"pretty": "3:53 PM GMT on September 17, 2015", "year": "2015", "mday": "17", "min": "53", "hour": "15", "tzname": "UTC", "mon": "09"}, "pressurem": "1015.6", "wdird": "180", "tornado": "0", "metar": "METAR KMDW 171553Z 18013G21KT 10SM FEW041 26/16 A3002 RMK AO2 SLP156 T02560156", "rain": "0", "hail": "0"}, {"wspdm": "24.1", "wspdi": "15.0", "snow": "0", "date": {"pretty": "11:53 AM CDT on September 17, 2015", "year": "2015", "mday": "17", "min": "53", "hour": "11", "tzname": "America/Chicago", "mon": "09"}, "precipi": "-9999.00", "wgusti": "29.9", "heatindexi": "82.7", "vism": "16.1", "precipm": "-9999.00", "dewpti": "61.0", "fog": "0", "heatindexm": "28.1", "wgustm": "48.2", "icon": "partlycloudy", "visi": "10.0", "windchillm": "-999", "conds": "Partly Cloudy", "windchilli": "-999", "pressurei": "29.97", "tempm": "27.8", "hum": "49", "tempi": "82.0", "thunder": "0", "dewptm": "16.1", "wdire": "South", "utcdate": {"pretty": "4:53 PM GMT on September 17, 2015", "year": "2015", "mday": "17", "min": "53", "hour": "16", "tzname": "UTC", "mon": "09"}, "pressurem": "1014.9", "wdird": "180", "tornado": "0", "metar": "METAR KMDW 171653Z 18013G26KT 10SM FEW037 FEW250 28/16 A3000 RMK AO2 PK WND 16026/1650 SLP149 T02780161", "rain": "0", "hail": "0"}, {"wspdm": "20.4", "wspdi": "12.7", "snow": "0", "date": {"pretty": "12:53 PM CDT on September 17, 2015", "year": "2015", "mday": "17", "min": "53", "hour": "12", "tzname": "America/Chicago", "mon": "09"}, "precipi": "-9999.00", "wgusti": "24.2", "heatindexi": "84.5", "vism": "16.1", "precipm": "-9999.00", "dewpti": "62.1", "fog": "0", "heatindexm": "29.2", "wgustm": "38.9", "icon": "partlycloudy", "visi": "10.0", "windchillm": "-999", "conds": "Partly Cloudy", "windchilli": "-999", "pressurei": "29.96", "tempm": "28.9", "hum": "47", "tempi": "84.0", "thunder": "0", "dewptm": "16.7", "wdire": "South", "utcdate": {"pretty": "5:53 PM GMT on September 17, 2015", "year": "2015", "mday": "17", "min": "53", "hour": "17", "tzname": "UTC", "mon": "09"}, "pressurem": "1014.4", "wdird": "190", "tornado": "0", "metar": "METAR KMDW 171753Z 19011G21KT 10SM FEW037 FEW250 29/17 A2998 RMK AO2 SLP144 T02890167 10289 20200 56018", "rain": "0", "hail": "0"}, {"wspdm": "24.1", "wspdi": "15.0", "snow": "0", "date": {"pretty": "1:53 PM CDT on September 17, 2015", "year": "2015", "mday": "17", "min": "53", "hour": "13", "tzname": "America/Chicago", "mon": "09"}, "precipi": "-9999.00", "wgusti": "25.3", "heatindexi": "85.9", "vism": "16.1", "precipm": "-9999.00", "dewpti": "63.0", "fog": "0", "heatindexm": "29.9", "wgustm": "40.7", "icon": "partlycloudy", "visi": "10.0", "windchillm": "-999", "conds": "Scattered Clouds", "windchilli": "-999", "pressurei": "29.95", "tempm": "29.4", "hum": "48", "tempi": "84.9", "thunder": "0", "dewptm": "17.2", "wdire": "South", "utcdate": {"pretty": "6:53 PM GMT on September 17, 2015", "year": "2015", "mday": "17", "min": "53", "hour": "18", "tzname": "UTC", "mon": "09"}, "pressurem": "1014.2", "wdird": "180", "tornado": "0", "metar": "METAR KMDW 171853Z 18013G22KT 10SM FEW045 SCT070 SCT250 29/17 A2998 RMK AO2 SLP142 T02940172", "rain": "0", "hail": "0"}, {"wspdm": "25.9", "wspdi": "16.1", "snow": "0", "date": {"pretty": "2:53 PM CDT on September 17, 2015", "year": "2015", "mday": "17", "min": "53", "hour": "14", "tzname": "America/Chicago", "mon": "09"}, "precipi": "-9999.00", "wgusti": "26.5", "heatindexi": "86.8", "vism": "16.1", "precipm": "-9999.00", "dewpti": "63.0", "fog": "0", "heatindexm": "30.5", "wgustm": "42.6", "icon": "mostlycloudy", "visi": "10.0", "windchillm": "-999", "conds": "Mostly Cloudy", "windchilli": "-999", "pressurei": "29.91", "tempm": "30.0", "hum": "46", "tempi": "86.0", "thunder": "0", "dewptm": "17.2", "wdire": "South", "utcdate": {"pretty": "7:53 PM GMT on September 17, 2015", "year": "2015", "mday": "17", "min": "53", "hour": "19", "tzname": "UTC", "mon": "09"}, "pressurem": "1012.7", "wdird": "190", "tornado": "0", "metar": "METAR KMDW 171953Z 19014G23KT 10SM FEW049 SCT070 BKN250 30/17 A2994 RMK AO2 SLP127 T03000172", "rain": "0", "hail": "0"}, {"wspdm": "18.5", "wspdi": "11.5", "snow": "0", "date": {"pretty": "3:53 PM CDT on September 17, 2015", "year": "2015", "mday": "17", "min": "53", "hour": "15", "tzname": "America/Chicago", "mon": "09"}, "precipi": "-9999.00", "wgusti": "23.0", "heatindexi": "86.8", "vism": "16.1", "precipm": "-9999.00", "dewpti": "63.0", "fog": "0", "heatindexm": "30.5", "wgustm": "37.0", "icon": "mostlycloudy", "visi": "10.0", "windchillm": "-999", "conds": "Mostly Cloudy", "windchilli": "-999", "pressurei": "29.89", "tempm": "30.0", "hum": "46", "tempi": "86.0", "thunder": "0", "dewptm": "17.2", "wdire": "SSW", "utcdate": {"pretty": "8:53 PM GMT on September 17, 2015", "year": "2015", "mday": "17", "min": "53", "hour": "20", "tzname": "UTC", "mon": "09"}, "pressurem": "1012.2", "wdird": "200", "tornado": "0", "metar": "METAR KMDW 172053Z 20010G20KT 10SM FEW050 SCT100 BKN150 30/17 A2992 RMK AO2 SLP122 T03000172 58021", "rain": "0", "hail": "0"}, {"wspdm": "22.2", "wspdi": "13.8", "snow": "0", "date": {"pretty": "4:53 PM CDT on September 17, 2015", "year": "2015", "mday": "17", "min": "53", "hour": "16", "tzname": "America/Chicago", "mon": "09"}, "precipi": "-9999.00", "wgusti": "-9999.0", "heatindexi": "85.9", "vism": "16.1", "precipm": "-9999.00", "dewpti": "63.0", "fog": "0", "heatindexm": "29.9", "wgustm": "-9999.0", "icon": "mostlycloudy", "visi": "10.0", "windchillm": "-999", "conds": "Mostly Cloudy", "windchilli": "-999", "pressurei": "29.90", "tempm": "29.4", "hum": "48", "tempi": "84.9", "thunder": "0", "dewptm": "17.2", "wdire": "SSW", "utcdate": {"pretty": "9:53 PM GMT on September 17, 2015", "year": "2015", "mday": "17", "min": "53", "hour": "21", "tzname": "UTC", "mon": "09"}, "pressurem": "1012.3", "wdird": "210", "tornado": "0", "metar": "METAR KMDW 172153Z 21012KT 10SM SCT050 SCT100 BKN150 BKN250 29/17 A2992 RMK AO2 SLP123 T02940172", "rain": "0", "hail": "0"}, {"wspdm": "18.5", "wspdi": "11.5", "snow": "0", "date": {"pretty": "5:06 PM CDT on September 17, 2015", "year": "2015", "mday": "17", "min": "06", "hour": "17", "tzname": "America/Chicago", "mon": "09"}, "precipi": "-9999.00", "wgusti": "24.2", "heatindexi": "85.9", "vism": "16.1", "precipm": "-9999.00", "dewpti": "63.0", "fog": "0", "heatindexm": "29.9", "wgustm": "38.9", "icon": "tstorms", "visi": "10.0", "windchillm": "-999", "conds": "Thunderstorm", "windchilli": "-999", "pressurei": "29.92", "tempm": "29.4", "hum": "48", "tempi": "84.9", "thunder": "1", "dewptm": "17.2", "wdire": "SSW", "utcdate": {"pretty": "10:06 PM GMT on September 17, 2015", "year": "2015", "mday": "17", "min": "06", "hour": "22", "tzname": "UTC", "mon": "09"}, "pressurem": "1013.1", "wdird": "210", "tornado": "0", "metar": "SPECI KMDW 172206Z 21010G21KT 10SM TS SCT050CB SCT085 BKN130 BKN250 29/17 A2992 RMK AO2 TSB05 OCNL LTGICCG VC W-N TS VC W-N MOV E T02940172", "rain": "0", "hail": "0"}, {"wspdm": "5.6", "wspdi": "3.5", "snow": "0", "date": {"pretty": "5:25 PM CDT on September 17, 2015", "year": "2015", "mday": "17", "min": "25", "hour": "17", "tzname": "America/Chicago", "mon": "09"}, "precipi": "0.04", "wgusti": "-9999.0", "heatindexi": "-9999", "vism": "4.0", "precipm": "1.0", "dewpti": "62.1", "fog": "0", "heatindexm": "-9999", "wgustm": "-9999.0", "icon": "tstorms", "visi": "2.5", "windchillm": "-999", "conds": "Light Thunderstorms and Rain", "windchilli": "-999", "pressurei": "29.93", "tempm": "25.0", "hum": "60", "tempi": "77.0", "thunder": "1", "dewptm": "16.7", "wdire": "Variable", "utcdate": {"pretty": "10:25 PM GMT on September 17, 2015", "year": "2015", "mday": "17", "min": "25", "hour": "22", "tzname": "UTC", "mon": "09"}, "pressurem": "1013.4", "wdird": "0", "tornado": "0", "metar": "SPECI KMDW 172225Z VRB03KT 2 1/2SM -TSRA SCT050CB BKN085 BKN130 BKN250 25/17 A2993 RMK AO2 RAB22 TSB05 FRQ LTGICCG OHD TS OHD MOV E P0004 T02500167", "rain": "1", "hail": "0"}, {"wspdm": "11.1", "wspdi": "6.9", "snow": "0", "date": {"pretty": "5:36 PM CDT on September 17, 2015", "year": "2015", "mday": "17", "min": "36", "hour": "17", "tzname": "America/Chicago", "mon": "09"}, "precipi": "0.20", "wgusti": "-9999.0", "heatindexi": "-9999", "vism": "14.5", "precipm": "5.1", "dewpti": "64.9", "fog": "0", "heatindexm": "-9999", "wgustm": "-9999.0", "icon": "tstorms", "visi": "9.0", "windchillm": "-999", "conds": "Light Thunderstorms and Rain", "windchilli": "-999", "pressurei": "29.90", "tempm": "23.3", "hum": "73", "tempi": "73.9", "thunder": "1", "dewptm": "18.3", "wdire": "ESE", "utcdate": {"pretty": "10:36 PM GMT on September 17, 2015", "year": "2015", "mday": "17", "min": "36", "hour": "22", "tzname": "UTC", "mon": "09"}, "pressurem": "1012.4", "wdird": "120", "tornado": "0", "metar": "SPECI KMDW 172236Z 12006KT 9SM R31C/3500VP6000FT -TSRA SCT028 BKN050CB OVC110 23/18 A2990 RMK AO2 RAB22 TSB05 FRQ LTGICCG OHD TS OHD MOV E P0020 T02330183", "rain": "1", "hail": "0"}, {"wspdm": "13.0", "wspdi": "8.1", "snow": "0", "date": {"pretty": "5:53 PM CDT on September 17, 2015", "year": "2015", "mday": "17", "min": "53", "hour": "17", "tzname": "America/Chicago", "mon": "09"}, "precipi": "0.20", "wgusti": "-9999.0", "heatindexi": "-9999", "vism": "14.5", "precipm": "5.1", "dewpti": "66.9", "fog": "0", "heatindexm": "-9999", "wgustm": "-9999.0", "icon": "tstorms", "visi": "9.0", "windchillm": "-999", "conds": "Light Thunderstorms and Rain", "windchilli": "-999", "pressurei": "29.88", "tempm": "25.6", "hum": "68", "tempi": "78.1", "thunder": "1", "dewptm": "19.4", "wdire": "SSE", "utcdate": {"pretty": "10:53 PM GMT on September 17, 2015", "year": "2015", "mday": "17", "min": "53", "hour": "22", "tzname": "UTC", "mon": "09"}, "pressurem": "1011.7", "wdird": "150", "tornado": "0", "metar": "METAR KMDW 172253Z 15007KT 9SM -TSRA FEW027 SCT050CB BKN090 OVC150 26/19 A2990 RMK AO2 RAB22 TSB05 SLP117 OCNL LTGICCG VC NE-SE TS NE-SE MOV E P0020 T02560194", "rain": "1", "hail": "0"}, {"wspdm": "16.7", "wspdi": "10.4", "snow": "0", "date": {"pretty": "6:02 PM CDT on September 17, 2015", "year": "2015", "mday": "17", "min": "02", "hour": "18", "tzname": "America/Chicago", "mon": "09"}, "precipi": "0.00", "wgusti": "-9999.0", "heatindexi": "83.3", "vism": "16.1", "precipm": "0.0", "dewpti": "66.9", "fog": "0", "heatindexm": "28.5", "wgustm": "-9999.0", "icon": "rain", "visi": "10.0", "windchillm": "-999", "conds": "Light Rain", "windchilli": "-999", "pressurei": "29.89", "tempm": "27.2", "hum": "62", "tempi": "81.0", "thunder": "0", "dewptm": "19.4", "wdire": "SSE", "utcdate": {"pretty": "11:02 PM GMT on September 17, 2015", "year": "2015", "mday": "17", "min": "02", "hour": "23", "tzname": "UTC", "mon": "09"}, "pressurem": "1012.1", "wdird": "160", "tornado": "0", "metar": "SPECI KMDW 172302Z 16009KT 10SM -RA FEW030 FEW060 BKN100 OVC150 27/19 A2989 RMK AO2 TSE01 P0000 T02720194", "rain": "1", "hail": "0"}, {"wspdm": "22.2", "wspdi": "13.8", "snow": "0", "date": {"pretty": "6:53 PM CDT on September 17, 2015", "year": "2015", "mday": "17", "min": "53", "hour": "18", "tzname": "America/Chicago", "mon": "09"}, "precipi": "0.01", "wgusti": "23.0", "heatindexi": "83.4", "vism": "16.1", "precipm": "0.3", "dewpti": "64.0", "fog": "0", "heatindexm": "28.6", "wgustm": "37.0", "icon": "cloudy", "visi": "10.0", "windchillm": "-999", "conds": "Overcast", "windchilli": "-999", "pressurei": "29.86", "tempm": "27.8", "hum": "54", "tempi": "82.0", "thunder": "0", "dewptm": "17.8", "wdire": "SSE", "utcdate": {"pretty": "11:53 PM GMT on September 17, 2015", "year": "2015", "mday": "17", "min": "53", "hour": "23", "tzname": "UTC", "mon": "09"}, "pressurem": "1011.1", "wdird": "160", "tornado": "0", "metar": "METAR KMDW 172353Z 16012G20KT 10SM FEW060 SCT100 BKN140 OVC250 28/18 A2988 RMK AO2 RAE04 TSE01 SLP111 P0001 60021 T02780178 10306 20233 58012", "rain": "0", "hail": "0"}, {"wspdm": "22.2", "wspdi": "13.8", "snow": "0", "date": {"pretty": "7:53 PM CDT on September 17, 2015", "year": "2015", "mday": "17", "min": "53", "hour": "19", "tzname": "America/Chicago", "mon": "09"}, "precipi": "-9999.00", "wgusti": "-9999.0", "heatindexi": "82.2", "vism": "16.1", "precipm": "-9999.00", "dewpti": "63.0", "fog": "0", "heatindexm": "27.9", "wgustm": "-9999.0", "icon": "mostlycloudy", "visi": "10.0", "windchillm": "-999", "conds": "Mostly Cloudy", "windchilli": "-999", "pressurei": "29.86", "tempm": "27.2", "hum": "54", "tempi": "81.0", "thunder": "0", "dewptm": "17.2", "wdire": "South", "utcdate": {"pretty": "12:53 AM GMT on September 18, 2015", "year": "2015", "mday": "18", "min": "53", "hour": "00", "tzname": "UTC", "mon": "09"}, "pressurem": "1011.1", "wdird": "170", "tornado": "0", "metar": "METAR KMDW 180053Z 17012KT 10SM SCT120 BKN150 27/17 A2988 RMK AO2 SLP111 T02720172", "rain": "0", "hail": "0"}, {"wspdm": "24.1", "wspdi": "15.0", "snow": "0", "date": {"pretty": "8:53 PM CDT on September 17, 2015", "year": "2015", "mday": "17", "min": "53", "hour": "20", "tzname": "America/Chicago", "mon": "09"}, "precipi": "-9999.00", "wgusti": "-9999.0", "heatindexi": "81.5", "vism": "16.1", "precipm": "-9999.00", "dewpti": "63.0", "fog": "0", "heatindexm": "27.5", "wgustm": "-9999.0", "icon": "mostlycloudy", "visi": "10.0", "windchillm": "-999", "conds": "Mostly Cloudy", "windchilli": "-999", "pressurei": "29.84", "tempm": "26.7", "hum": "56", "tempi": "80.1", "thunder": "0", "dewptm": "17.2", "wdire": "South", "utcdate": {"pretty": "1:53 AM GMT on September 18, 2015", "year": "2015", "mday": "18", "min": "53", "hour": "01", "tzname": "UTC", "mon": "09"}, "pressurem": "1010.4", "wdird": "180", "tornado": "0", "metar": "METAR KMDW 180153Z 18013KT 10SM FEW070 FEW095 SCT120 BKN150 27/17 A2987 RMK AO2 SLP104 T02670172", "rain": "0", "hail": "0"}, {"wspdm": "29.6", "wspdi": "18.4", "snow": "0", "date": {"pretty": "9:53 PM CDT on September 17, 2015", "year": "2015", "mday": "17", "min": "53", "hour": "21", "tzname": "America/Chicago", "mon": "09"}, "precipi": "0.02", "wgusti": "24.2", "heatindexi": "-9999", "vism": "14.5", "precipm": "0.5", "dewpti": "64.0", "fog": "0", "heatindexm": "-9999", "wgustm": "38.9", "icon": "rain", "visi": "9.0", "windchillm": "-999", "conds": "Light Rain", "windchilli": "-999", "pressurei": "29.85", "tempm": "25.6", "hum": "62", "tempi": "78.1", "thunder": "0", "dewptm": "17.8", "wdire": "South", "utcdate": {"pretty": "2:53 AM GMT on September 18, 2015", "year": "2015", "mday": "18", "min": "53", "hour": "02", "tzname": "UTC", "mon": "09"}, "pressurem": "1010.6", "wdird": "180", "tornado": "0", "metar": "METAR KMDW 180253Z 18016G21KT 9SM -RA FEW047 BKN095 OVC110 26/18 A2987 RMK AO2 RAB47 SLP106 FRQ LTGICCG DSNT N CB DSNT N P0002 60002 T02560178 55004", "rain": "1", "hail": "0"}, {"wspdm": "27.8", "wspdi": "17.3", "snow": "0", "date": {"pretty": "10:02 PM CDT on September 17, 2015", "year": "2015", "mday": "17", "min": "02", "hour": "22", "tzname": "America/Chicago", "mon": "09"}, "precipi": "0.03", "wgusti": "24.2", "heatindexi": "-9999", "vism": "14.5", "precipm": "0.8", "dewpti": "64.0", "fog": "0", "heatindexm": "-9999", "wgustm": "38.9", "icon": "tstorms", "visi": "9.0", "windchillm": "-999", "conds": "Light Thunderstorms and Rain", "windchilli": "-999", "pressurei": "29.87", "tempm": "25.0", "hum": "64", "tempi": "77.0", "thunder": "1", "dewptm": "17.8", "wdire": "South", "utcdate": {"pretty": "3:02 AM GMT on September 18, 2015", "year": "2015", "mday": "18", "min": "02", "hour": "03", "tzname": "UTC", "mon": "09"}, "pressurem": "1011.4", "wdird": "180", "tornado": "0", "metar": "SPECI KMDW 180302Z 18015G21KT 9SM -TSRA SCT045CB SCT095 OVC110 25/18 A2987 RMK AO2 TSB01 FRQ LTGICCG VC N TS VC N MOV E P0003 T02500178", "rain": "1", "hail": "0"}, {"wspdm": "27.8", "wspdi": "17.3", "snow": "0", "date": {"pretty": "10:40 PM CDT on September 17, 2015", "year": "2015", "mday": "17", "min": "40", "hour": "22", "tzname": "America/Chicago", "mon": "09"}, "precipi": "0.03", "wgusti": "27.6", "heatindexi": "-9999", "vism": "16.1", "precipm": "0.8", "dewpti": "64.0", "fog": "0", "heatindexm": "-9999", "wgustm": "44.4", "icon": "cloudy", "visi": "10.0", "windchillm": "-999", "conds": "Overcast", "windchilli": "-999", "pressurei": "29.87", "tempm": "25.6", "hum": "62", "tempi": "78.1", "thunder": "0", "dewptm": "17.8", "wdire": "SSW", "utcdate": {"pretty": "3:40 AM GMT on September 18, 2015", "year": "2015", "mday": "18", "min": "40", "hour": "03", "tzname": "UTC", "mon": "09"}, "pressurem": "1011.4", "wdird": "200", "tornado": "0", "metar": "SPECI KMDW 180340Z 20015G24KT 10SM FEW065 SCT080 OVC100 26/18 A2987 RMK AO2 RAE05 TSB01E38 FRQ LTGICCG DSNT NE CB DSNT NE P0003 T02560178", "rain": "0", "hail": "0"}, {"wspdm": "27.8", "wspdi": "17.3", "snow": "0", "date": {"pretty": "10:53 PM CDT on September 17, 2015", "year": "2015", "mday": "17", "min": "53", "hour": "22", "tzname": "America/Chicago", "mon": "09"}, "precipi": "0.03", "wgusti": "25.3", "heatindexi": "-9999", "vism": "16.1", "precipm": "0.8", "dewpti": "63.0", "fog": "0", "heatindexm": "-9999", "wgustm": "40.7", "icon": "cloudy", "visi": "10.0", "windchillm": "-999", "conds": "Overcast", "windchilli": "-999", "pressurei": "29.83", "tempm": "25.6", "hum": "60", "tempi": "78.1", "thunder": "0", "dewptm": "17.2", "wdire": "South", "utcdate": {"pretty": "3:53 AM GMT on September 18, 2015", "year": "2015", "mday": "18", "min": "53", "hour": "03", "tzname": "UTC", "mon": "09"}, "pressurem": "1010.0", "wdird": "190", "tornado": "0", "metar": "METAR KMDW 180353Z COR 19015G22KT 10SM FEW065 BKN100 OVC140 26/17 A2986 RMK AO2 RAE05 TSB01E38 SLP100 FRQ LTGICCG DSNT NE CB DSNT NE P0003 T02560172", "rain": "0", "hail": "0"}, {"wspdm": "25.9", "wspdi": "16.1", "snow": "0", "date": {"pretty": "11:53 PM CDT on September 17, 2015", "year": "2015", "mday": "17", "min": "53", "hour": "23", "tzname": "America/Chicago", "mon": "09"}, "precipi": "-9999.00", "wgusti": "-9999.0", "heatindexi": "-9999", "vism": "16.1", "precipm": "-9999.00", "dewpti": "63.0", "fog": "0", "heatindexm": "-9999", "wgustm": "-9999.0", "icon": "cloudy", "visi": "10.0", "windchillm": "-999", "conds": "Overcast", "windchilli": "-999", "pressurei": "29.81", "tempm": "25.0", "hum": "62", "tempi": "77.0", "thunder": "0", "dewptm": "17.2", "wdire": "South", "utcdate": {"pretty": "4:53 AM GMT on September 18, 2015", "year": "2015", "mday": "18", "min": "53", "hour": "04", "tzname": "UTC", "mon": "09"}, "pressurem": "1009.3", "wdird": "190", "tornado": "0", "metar": "METAR KMDW 180453Z 19014KT 10SM FEW065 FEW090 SCT120 OVC180 25/17 A2984 RMK AO2 SLP093 CONS LTGICCG DSNT NW-N-NE CB DSNT NW-N-NE T02500172", "rain": "0", "hail": "0"}], "date": {"pretty": "September 17, 2015", "year": "2015", "mday": "17", "min": "00", "hour": "12", "tzname": "America/Chicago", "mon": "09"}, "utcdate": {"pretty": "September 17, 2015", "year": "2015", "mday": "17", "min": "00", "hour": "17", "tzname": "UTC", "mon": "09"}, "dailysummary": [{"heatingdegreedays": "0", "meantempi": "77", "snow": "0", "meanwindspdi": "12", "gdegreedays": "26", "precipm": "6.60", "heatingdegreedaysnormal": "2", "mintempm": "19", "mintempi": "66", "meanpressurem": "1014", "since1sepcoolingdegreedaysnormal": "91", "maxpressurei": "30.07", "fog": "0", "monthtodatesnowfalli": "", "maxtempi": "87", "since1jancoolingdegreedaysnormal": "1001", "meandewptm": "16", "meanwindspdm": "20", "monthtodatesnowfallm": "", "since1julheatingdegreedaysnormal": "28", "meandewpti": "61", "since1julsnowfalli": "", "snowfalli": "0.00", "snowdepthm": "", "meanvism": "15", "coolingdegreedays": "12", "precipi": "0.26", "monthtodateheatingdegreedaysnormal": "23", "meanvisi": "10", "minvisi": "2", "since1sepcoolingdegreedays": "179", "maxtempm": "31", "since1julsnowfallm": "", "tornado": "0", "maxvisi": "10", "maxpressurem": "1018", "hail": "0", "maxwspdi": "21", "date": {"pretty": "12:00 PM CDT on September 17, 2015", "year": "2015", "mday": "17", "min": "00", "hour": "12", "tzname": "America/Chicago", "mon": "09"}, "snowdepthi": "", "meantempm": "25", "rain": "1", "minwspdi": "4", "monthtodatecoolingdegreedaysnormal": "91", "minvism": "4", "coolingdegreedaysnormal": "3", "minhumidity": "36", "monthtodateheatingdegreedays": "11", "since1sepheatingdegreedays": "11", "maxdewptm": "19", "mindewptm": "13", "minpressurem": "1009", "precipsource": "", "mindewpti": "55", "meanpressurei": "29.95", "since1sepheatingdegreedaysnormal": "23", "since1julheatingdegreedays": "17", "maxdewpti": "67", "meanwdird": "180", "minpressurei": "29.81", "thunder": "1", "monthtodatecoolingdegreedays": "179", "maxvism": "16", "maxwspdm": "34", "snowfallm": "0.00", "maxhumidity": "73", "meanwdire": "", "minwspdm": "6", "since1jancoolingdegreedays": "1092", "humidity": ""}]}}